Workbook

Sheet Ellora Electricity Billing
G2: Monthly Consumption & Billing
H3: ELLORA PROPERTY SERVICES PVT. LTD.
H4: Electricity Charges for the Month of Nov 2020 | P4: Partywise Electicty Cahrges
B5: Sr.no. | C5: Customer Name | D5: Hospital LT | E5: Bungalow 1 LT Panel | F5: Office Set LT Panel | G5: Police Station | H5: 8000 Sqft | I5: Restaurant | J5: Parsi | K5: Bungalow 2 LT | L5: Villa | M5: ODU | N5: Total
B6: 1 | C6: Balaji Telefilms Ltd | D6: =Summary!F17 -> 0 | E6: =Summary!H17 -> 0 | F6: =Summary!J17 -> 0 | G6: =Summary!K17 -> 73 | H6: =Summary!L17 -> 0 | I6: =Summary!M17 -> 0 | J6: =Summary!N17+Summary!O17 -> 0 | K6: =Summary!P17 -> 0 | L6: =Summary!Q17+Summary!R17 -> 0 | M6: =Summary!G17+Summary!I17+Summary!S17+Summary!T17+Summary!U17 -> 0 | N6: =SUM(D6:M6) -> 73 | P6: Daily Readings
B7: 2 | C7: Bambai Dreams Entertainment (Opc) Private Limited | D7: =Summary!F18 -> 368 | E7: =Summary!H18 -> 0 | F7: =Summary!J18 -> 0 | G7: =Summary!K18 -> 0 | H7: =Summary!L18 -> 0 | I7: =Summary!M18 -> 0 | J7: =Summary!N18+Summary!O18 -> 0 | K7: =Summary!P18 -> 0 | L7: =Summary!Q18+Summary!R18 -> 0 | M7: =Summary!G18+Summary!I18+Summary!S18+Summary!T18+Summary!U18 -> 0 | N7: =SUM(D7:M7) -> 368 | P7: Daily Readings - Makeup Room
B8: 3 | C8: Boathouse Media Private Limited | D8: =Summary!F19 -> 0 | E8: =Summary!H19 -> 620 | F8: =Summary!J19 -> 0 | G8: =Summary!K19 -> 0 | H8: =Summary!L19 -> 0 | I8: =Summary!M19 -> 0 | J8: =Summary!N19+Summary!O19 -> 0 | K8: =Summary!P19 -> 0 | L8: =Summary!Q19+Summary!R19 -> 0 | M8: =Summary!G19+Summary!I19+Summary!S19+Summary!T19+Summary!U19 -> 0 | N8: =SUM(D8:M8) -> 620 | P8: Unit Consumption Details
B9: 4 | C9: Classic Films | D9: =Summary!F20 -> 0 | E9: =Summary!H20 -> 692 | F9: =Summary!J20 -> 0 | G9: =Summary!K20 -> 0 | H9: =Summary!L20 -> 0 | I9: =Summary!M20 -> 0 | J9: =Summary!N20+Summary!O20 -> 0 | K9: =Summary!P20 -> 1954 | L9: =Summary!Q20+Summary!R20 -> 0 | M9: =Summary!G20+Summary!I20+Summary!S20+Summary!T20+Summary!U20 -> 0 | N9: =SUM(D9:M9) -> 2646 | P9: Monthly LT Panel Summary
B10: 5 | C10: Contiloe Pictures Pvt Ltd. | D10: =Summary!F21 -> 0 | E10: =Summary!H21 -> 0 | F10: =Summary!J21 -> 0 | G10: =Summary!K21 -> 0 | H10: =Summary!L21 -> 0 | I10: =Summary!M21 -> 0 | J10: =Summary!N21+Summary!O21 -> 0 | K10: =Summary!P21 -> 0 | L10: =Summary!Q21+Summary!R21 -> 0 | M10: =Summary!G21+Summary!I21+Summary!S21+Summary!T21+Summary!U21 -> 0 | N10: =SUM(D10:M10) -> 0
B11: 6 | C11: Dashmi Creations LLP | D11: =Summary!F22 -> 173 | E11: =Summary!H22 -> 116 | F11: =Summary!J22 -> 0 | G11: =Summary!K22 -> 86 | H11: =Summary!L22 -> 0 | I11: =Summary!M22 -> 39 | J11: =Summary!N22+Summary!O22 -> 0 | K11: =Summary!P22 -> 0 | L11: =Summary!Q22+Summary!R22 -> 0 | M11: =Summary!G22+Summary!I22+Summary!S22+Summary!T22+Summary!U22 -> 0 | N11: =SUM(D11:M11) -> 414
B12: 7 | C12: Essel Vision Production Ltd. | D12: =Summary!F23 -> 486 | E12: =Summary!H23 -> 0 | F12: =Summary!J23 -> 0 | G12: =Summary!K23 -> 0 | H12: =Summary!L23 -> 0 | I12: =Summary!M23 -> 0 | J12: =Summary!N23+Summary!O23 -> 0 | K12: =Summary!P23 -> 0 | L12: =Summary!Q23+Summary!R23 -> 1776 | M12: =Summary!G23+Summary!I23+Summary!S23+Summary!T23+Summary!U23 -> 304 | N12: =SUM(D12:M12) -> 2566
B13: 8 | C13: Fanboy Pictures Private Limited | D13: =Summary!F24 -> 0 | E13: =Summary!H24 -> 720 | F13: =Summary!J24 -> 47 | G13: =Summary!K24 -> 130 | H13: =Summary!L24 -> 0 | I13: =Summary!M24 -> 0 | J13: =Summary!N24+Summary!O24 -> 0 | K13: =Summary!P24 -> 0 | L13: =Summary!Q24+Summary!R24 -> 0 | M13: =Summary!G24+Summary!I24+Summary!S24+Summary!T24+Summary!U24 -> 0 | N13: =SUM(D13:M13) -> 897
B14: 9 | C14: Flying Elephant Studios Pvt.Ltd. | D14: =Summary!F25 -> 0 | E14: =Summary!H25 -> 0 | F14: =Summary!J25 -> 0 | G14: =Summary!K25 -> 0 | H14: =Summary!L25 -> 0 | I14: =Summary!M25 -> 559 | J14: =Summary!N25+Summary!O25 -> 0 | K14: =Summary!P25 -> 0 | L14: =Summary!Q25+Summary!R25 -> 0 | M14: =Summary!G25+Summary!I25+Summary!S25+Summary!T25+Summary!U25 -> 0 | N14: =SUM(D14:M14) -> 559
B15: 10 | C15: Four Lions Films Private Limited | D15: =Summary!F26 -> 0 | E15: =Summary!H26 -> 0 | F15: =Summary!J26 -> 0 | G15: =Summary!K26 -> 0 | H15: =Summary!L26 -> 0 | I15: =Summary!M26 -> 0 | J15: =Summary!N26+Summary!O26 -> 0 | K15: =Summary!P26 -> 207 | L15: =Summary!Q26+Summary!R26 -> 0 | M15: =Summary!G26+Summary!I26+Summary!S26+Summary!T26+Summary!U26 -> 0 | N15: =SUM(D15:M15) -> 207
B16: 11 | C16: Gulliver Motion Pictures LLP | D16: =Summary!F27 -> 0 | E16: =Summary!H27 -> 743 | F16: =Summary!J27 -> 0 | G16: =Summary!K27 -> 0 | H16: =Summary!L27 -> 0 | I16: =Summary!M27 -> 0 | J16: =Summary!N27+Summary!O27 -> 0 | K16: =Summary!P27 -> 0 | L16: =Summary!Q27+Summary!R27 -> 0 | M16: =Summary!G27+Summary!I27+Summary!S27+Summary!T27+Summary!U27 -> 0 | N16: =SUM(D16:M16) -> 743
B17: 12 | C17: High Rise Films Private Limited | D17: =Summary!F28 -> 0 | E17: =Summary!H28 -> 0 | F17: =Summary!J28 -> 0 | G17: =Summary!K28 -> 0 | H17: =Summary!L28 -> 0 | I17: =Summary!M28 -> 370 | J17: =Summary!N28+Summary!O28 -> 1524 | K17: =Summary!P28 -> 0 | L17: =Summary!Q28+Summary!R28 -> 0 | M17: =Summary!G28+Summary!I28+Summary!S28+Summary!T28+Summary!U28 -> 0 | N17: =SUM(D17:M17) -> 1894
B18: 13 | C18: In 10 Media Pvt.Ltd. | D18: =Summary!F29 -> 73 | E18: =Summary!H29 -> 258 | F18: =Summary!J29 -> 788 | G18: =Summary!K29 -> 0 | H18: =Summary!L29 -> 0 | I18: =Summary!M29 -> 0 | J18: =Summary!N29+Summary!O29 -> 0 | K18: =Summary!P29 -> 0 | L18: =Summary!Q29+Summary!R29 -> 0 | M18: =Summary!G29+Summary!I29+Summary!S29+Summary!T29+Summary!U29 -> 0 | N18: =SUM(D18:M18) -> 1119
B19: 14 | C19: Mahesh Pandey Production LLP | D19: =Summary!F30 -> 0 | E19: =Summary!H30 -> 432 | F19: =Summary!J30 -> 0 | G19: =Summary!K30 -> 0 | H19: =Summary!L30 -> 0 | I19: =Summary!M30 -> 0 | J19: =Summary!N30+Summary!O30 -> 0 | K19: =Summary!P30 -> 0 | L19: =Summary!Q30+Summary!R30 -> 0 | M19: =Summary!G30+Summary!I30+Summary!S30+Summary!T30+Summary!U30 -> 0 | N19: =SUM(D19:M19) -> 432
B20: 15 | C20: Maximus Films | D20: =Summary!F31 -> 0 | E20: =Summary!H31 -> 0 | F20: =Summary!J31 -> 0 | G20: =Summary!K31 -> 0 | H20: =Summary!L31 -> 0 | I20: =Summary!M31 -> 0 | J20: =Summary!N31+Summary!O31 -> 0 | K20: =Summary!P31 -> 547 | L20: =Summary!Q31+Summary!R31 -> 0 | M20: =Summary!G31+Summary!I31+Summary!S31+Summary!T31+Summary!U31 -> 0 | N20: =SUM(D20:M20) -> 547
B21: 16 | C21: Planet Marathi | D21: =Summary!F32 -> 0 | E21: =Summary!H32 -> 727 | F21: =Summary!J32 -> 0 | G21: =Summary!K32 -> 0 | H21: =Summary!L32 -> 0 | I21: =Summary!M32 -> 0 | J21: =Summary!N32+Summary!O32 -> 0 | K21: =Summary!P32 -> 0 | L21: =Summary!Q32+Summary!R32 -> 0 | M21: =Summary!G32+Summary!I32+Summary!S32+Summary!T32+Summary!U32 -> 40 | N21: =SUM(D21:M21) -> 767
... B29: 24 | C29: Vijaya Entertainment India | D29: =Summary!F40 -> 0 | E29: =Summary!H40 -> 0 | F29: =Summary!J40 -> 0 | G29: =Summary!K40 -> 35 | H29: =Summary!L40 -> 0 | I29: =Summary!M40 -> 1 | J29: =Summary!N40+Summary!O40 -> 0 | K29: =Summary!P40 -> 474 | L29: =Summary!Q40+Summary!R40 -> 923 | M29: =Summary!G40+Summary!I40+Summary!S40+Summary!T40+Summary!U40 -> 11 | N29: =SUM(D29:M29) -> 1444
B30: 25 | C30: Viniyard Films | D30: =Summary!F41 -> 0 | E30: =Summary!H41 -> 0 | F30: =Summary!J41 -> 0 | G30: 0 | H30: =Summary!L41 -> 0 | I30: =Summary!M41 -> 445 | J30: =Summary!N41+Summary!O41 -> 0 | K30: =Summary!P41 -> 0 | L30: =Summary!Q41+Summary!R41 -> 4911 | M30: =Summary!G41+Summary!I41+Summary!S41+Summary!T41+Summary!U41 -> 0 | N30: =SUM(D30:M30) -> 5356
B31: 26 | C31: White Rivers Media Solutions Private Limited | D31: =Summary!F42 -> 506 | E31: =Summary!H42 -> 0 | F31: =Summary!J42 -> 0 | G31: =Summary!K42 -> 0 | H31: =Summary!L42 -> 0 | I31: =Summary!M42 -> 0 | J31: =Summary!N42+Summary!O42 -> 0 | K31: =Summary!P42 -> 0 | L31: =Summary!Q42+Summary!R42 -> 0 | M31: =Summary!G42+Summary!I42+Summary!S42+Summary!T42+Summary!U42 -> 0 | N31: =SUM(D31:M31) -> 506
B32: 27 | D32: =Summary!F43 -> 0 | E32: =Summary!H43 -> 0 | F32: =Summary!J43 -> 0 | G32: =Summary!K43 -> 0 | H32: =Summary!L43 -> 0 | I32: =Summary!M43 -> 0 | J32: =Summary!N43+Summary!O43 -> 0 | K32: =Summary!P43 -> 0 | L32: =Summary!Q43+Summary!R43 -> 0 | M32: =Summary!G43+Summary!I43+Summary!S43+Summary!T43+Summary!U43 -> 0 | N32: =SUM(D32:M32) -> 0
B33: 28 | D33: =Summary!F44 -> 0 | E33: =Summary!H44 -> 0 | F33: =Summary!J44 -> 0 | G33: =Summary!K44 -> 0 | H33: =Summary!L44 -> 0 | I33: =Summary!M44 -> 0 | J33: =Summary!N44+Summary!O44 -> 0 | K33: =Summary!P44 -> 0 | L33: =Summary!Q44+Summary!R44 -> 0 | M33: =Summary!G44+Summary!I44+Summary!S44+Summary!T44+Summary!U44 -> 0 | N33: =SUM(D33:M33) -> 0
B34: 29 | D34: =Summary!F45 -> 0 | E34: =Summary!H45 -> 0 | F34: =Summary!J45 -> 0 | G34: =Summary!K45 -> 0 | H34: =Summary!L45 -> 0 | I34: =Summary!M45 -> 0 | J34: =Summary!N45+Summary!O45 -> 0 | K34: =Summary!P45 -> 0 | L34: =Summary!Q45+Summary!R45 -> 0 | M34: =Summary!G45+Summary!I45+Summary!S45+Summary!T45+Summary!U45 -> 0 | N34: =SUM(D34:M34) -> 0
B35: 30 | D35: =Summary!F46 -> 0 | E35: =Summary!H46 -> 0 | F35: =Summary!J46 -> 0 | G35: =Summary!K46 -> 0 | H35: =Summary!L46 -> 0 | I35: =Summary!M46 -> 0 | J35: =Summary!N46+Summary!O46 -> 0 | K35: =Summary!P46 -> 0 | L35: =Summary!Q46+Summary!R46 -> 0 | M35: =Summary!G46+Summary!I46+Summary!S46+Summary!T46+Summary!U46 -> 0 | N35: =SUM(D35:M35) -> 0
B36: 31 | D36: =Summary!F47 -> 0 | E36: =Summary!H47 -> 0 | F36: =Summary!J47 -> 0 | G36: =Summary!K47 -> 0 | H36: =Summary!L47 -> 0 | I36: =Summary!M47 -> 0 | J36: =Summary!N47+Summary!O47 -> 0 | K36: =Summary!P47 -> 0 | L36: =Summary!Q47+Summary!R47 -> 0 | M36: =Summary!G47+Summary!I47+Summary!S47+Summary!T47+Summary!U47 -> 0 | N36: =SUM(D36:M36) -> 0
B37: 32 | D37: =Summary!F48 -> 0 | E37: =Summary!H48 -> 0 | F37: =Summary!J48 -> 0 | G37: =Summary!K48 -> 0 | H37: =Summary!L48 -> 0 | I37: =Summary!M48 -> 0 | J37: =Summary!N48+Summary!O48 -> 0 | K37: =Summary!P48 -> 0 | L37: =Summary!Q48+Summary!R48 -> 0 | M37: =Summary!G48+Summary!I48+Summary!S48+Summary!T48+Summary!U48 -> 0 | N37: =SUM(D37:M37) -> 0
B38: 33 | D38: =Summary!F49 -> 0 | E38: =Summary!H49 -> 0 | F38: =Summary!J49 -> 0 | G38: =Summary!K49 -> 0 | H38: =Summary!L49 -> 0 | I38: =Summary!M49 -> 0 | J38: =Summary!N49+Summary!O49 -> 0 | K38: =Summary!P49 -> 0 | L38: =Summary!Q49+Summary!R49 -> 0 | M38: =Summary!G49+Summary!I49+Summary!S49+Summary!T49+Summary!U49 -> 0 | N38: =SUM(D38:M38) -> 0
B39: 34 | D39: =Summary!F50 -> 0 | E39: =Summary!H50 -> 0 | F39: =Summary!J50 -> 0 | G39: =Summary!K50 -> 0 | H39: =Summary!L50 -> 0 | I39: =Summary!M50 -> 0 | J39: =Summary!N50+Summary!O50 -> 0 | K39: =Summary!P50 -> 0 | L39: =Summary!Q50+Summary!R50 -> 0 | M39: =Summary!G50+Summary!I50+Summary!S50+Summary!T50+Summary!U50 -> 0 | N39: =SUM(D39:M39) -> 0
B40: 35 | D40: =Summary!F51 -> 0 | E40: =Summary!H51 -> 0 | F40: =Summary!J51 -> 0 | G40: =Summary!K51 -> 0 | H40: =Summary!L51 -> 0 | I40: =Summary!M51 -> 0 | J40: =Summary!N51+Summary!O51 -> 0 | K40: =Summary!P51 -> 0 | L40: =Summary!Q51+Summary!R51 -> 0 | M40: =Summary!G51+Summary!I51+Summary!S51+Summary!T51+Summary!U51 -> 0 | N40: =SUM(D40:M40) -> 0
B41: 36
B42: 37
C44: Total | D44: =SUM(D6:D43) -> 2163 | E44: =SUM(E6:E43) -> 4921 | F44: =SUM(F6:F43) -> 1665 | G44: =SUM(G6:G43) -> 584 | H44: =SUM(H6:H43) -> 961 | I44: =SUM(I6:I43) -> 1646 | J44: =SUM(J6:J43) -> 1524 | K44: =SUM(K6:K43) -> 5142 | ... N44: =SUM(N6:N43) -> 28395 | O44: 32633
B46: Adani Billing Unit as Per Electricity Bill | N46: 45360
B48: Unit Consmption Details
B49: Sr.no. | C49: Item Description | D49: Location Name | N49: Unit | O49: Losses in %
D50: Hospital LT | E50: Bungalow 1 LT Panel | F50: Office Set LT Panel | G50: Police Station | H50: 8000 Sqft | I50: Restaurant | J50: Parsi | K50: Bungalow 2 LT | L50: Villa | M50: ODU
B51: 1 | C51: Units Billed to Parties | D51: =D44 -> 2163 | E51: =E44 -> 4921 | F51: =F44 -> 1665 | G51: =G44 -> 584 | H51: =H44 -> 961 | I51: =I44 -> 1646 | J51: =J44 -> 1524 | K51: =K44 -> 5142 | ... M51: =M44 -> 355 | N51: =SUM(D51:M51) -> 28395 | P51: DONE
B52: 2 | C52: Unit Use for Shooting Purpose | D52: =Summary!Z106 -> 600 | E52: =Summary!Z93 -> 866 | F52: =Summary!Z95 -> 2657 | G52: =Summary!Z96 -> 0 | H52: =Summary!Z97 -> 0 | I52: =Summary!Z98 -> 150 | J52: =Summary!Z99+Summary!Z100 -> 0 | K52: =Summary!Z101 -> 600 | L52: =Summary!Z103+Summary!Z104 -> 0 | M52: =Summary!Z94+Summary!Z105+Summary!Z107+Summary!Z108+Summary!Z109 -> 9 | N52: =SUM(D52:M52) -> 4882 | P52: DONE
B53: 3 | C53: Unit use by Ellora Team for Operational Purpose including Vendor Work with Makeup Rooms | N53: =Summary!T94+Summary!T95+Summary!T96+Summary!T97+Summary!T98+Summary!T99+Summary!T102+Summary!T103+Summary!T104+Summary!T105+Summary!T106+Summary!T107+Summary!T108+Summary!T109+Summary!T110+Summary!T111+Summary!T112+Summary!T113+Summary!T114+Summary!T116 -> 923 | P53: DONE
B54: 4 | C54: Unit Use for Makeup Rooms ( Un billed Unit) | N54: =Summary!G12 -> 3072 | P54: DONE
B55: 5 | C55: Unit Use for Ellora Gate Office | N55: =Summary!T101 -> 396 | P55: DONE
B56: 6 | C56: Unit Use for Electric Motor | N56: =Summary!T100 -> 871 | P56: DONE
B57: 7 | C57: Unit Use for Road Light | N57: =Summary!T115 -> 1735 | P57: DONE
C58: Non Identified Unit | N58: =N46-(SUM(N51:N57)) -> 5086 | O58: =(N58/$N$46) -> 0.11212522 | P58: DONE
C59: Unit Losses Details
B60: 1 | C60: Monthly Transformer Unit Losses | N60: ='Monthly Unit Losses'!C14 -> 3350 | O60: =(N60/$N$46) -> 0.073853616 | P60: Formula Reqd
B61: 2 | C61: Unit Consumed by Capacitor Bank | N61: ='Monthly Unit Losses'!E14 -> 64.0224 | O61: =(N61/$N$46) -> 0.0014114286 | P61: Formula Reqd
B62: 3 | C62: Main LT Panels Energy Meter loss and Cable losses | N62: ='Monthly Unit Losses'!G14 -> 598.9776 | O62: =(N62/$N$46) -> 0.013204974 | P62: Formula Reqd
B63: 4 | C63: Location LT Panels Energy Meter loss and Cable losses | N63: ='Monthly Unit Losses'!I14 -> 663 | O63: =(N63/$N$46) -> 0.014616402 | P63: Formula Reqd
C64: Grand Total of Unit Losses | N64: =SUM(N60:N63) -> 4676
B66: Difference between Adani Biling Unit and Ellora Unit consumtion Details | N66: =N46-((SUM(N51:N57))+N64) -> 410
C68: Monthly Makeup Room Details
C69: Makeup Room Details | D69: Day 1 | E69: Day 2 | F69: Day 3 | G69: Day 4 | H69: Day 5 | I69: Day 6 | J69: Day 7 | K69: Day 8 | L69: Day 9 | M69: Day 10 | N69: Day 11 | O69: Day 12 | P69: Day 13 | Q69: Day 14 | R69: Day 15 | S69: Day 16 | T69: Day 17 | U69: Day 18 | V69: Day 19 | W69: Day 20 | X69: Day 21 | Y69: Day 22 | Z69: Day 23 | AA69: Day 24 | AB69: Day 25 | AC69: Day 26 | AD69: Day 27 | AE69: Day 28 | AF69: Day 29 | AG69: Day 30 | AH69: Day 31 | AI69: Meter Wise Monthly Makeup Room Qty
D70: Total | E70: Total | F70: Total | G70: Total | H70: Total | I70: Total | J70: Total | K70: Total | L70: Total | M70: Total | N70: Total | O70: Total | P70: Total | Q70: Total | R70: Total | S70: Total | T70: Total | U70: Total | V70: Total | W70: Total | X70: Total | Y70: Total | Z70: Total | AA70: Total | AB70: Total | AC70: Total | AD70: Total | AE70: Total | AF70: Total | AG70: Total | AH70: Total
C71: Hospital Location 201 - 203 | D71: 3 | E71: 0 | F71: 3 | G71: 0 | H71: 3 | I71: 0 | J71: 1 | K71: 0 | L71: 0 | M71: 0 | N71: 0 | O71: 0 | P71: 0 | Q71: 0 | R71: 0 | S71: 3 | T71: 3 | U71: 0 | V71: 2 | W71: 0 | X71: 0 | Y71: 3 | Z71: 1 | AA71: 1 | AB71: 1 | AC71: 1 | AD71: 0 | AE71: 0 | AF71: 0 | AG71: 0 | AH71: 0 | AI71: =SUM(D71:AH71) -> 25
C72: Hospital Location 204 - 206 | D72: 0 | E72: 0 | F72: 0 | G72: 0 | H72: 0 | I72: 0 | J72: 0 | K72: 0 | L72: 0 | M72: 0 | N72: 0 | O72: 0 | P72: 0 | Q72: 0 | R72: 0 | S72: 0 | T72: 0 | U72: 0 | V72: 0 | W72: 0 | X72: 0 | Y72: 0 | Z72: 0 | AA72: 0 | AB72: 0 | AC72: 0 | AD72: 0 | AE72: 0 | AF72: 0 | AG72: 0 | AH72: 0 | AI72: =SUM(D72:AG72) -> 0
C73: Hospital Location 11 - 14 | D73: 2 | E73: 0 | F73: 3 | G73: 0 | H73: 3 | I73: 0 | J73: 2 | K73: 0 | L73: 0 | M73: 0 | N73: 0 | O73: 0 | P73: 0 | Q73: 0 | R73: 0 | S73: 3 | T73: 3 | U73: 0 | V73: 0 | W73: 0 | X73: 0 | Y73: 0 | Z73: 0 | AA73: 0 | AB73: 0 | AC73: 0 | AD73: 0 | AE73: 0 | AF73: 0 | AG73: 0 | AH73: 0 | AI73: =SUM(D73:AH73) -> 16
C74: Villa (301 - 308) | D74: 8 | E74: 7 | F74: 0 | G74: 0 | H74: 8 | I74: 0 | J74: 0 | K74: 2 | L74: 0 | M74: 3 | N74: 6 | O74: 8 | P74: 1 | Q74: 0 | R74: 4 | S74: 7 | T74: 6 | U74: 8 | V74: 8 | W74: 5 | X74: 6 | Y74: 5 | Z74: 6 | AA74: 2 | AB74: 2 | AC74: 6 | AD74: 6 | AE74: 4 | AF74: 3 | AG74: 0 | AH74: 0 | AI74: =SUM(D74:AH74) -> 121
C75: Parsi (601 -611) | D75: 0 | E75: 0 | F75: 0 | G75: 0 | H75: 0 | I75: 3 | J75: 0 | K75: 0 | L75: 0 | M75: 0 | N75: 0 | O75: 0 | P75: 0 | Q75: 0 | R75: 0 | S75: 0 | T75: 0 | U75: 0 | V75: 0 | W75: 0 | X75: 0 | Y75: 6 | Z75: 0 | AA75: 0 | AB75: 0 | AC75: 0 | AD75: 0 | AE75: 0 | AF75: 0 | AG75: 0 | AH75: 0 | AI75: =SUM(D75:AH75) -> 9
C76: 8000 sift( 401-406) | D76: 0 | E76: 0 | F76: 0 | G76: 0 | H76: 0 | I76: 0 | J76: 0 | K76: 0 | L76: 0 | M76: 0 | N76: 0 | O76: 0 | P76: 0 | Q76: 0 | R76: 0 | S76: 0 | T76: 0 | U76: 0 | V76: 0 | W76: 0 | X76: 0 | Y76: 0 | Z76: 0 | AA76: 0 | AB76: 0 | AC76: 0 | AD76: 0 | AE76: 2 | AF76: 0 | AG76: 0 | AH76: 0 | AI76: =SUM(D76:AH76) -> 2
C77: Restaurant (101 -103) | D77: 3 | E77: 2 | F77: 1 | G77: 0 | H77: 0 | I77: 0 | J77: 0 | K77: 0 | L77: 0 | M77: 3 | N77: 3 | O77: 3 | P77: 0 | Q77: 0 | R77: 0 | S77: 0 | T77: 0 | U77: 1 | V77: 3 | W77: 3 | X77: 3 | Y77: 3 | Z77: 3 | AA77: 3 | AB77: 3 | AC77: 0 | AD77: 3 | AE77: 3 | AF77: 1 | AG77: 1 | AH77: 0 | AI77: =SUM(D77:AH77) -> 45
C78: Bungalow 2 | D78: 2 | E78: 0 | F78: 1 | G78: 0 | H78: 0 | I78: 5 | J78: 1 | K78: 2 | L78: 0 | M78: 0 | N78: 7 | O78: 5 | P78: 0 | Q78: 0 | R78: 2 | S78: 10 | T78: 7 | U78: 9 | V78: 7 | W78: 1 | X78: 2 | Y78: 9 | Z78: 11 | AA78: 9 | AB78: 8 | AC78: 3 | AD78: 3 | AE78: 1 | AF78: 0 | AG78: 0 | AH78: 0 | AI78: =SUM(D78:AG78) -> 105
C79: Per Day Makeup Room Details | D79: =SUM(D71:D78) -> 18 | E79: =SUM(E71:E78) -> 9 | F79: =SUM(F71:F78) -> 8 | G79: =SUM(G71:G78) -> 0 | H79: =SUM(H71:H78) -> 14 | I79: =SUM(I71:I78) -> 8 | J79: =SUM(J71:J78) -> 4 | K79: =SUM(K71:K78) -> 4 | ... AI79: =SUM(AI71:AI78) -> 323
D80: =D79-(D92+D105) -> 2 | E80: =E79-(E92+E105) -> 2 | F80: =F79-(F92+F105) -> 0 | G80: =G79-(G92+G105) -> 0 | H80: =H79-(H92+H105) -> 2 | I80: =I79-(I92+I105) -> 0 | J80: =J79-(J92+J105) -> 0 | K80: =K79-(K92+K105) -> 2 | ... AI80: =AI79-(AI92+AI105) -> 38
C81: Monthly Billing Makeup Room Details
C82: Makeup Room Details | D82: Day 1 | E82: Day 2 | F82: Day 3 | G82: Day 4 | H82: Day 5 | I82: Day 6 | J82: Day 7 | K82: Day 8 | L82: Day 9 | M82: Day 10 | N82: Day 11 | O82: Day 12 | P82: Day 13 | Q82: Day 14 | R82: Day 15 | S82: Day 16 | T82: Day 17 | U82: Day 18 | V82: Day 19 | W82: Day 20 | X82: Day 21 | Y82: Day 22 | Z82: Day 23 | AA82: Day 24 | AB82: Day 25 | AC82: Day 26 | AD82: Day 27 | AE82: Day 28 | AF82: Day 29 | AG82: Day 30 | AH82: Day 31 | AI82: Meter Wise Monthly Makeup Room Qty
D83: Total | E83: Total | F83: Total | G83: Total | H83: Total | I83: Total | J83: Total | K83: Total | L83: Total | M83: Total | N83: Total | O83: Total | P83: Total | Q83: Total | R83: Total | S83: Total | T83: Total | U83: Total | V83: Total | W83: Total | X83: Total | Y83: Total | Z83: Total | AA83: Total | AB83: Total | AC83: Total | AD83: Total | AE83: Total | AF83: Total | AG83: Total | AH83: Total
C84: Hospital Location 201 - 203 | D84: 2 | E84: 0 | F84: 2 | G84: 0 | H84: 2 | I84: 0 | J84: 0 | K84: 0 | L84: 0 | M84: 0 | N84: 0 | O84: 0 | P84: 0 | Q84: 0 | R84: 0 | S84: 2 | T84: 2 | U84: 0 | V84: 2 | W84: 0 | X84: 0 | Y84: 1 | Z84: 1 | AA84: 1 | AB84: 1 | AC84: 1 | AD84: 0 | AE84: 0 | AF84: 0 | AG84: 0 | AH84: 0 | AI84: =SUM(D84:AH84) -> 17
C85: Hospital Location 204 - 206 | D85: 0 | E85: 0 | F85: 0 | G85: 0 | H85: 0 | I85: 0 | J85: 1 | K85: 0 | L85: 0 | M85: 0 | N85: 0 | O85: 0 | P85: 0 | Q85: 0 | R85: 0 | S85: 0 | T85: 0 | U85: 0 | V85: 0 | W85: 0 | X85: 0 | Y85: 0 | Z85: 0 | AA85: 0 | AB85: 0 | AC85: 0 | AD85: 0 | AE85: 0 | AF85: 0 | AG85: 0 | AH85: 0 | AI85: =SUM(D85:AG85) -> 1
C86: Hospital Location 11 - 14 | D86: 1 | E86: 0 | F86: 2 | G86: 0 | H86: 2 | I86: 0 | J86: 0 | K86: 0 | L86: 0 | M86: 0 | N86: 0 | O86: 0 | P86: 0 | Q86: 0 | R86: 0 | S86: 2 | T86: 2 | U86: 0 | V86: 0 | W86: 0 | X86: 0 | Y86: 0 | Z86: 0 | AA86: 0 | AB86: 0 | AC86: 0 | AD86: 0 | AE86: 0 | AF86: 0 | AG86: 0 | AH86: 0 | AI86: =SUM(D86:AH86) -> 9
C87: Villa (301 -308) | D87: 6 | E87: 5 | F87: 0 | G87: 0 | H87: 6 | I87: 0 | J87: 0 | K87: 0 | L87: 0 | M87: 1 | N87: 4 | O87: 6 | P87: 0 | Q87: 0 | R87: 2 | S87: 5 | T87: 4 | U87: 6 | V87: 6 | W87: 2 | X87: 2 | Y87: 3 | Z87: 5 | AA87: 2 | AB87: 2 | AC87: 4 | AD87: 2 | AE87: 3 | AF87: 1 | AG87: 0 | AH87: 0 | AI87: =SUM(D87:AH87) -> 77
C88: Parsi | D88: 0 | E88: 0 | F88: 0 | G88: 0 | H88: 0 | I88: 1 | J88: 0 | K88: 0 | L88: 0 | M88: 0 | N88: 0 | O88: 0 | P88: 0 | Q88: 0 | R88: 0 | S88: 0 | T88: 0 | U88: 0 | V88: 0 | W88: 0 | X88: 0 | Y88: 5 | Z88: 0 | AA88: 0 | AB88: 0 | AC88: 0 | AD88: 0 | AE88: 0 | AF88: 0 | AG88: 0 | AH88: 0 | AI88: =SUM(D88:AG88) -> 6
C89: 8000 sqft | D89: 0 | E89: 0 | F89: 0 | G89: 0 | H89: 0 | I89: 0 | J89: 0 | K89: 0 | L89: 0 | M89: 0 | N89: 0 | O89: 0 | P89: 0 | Q89: 0 | R89: 0 | S89: 0 | T89: 0 | U89: 0 | V89: 0 | W89: 0 | X89: 0 | Y89: 0 | Z89: 0 | AA89: 0 | AB89: 0 | AC89: 0 | AD89: 0 | AE89: 0 | AF89: 0 | AG89: 0 | AH89: 0 | AI89: =SUM(D89:AH89) -> 0
C90: Restaurant | D90: 2 | E90: 0 | F90: 0 | G90: 0 | H90: 0 | I90: 0 | J90: 0 | K90: 0 | L90: 0 | M90: 2 | N90: 1 | O90: 1 | P90: 0 | Q90: 0 | R90: 0 | S90: 0 | T90: 0 | U90: 0 | V90: 1 | W90: 1 | X90: 1 | Y90: 2 | Z90: 2 | AA90: 2 | AB90: 2 | AC90: 0 | AD90: 2 | AE90: 2 | AF90: 0 | AG90: 0 | AH90: 0 | AI90: =SUM(D90:AH90) -> 21
C91: Bungalow 2 | D91: 1 | E91: 0 | F91: 0 | G91: 0 | H91: 0 | I91: 3 | J91: 0 | K91: 0 | L91: 0 | M91: 0 | N91: 5 | O91: 3 | P91: 0 | Q91: 0 | R91: 0 | S91: 8 | T91: 7 | U91: 7 | V91: 5 | W91: 0 | X91: 0 | Y91: 5 | Z91: 9 | AA91: 8 | AB91: 7 | AC91: 1 | AD91: 2 | AE91: 0 | AF91: 0 | AG91: 0 | AH91: 0 | AI91: =SUM(D91:AH91) -> 71
C92: Per Day Makeup Room Details | D92: =SUM(D84:D91) -> 12 | E92: =SUM(E84:E91) -> 5 | F92: =SUM(F84:F91) -> 4 | G92: =SUM(G84:G91) -> 0 | H92: =SUM(H84:H91) -> 10 | I92: =SUM(I84:I91) -> 4 | J92: =SUM(J84:J91) -> 1 | K92: =SUM(K84:K91) -> 0 | ... AI92: =SUM(AI84:AI91) -> 202
C94: Monthly Free Makeup Room Details
C95: Makeup Room Details | D95: Day 1 | E95: Day 2 | F95: Day 3 | G95: Day 4 | H95: Day 5 | I95: Day 6 | J95: Day 7 | K95: Day 8 | L95: Day 9 | M95: Day 10 | N95: Day 11 | O95: Day 12 | P95: Day 13 | Q95: Day 14 | R95: Day 15 | S95: Day 16 | T95: Day 17 | U95: Day 18 | V95: Day 19 | W95: Day 20 | X95: Day 21 | Y95: Day 22 | Z95: Day 23 | AA95: Day 24 | AB95: Day 25 | AC95: Day 26 | AD95: Day 27 | AE95: Day 28 | AF95: Day 29 | AG95: Day 30 | AH95: Day 31 | AI95: Meter Wise Monthly Makeup Room Qty
D96: Total | E96: Total | F96: Total | G96: Total | H96: Total | I96: Total | J96: Total | K96: Total | L96: Total | M96: Total | N96: Total | O96: Total | P96: Total | Q96: Total | R96: Total | S96: Total | T96: Total | U96: Total | V96: Total | W96: Total | X96: Total | Y96: Total | Z96: Total | AA96: Total | AB96: Total | AC96: Total | AD96: Total | AE96: Total | AF96: Total | AG96: Total | AH96: Total
C97: Hospital Location 201 - 203 | D97: =D71-D84 -> 1 | E97: =E71-E84 -> 0 | F97: =F71-F84 -> 1 | G97: =G71-G84 -> 0 | H97: =H71-H84 -> 1 | I97: =I71-I84 -> 0 | J97: =J71-J84 -> 1 | K97: =K71-K84 -> 0 | ... AH97: =AH71-AH84 -> 0 | AI97: =SUM(D97:AG97) -> 8
C98: Hospital Location 204 - 206 | D98: =D72-D85 -> 0 | E98: =E72-E85 -> 0 | F98: =F72-F85 -> 0 | G98: =G72-G85 -> 0 | H98: =H72-H85 -> 0 | I98: =I72-I85 -> 0 | J98: =J72-J85 -> -1 | K98: =K72-K85 -> 0 | ... AH98: =AH72-AH85 -> 0 | AI98: =SUM(D98:AG98) -> -1
C99: Hospital Location 11 - 14 | D99: =D73-D86 -> 1 | E99: =E73-E86 -> 0 | F99: =F73-F86 -> 1 | G99: =G73-G86 -> 0 | H99: =H73-H86 -> 1 | I99: =I73-I86 -> 0 | J99: =J73-J86 -> 2 | K99: =K73-K86 -> 0 | ... AH99: =AH73-AH86 -> 0 | AI99: =SUM(D99:AG99) -> 7
C100: Villa | D100: 0 | E100: 0 | F100: 0 | G100: 0 | H100: 0 | I100: 0 | J100: 0 | K100: 0 | L100: 0 | M100: =M74-M87 -> 2 | N100: 0 | O100: 0 | P100: 0 | Q100: =Q74-Q87 -> 0 | R100: =R74-R87 -> 2 | S100: 0 | T100: 0 | U100: 0 | V100: =V74-V87 -> 2 | W100: 0 | X100: 0 | Y100: 0 | Z100: 0 | AA100: 0 | AB100: 0 | AC100: 0 | AD100: 0 | AE100: 0 | AF100: 0 | AG100: 0 | AH100: 0 | AI100: =SUM(D100:AG100) -> 6
C101: Parsi | D101: =D75-D88 -> 0 | E101: =E75-E88 -> 0 | F101: =F75-F88 -> 0 | G101: =G75-G88 -> 0 | H101: =H75-H88 -> 0 | I101: =I75-I88 -> 2 | J101: =J75-J88 -> 0 | K101: =K75-K88 -> 0 | ... AH101: =AH75-AH88 -> 0 | AI101: =SUM(D101:AG101) -> 3
C102: 8000 sqff | D102: =D76-D89 -> 0 | E102: =E76-E89 -> 0 | F102: =F76-F89 -> 0 | G102: =G76-G89 -> 0 | H102: =H76-H89 -> 0 | I102: =I76-I89 -> 0 | J102: =J76-J89 -> 0 | K102: =K76-K89 -> 0 | ... AH102: =AH76-AH89 -> 0 | AI102: =SUM(D102:AG102) -> 2
C103: Restaurant | D103: =D77-D90 -> 1 | E103: =E77-E90 -> 2 | F103: =F77-F90 -> 1 | G103: =G77-G90 -> 0 | H103: =H77-H90 -> 0 | I103: =I77-I90 -> 0 | J103: =J77-J90 -> 0 | K103: =K77-K90 -> 0 | ... AH103: =AH77-AH90 -> 0 | AI103: =SUM(D103:AG103) -> 24
C104: Bungalow 2 | D104: =D78-D91 -> 1 | E104: =E78-E91 -> 0 | F104: =F78-F91 -> 1 | G104: =G78-G91 -> 0 | H104: =H78-H91 -> 0 | I104: =I78-I91 -> 2 | J104: =J78-J91 -> 1 | K104: =K78-K91 -> 2 | ... AH104: =AH78-AH91 -> 0 | AI104: =SUM(D104:AG104) -> 34
C105: Per Day Makeup Room Details | D105: =SUM(D97:D104) -> 4 | E105: =SUM(E97:E104) -> 2 | F105: =SUM(F97:F104) -> 4 | G105: =SUM(G97:G104) -> 0 | H105: =SUM(H97:H104) -> 2 | I105: =SUM(I97:I104) -> 4 | J105: =SUM(J97:J104) -> 3 | K105: =SUM(K97:K104) -> 2 | ... AI105: =SUM(AI97:AI104) -> 83

Sheet Monthly Adani Bill Deatils
A1: Security Deposite = 14,57,750/-
A2: Month | B2: Billing Unit As per Power Supply Agency | C2: Amount As Per Below Calculation | D2: PF Incentive Amount if Maintained >= 0.995 | E2: PF Received Amount As Per Poer Supply Agency Bill | F2: PF Loss Amount
A3: 43556 | B3: =B27 -> 70560 | C3: =B50 -> 1064447.4 | D3: =(B38+B39+B40+B41+B42+B43+B45+B44)*3.5% -> 30729.965 | E3: =-(B47) -> 21949.975 | F3: =D3-E3 -> 8779.99
A4: 43586 | B4: =C27 -> 93000 | C4: =C50 -> 1372775.2 | D4: =(C38+C39+C40+C41+C42+C43+C45+C44)*3.5% -> 39948.195 | E4: =-(C47) -> 39948.195 | F4: =D4-E4 -> 0
A5: 43617 | B5: =D27 -> 63624 | C5: =D50 -> 971027.29 | D5: =(D38+D39+D40+D41+D42+D43+D45+D44)*3.5% -> 28279.097 | E5: =-(D47) -> 28279.097 | F5: =D5-E5 -> 0
A6: 43647 | B6: =E27 -> 62316 | C6: =E50 -> 955344.18 | D6: =(E38+E39+E40+E41+E42+E43+E45+E44)*3.5% -> 27825.203 | E6: =-(E47) -> 27825.203 | F6: =D6-E6 -> 0
A7: 43678 | B7: =F27 -> 59892 | C7: =F50 -> 929889.67 | D7: =(F36+F37+F38+F39+F40+F41+F43+F44)*3.5% -> 26892.725 | E7: =-(F47) -> 19187.815 | F7: =D7-E7 -> 7704.9096
A8: 43709 | B8: =G27 -> 78252 | C8: =G50 -> 1168956.1 | D8: =(G36+G37+G38+G39+G40+G41+G43+G44)*3.5% -> 33039.943 | E8: =-(G47) -> 14338.734 | F8: =D8-E8 -> 18701.209
A9: 43739 | B9: =H27 -> -3014484 | C9: =H50 -> -36745661 | D9: =(H36+H37+H38+H39+H40+H41+H43+H44)*3.5% -> -988062.08 | E9: =-(H47) -> -753576.61 | F9: =D9-E9 -> -234485.47
A10: 43770 | B10: =I27 -> 0 | C10: =I50 -> 180712.5 | D10: =(I36+I37+I38+I39+I40+I41+I43+I44)*3.5% -> 6869.45 | E10: =-(I47) -> 3812.5 | F10: =D10-E10 -> 3056.95
A11: 43800 | B11: =J27 -> 0 | C11: =J50 -> 180712.5 | D11: =(J36+J37+J38+J39+J40+J41+J43+J44)*3.5% -> 6870.5 | E11: =-(J47) -> 3812.5 | F11: =D11-E11 -> 3058
A12: 43831 | B12: =K27 -> 0 | C12: =K50 -> 180712.5 | D12: =(K37+K38+K39+K40+K41+K42+K44+K45)*3.5% -> 6871.585 | E12: =-(K47) -> 3812.5 | F12: =D12-E12 -> 3059.085
A13: 43862 | B13: =L27 -> 0 | C13: =L50 -> 180712.5 | D13: =(L38+L39+L40+L41+L42+L43+L45+L44)*3.5% -> 5337.5 | E13: =-(L47) -> 3812.5 | F13: =D13-E13 -> 1525
A14: 43891 | B14: =M27 -> 0 | C14: =M50 -> 180712.5 | D14: =(M38+M39+M40+M41+M42+M43+M45+M44)*3.5% -> 5337.5 | E14: =-(M47) -> 3812.5 | F14: =D14-E14 -> 1525
A16: Readings | B16: 43556 | C16: 43586 | D16: 43617 | E16: 43647 | F16: 43678 | G16: 43709 | H16: 43739 | I16: 43770 | J16: 43800 | K16: 43831 | L16: 43862 | M16: 43891
A17: Starting | B17: 2155.7 | C17: =B18 -> 2214.5 | D17: =C18 -> 2292 | E17: =D18 -> 2345.02 | F17: =E18 -> 2396.95 | G17: =F18 -> 2446.86 | H17: =G18 -> 2512.07 | I17: =H18 -> 0 | J17: =I18 -> 0 | ... M17: =L18 -> 0
A18: Closing | B18: 2214.5 | C18: 2292 | D18: 2345.02 | E18: 2396.95 | F18: 2446.86 | G18: 2512.07
A19: MF Value | B19: 1200 | C19: 1200 | D19: 1200 | E19: 1200 | F19: 1200 | G19: 1200 | H19: 1200 | I19: 1200 | J19: 1200 | K19: 1200 | L19: 1200 | M19: 1200
A20: Consumption | B20: =(B18-B17)*B19 -> 70560 | C20: =(C18-C17)*C19 -> 93000 | D20: =(D18-D17)*D19 -> 63624 | E20: =(E18-E17)*E19 -> 62316 | F20: =(F18-F17)*F19 -> 59892 | G20: =(G18-G17)*G19 -> 78252 | H20: =(H18-H17)*H19 -> -3014484 | I20: =(I18-I17)*I19 -> 0 | ... M20: =(M18-M17)*M19 -> 0
A22: Ellora Electricity Bill Details - Consumer No - 152283599
A23: Month | B23: 43556 | C23: 43586 | D23: 43617 | E23: 43647 | F23: 43678 | G23: 43709 | H23: 43739 | I23: 43770 | J23: 43800 | K23: 43831 | L23: 43862 | M23: 43891
A24: Tariff Cat | B24: HT II | C24: HT II | D24: HT II | E24: HT II | F24: HT II | G24: HT II | H24: HT II | I24: HT II | J24: HT II | K24: HT II | L24: HT II | M24: HT II
A25: Meter no. | B25: H952738 | C25: H952738 | D25: H952738 | E25: H952738 | F25: H952738 | G25: H952738 | H25: H952738 | I25: H952738 | J25: H952738 | K25: H952738 | L25: H952738 | M25: H952738
A26: Bill No | B26: 100398625474 | C26: 10058642815 | D26: 10003133890 | E26: 101294024800 | F26: 101294056772 | G26: 101294084308
A27: Meter Units | B27: =B20 -> 70560 | C27: =C20 -> 93000 | D27: =D20 -> 63624 | E27: =E20 -> 62316 | F27: =F20 -> 59892 | G27: =G20 -> 78252 | H27: =H20 -> -3014484 | I27: =I20 -> 0 | ... M27: =M20 -> 0
A28: 9:00 Hrs - 12:00 Hrs | B28: 12072 | C28: 15792 | D28: =28524-C28 -> 12732 | E28: 12480 | F28: 11388 | G28: 14220
A29: 18:00 Hrs - 22:00 Hrs | B29: 17220 | C29: 21264 | D29: =35280-C29 -> 14016 | E29: 14472 | F29: 13452 | G29: 17712
A30: 22:00 Hrs - 6:00 Hrs | B30: 9180 | C30: 12612 | D30: =18384-C30 -> 5772 | E30: 5976 | F30: 8064 | G30: 10452
A31: Unit Use Between (6:00 Hrs - 9:00 Hrs and 12:00 Hrs - 18:00 Hrs (No Electricity Extra Charges) | B31: =B27-(B28+B29+B30) -> 32088 | C31: =C27-(C28+C29+C30) -> 43332 | D31: =D27-(D28+D29+D30) -> 31104 | E31: =E27-(E28+E29+E30) -> 29388 | F31: =F27-(F28+F29+F30) -> 26988 | G31: =G27-(G28+G29+G30) -> 35868 | H31: =H27-(H28+H29+H30) -> -3014484 | I31: =I27-(I28+I29+I30) -> 0 | ... M31: =M27-(M28+M29+M30) -> 0
A32: Sanctioned demand | B32: 1000 | C32: 1000 | D32: 1000 | E32: 1000 | F32: 1000 | G32: 1000 | H32: 1000 | I32: 1000 | J32: 1000 | K32: 1000 | L32: 1000 | M32: 1000
A33: Maximum demand | B33: 484.4 | C33: 613.2 | D33: 400 | E33: 364.8 | F33: 404.4 | G33: 494.4
A34: PF Value | B34: 0.991 | C34: 0.995 | D34: 0.995 | E34: 0.995 | F34: 0.986 | G34: 0.977
A35: Billing amount As Per Power Supply Agency | B35: =B63 -> 1064447.4 | C35: =C63 -> 1372775.2 | D35: =D63 -> 971027.29 | E35: =E63 -> 955344.18 | F35: =F63 -> 929889.67 | G35: =G63 -> 1168956.1 | H35: =H63 -> -36745661 | I35: =I63 -> 180712.5 | ... M35: =M63 -> 180712.5
A37: Calculation | B37: 43556 | C37: 43586 | D37: 43617 | E37: 43647 | F37: 43678 | G37: 43709 | H37: 43739 | I37: 43770 | J37: 43800 | K37: 43831 | L37: 43862 | M37: 43891 | P37: =524.4*275 -> 144210 | Q37: =410.4*275 -> 112860
A38: Demand/Fixed Charge | B38: =IF(B33>500,(B33*305),(500*305)) -> 152500 | C38: =(IF(C33>500,(C33*305),(500*305))) -> 187026 | D38: =(IF(D33>500,(D33*305),(500*305))) -> 152500 | E38: =(IF(E33>500,(E33*305),(500*305))) -> 152500 | F38: =(IF(F33>500,(F33*305),(500*305))) -> 152500 | G38: =(IF(G33>500,(G33*305),(500*305))) -> 152500 | H38: =(IF(H33>500,(H33*305),(500*305))) -> 152500 | I38: =(IF(I33>500,(I33*305),(500*305))) -> 152500 | J38: =(IF(J33>500,(J33*305),(500*305))) -> 152500 | ... M38: =(IF(M33>500,(M33*305),(500*305))) -> 152500
A39: Whelling Charges | B39: =B27*0.72 -> 50803.2 | C39: =C27*0.72 -> 66960 | D39: =D27*0.72 -> 45809.28 | E39: =E27*0.72 -> 44867.52 | F39: =F27*0.72 -> 43122.24 | G39: =G27*0.72 -> 56341.44 | H39: =H27*0.72 -> -2170428.5 | I39: =I27*0.72 -> 0 | ... M39: =M27*0.72 -> 0
A40: Regulatory Asset Charge | B40: =B27*0.76 -> 53625.6 | C40: =C27*0.76 -> 70680 | D40: =D27*0.76 -> 48354.24 | E40: =E27*0.76 -> 47360.16 | F40: =F27*0.76 -> 45517.92 | G40: =G27*0.76 -> 59471.52 | H40: =H27*0.76 -> -2291007.8 | I40: =I27*0.76 -> 0 | ... M40: =M27*0.76 -> 0
A41: Energy Charges | B41: =B27*7.95 -> 560952 | C41: =C27*7.95 -> 739350 | D41: =D27*7.95 -> 505810.8 | E41: =E27*7.95 -> 495412.2 | F41: =F27*7.95 -> 476141.4 | G41: =G27*7.95 -> 622103.4 | H41: =H27*7.95 -> -23965148 | I41: =I27*7.95 -> 0 | ... M41: =M27*7.95 -> 0
A42: 9:00 Hrs - 12: Hrs | B42: =B28*0.5 -> 6036 | C42: =C28*0.5 -> 7896 | D42: =D28*0.5 -> 6366 | E42: =E28*0.5 -> 6240 | F42: =F28*0.5 -> 5694 | G42: =G28*0.5 -> 7110 | H42: =H28*0.5 -> 0 | I42: =I28*0.5 -> 0 | ... M42: =M28*0.5 -> 0
A43: 18:00 Hrs - 22:00 Hrs | B43: =B29*1 -> 17220 | C43: =C29*1 -> 21264 | D43: =D29*1 -> 14016 | E43: =E29*1 -> 14472 | F43: =F29*1 -> 13452 | G43: =G29*1 -> 17712 | H43: =H29*1 -> 0 | I43: =I29*1 -> 0 | ... M43: =M29*1 -> 0
A44: 22:00 Hrs - 6:00 Hrs | B44: =B30*(-0.75) -> -6885 | C44: =C30*(-0.75) -> -9459 | D44: =D30*(-0.75) -> -4329 | E44: =E30*(-0.75) -> -4482 | F44: =F30*(-0.75) -> -6048 | G44: =G30*(-0.75) -> -7839 | H44: =H30*(-0.75) -> 0 | I44: =I30*(-0.75) -> 0 | ... M44: =M30*(-0.75) -> 0
A45: Fuel Adjustment | B45: =B27*0.62 -> 43747.2 | C45: =C27*0.62 -> 57660 | D45: =D27*0.62 -> 39446.88 | E45: =E27*0.62 -> 38635.92 | F45: =F27*0.62 -> 37133.04 | G45: =G27*0.62 -> 48516.24 | H45: =H27*0.62 -> -1868980.1 | I45: =I27*0.62 -> 0 | ... M45: =M27*0.62 -> 0
A46: Penalty For Exceeding Contract Demand | B46: 0 | C46: 0 | D46: 0 | E46: 0 | F46: 0 | G46: 0 | H46: 0 | I46: 0 | J46: 0 | K46: 0 | L46: 0 | M46: 0
A47: PF(Incentive) | B47: =-(B38+B39+B40+B41+B42+B43+B44+B45)*2.5% -> -21949.975 | C47: =-(C38+C39+C40+C41+C42+C43+C44+C45)*3.5% -> -39948.195 | D47: =-(D38+D39+D40+D41+D42+D43+D44+D45)*3.5% -> -28279.097 | E47: =-(E38+E39+E40+E41+E42+E43+E44+E45)*3.5% -> -27825.203 | F47: =-(F38+F39+F40+F41+F42+F43+F44+F45)*2.5% -> -19187.815 | G47: =-(G38+G39+G40+G41+G42+G43+G44+G45)*1.5% -> -14338.734 | H47: =-(H38+H39+H40+H41+H42+H43+H44+H45)*2.5% -> 753576.61 | I47: =-(I38+I39+I40+I41+I42+I43+I44+I45)*2.5% -> -3812.5 | J47: =-(J38+J39+J40+J41+J42+J43+J44+J45)*2.5% -> -3812.5 | K47: =-(K38+K39+K40+K41+K42+K43+K44+K45)*2.5% -> -3812.5 | L47: =-(L38+L39+L40+L41+L42+L43+L44+L45)*2.5% -> -3812.5 | M47: =-(M38+M39+M40+M41+M42+M43+M44+M45)*2.5% -> -3812.5
A48: Electricity Duty | B48: =(B38+B39+B40+B41+B42+B43+B44+B45)*21% -> 184379.79 | C48: =(C38+C39+C40+C41+C42+C43+C44+C45)*21% -> 239689.17 | D48: =(D38+D39+D40+D41+D42+D43+D44+D45)*21% -> 169674.58 | E48: =(E38+E39+E40+E41+E42+E43+E44+E45)*21% -> 166951.22 | F48: =(F38+F39+F40+F41+F42+F43+F44+F45)*21% -> 161177.65 | G48: =(G38+G39+G40+G41+G42+G43+G44+G45)*21% -> 200742.28 | H48: =(H38+H39+H40+H41+H42+H43+H44+H45)*21% -> -6330043.5 | I48: =(I38+I39+I40+I41+I42+I43+I44+I45)*21% -> 32025 | ... M48: =(M38+M39+M40+M41+M42+M43+M44+M45)*21% -> 32025
A49: Tax | B49: =B27*0.3404 -> 24018.624 | C49: =C27*0.3404 -> 31657.2 | D49: =D27*0.3404 -> 21657.61 | E49: =E27*0.3404 -> 21212.366 | F49: =F27*0.3404 -> 20387.237 | G49: =G27*0.3404 -> 26636.981 | H49: =H27*0.3404 -> -1026130.4 | I49: =I27*0.3404 -> 0 | ... M49: =M27*0.3404 -> 0
A50: Current Month Bill amount (A) | B50: =SUM(B38:B49) -> 1064447.4 | C50: =SUM(C38:C49) -> 1372775.2 | D50: =SUM(D38:D49) -> 971027.29 | E50: =SUM(E38:E49) -> 955344.18 | F50: =SUM(F38:F49) -> 929889.67 | G50: =SUM(G38:G49) -> 1168956.1 | H50: =SUM(H38:H49) -> -36745661 | I50: =SUM(I38:I49) -> 180712.5 | ... M50: =SUM(M38:M49) -> 180712.5
A51: Load Factor Incentive | B51: 0 | C51: 0 | D51: 0 | E51: 0 | F51: 0 | G51: 0 | H51: 0 | I51: 0 | J51: 0 | K51: 0 | L51: 0 | M51: 0
A52: Digital Payment Discount | B52: 0 | C52: 0 | D52: 0 | E52: 0 | F52: 0 | G52: 0 | H52: 0 | I52: 0 | J52: 0 | K52: 0 | L52: 0 | M52: 0
A53: Others | B53: 0 | C53: 0 | D53: 0 | E53: 0 | F53: 0 | G53: 0 | H53: 0 | I53: 0 | J53: 0 | K53: 0 | L53: 0 | M53: 0
A54: Delay Payment Charge on Rrevious Month Bill | B54: 0 | C54: 0 | D54: 0 | E54: 0 | F54: 0 | G54: 0 | H54: 0 | I54: 0 | J54: 0 | K54: 0 | L54: 0 | M54: 0
A55: Interest Charged on Arrears | B55: 0 | C55: 0 | D55: 0 | E55: 0 | F55: 0 | G55: 0 | H55: 0 | I55: 0 | J55: 0 | K55: 0 | L55: 0 | M55: 0
A56: Adjustement | B56: 0 | C56: 0 | D56: 0 | E56: 0 | F56: 0 | G56: 0 | H56: 0 | I56: 0 | J56: 0 | K56: 0 | L56: 0 | M56: 0
A57: Net Other Charges in Current Bill ( B) | B57: 0 | C57: 0 | D57: 0 | E57: 0 | F57: 0 | G57: 0 | H57: 0 | I57: 0 | J57: 0 | K57: 0 | L57: 0 | M57: 0
A58: Total Current Month Charges ( A + B) | B58: 0 | C58: 0 | D58: 0 | E58: 0 | F58: 0 | G58: 0 | H58: 0 | I58: 0 | J58: 0 | K58: 0 | L58: 0 | M58: 0
A59: Previous Month Bill Amount
A60: Payment Receivied upto 9th of every Maonth | B60: 0 | C60: 0 | D60: 0 | E60: 0 | F60: 0 | G60: 0 | H60: 0 | I60: 0 | J60: 0 | K60: 0 | L60: 0 | M60: 0
A61: Promt Payment Discount | B61: 0 | C61: 0 | D61: 0 | E61: 0 | F61: 0 | G61: 0 | H61: 0 | I61: 0 | J61: 0 | K61: 0 | L61: 0 | M61: 0
A62: Net Prevoius Balance [ C ] | B62: 0 | C62: 0 | D62: 0 | E62: 0 | F62: 0 | G62: 0 | H62: 0 | I62: 0 | J62: 0 | K62: 0 | L62: 0 | M62: 0
A63: Total Bill (A + B + C) | B63: =B62+B57+B50 -> 1064447.4 | C63: =C62+C57+C50 -> 1372775.2 | D63: =D50+D57+D62 -> 971027.29 | E63: =E50+E57+E62 -> 955344.18 | F63: =F50+F57+F62 -> 929889.67 | G63: =G50+G57+G62 -> 1168956.1 | H63: =H50+H57+H62 -> -36745661 | I63: =I50+I57+I62 -> 180712.5 | J63: =J50+J57+J62 -> 180712.5 | K63: =K50+K57+K62 -> 180712.5 | ... M63: =M50+M57+M62 -> 180712.5

Sheet Monthly Fire Meter
A1: Security Deposite = 10,630/-
A2: Month | B2: Billing Unit As per Power Supply Agency | C2: Amount As Per Below Calculation | D2: PF Incentive Amount if Maintained >= 0.995 | E2: PF Received Amount As Per Poer Supply Agency Bill | F2: PF Loss Amount
A3: 43556 | B3: =B27 -> 25.9 | C3: =B50 -> 6511.0466 | D3: =(B38+B39+B40+B41+B42+B43+B45+B44)*3.5% -> 136.6827 | E3: =-(B47) -> -1776.88 | F3: =D3-E3 -> 1913.5627
A4: 43586 | B4: =C27 -> 100.1 | C4: =C50 -> 20500.974 | D4: =(C38+C39+C40+C41+C42+C43+C45+C44)*3.5% -> 460.63437 | E4: =-(C47) -> -4542.112 | F4: =D4-E4 -> 5002.7464
A5: 43617 | B5: =D27 -> 129.6 | C5: =D50 -> 16330.992 | D5: =(D38+D39+D40+D41+D42+D43+D45+D44)*3.5% -> 471.10798 | E5: =-(D47) -> 0 | F5: =D5-E5 -> 471.10798
A6: 43647 | B6: =E27 -> 22.4 | C6: =E50 -> 15511.54 | D6: =(E38+E39+E40+E41+E42+E43+E45+E44)*3.5% -> 434.11354 | E6: =-(E47) -> -495.99 | F6: =D6-E6 -> 930.10354
A7: 43678 | B7: =F27 -> 2 | C7: =F50 -> 16008.37 | D7: =(F36+F37+F38+F39+F40+F41+F43+F44)*3.5% -> 1956.3733 | E7: =-(F47) -> -1221.961 | F7: =D7-E7 -> 3178.3343
A8: 43709 | B8: =G27 -> 56.4 | C8: =G50 -> 15379.977 | D8: =(G36+G37+G38+G39+G40+G41+G43+G44)*3.5% -> 1974.7548 | E8: =-(G47) -> 63.73767 | F8: =D8-E8 -> 1911.0171
A9: 43739 | B9: =H27 -> -220.4 | C9: =H50 -> 11819.859 | D9: =(H36+H37+H38+H39+H40+H41+H43+H44)*3.5% -> 1886.9733 | E9: =-(H47) -> 250.9469 | F9: =D9-E9 -> 1636.0264
A10: 43770 | B10: =I27 -> 0 | C10: =I50 -> 14457 | D10: =(I36+I37+I38+I39+I40+I41+I43+I44)*3.5% -> 1958.95 | E10: =-(I47) -> 305 | F10: =D10-E10 -> 1653.95
A11: 43800 | B11: =J27 -> 0 | C11: =J50 -> 14457 | D11: =(J36+J37+J38+J39+J40+J41+J43+J44)*3.5% -> 1960 | E11: =-(J47) -> 305 | F11: =D11-E11 -> 1655
A12: 43831 | B12: =K27 -> 0 | C12: =K50 -> 14457 | D12: =(K37+K38+K39+K40+K41+K42+K44+K45)*3.5% -> 1961.085 | E12: =-(K47) -> 305 | F12: =D12-E12 -> 1656.085
A13: 43862 | B13: =L27 -> 0 | C13: =L50 -> 14457 | D13: =(L38+L39+L40+L41+L42+L43+L45+L44)*3.5% -> 427 | E13: =-(L47) -> 305 | F13: =D13-E13 -> 122
A14: 43891 | B14: =M27 -> 0 | C14: =M50 -> 14457 | D14: =(M38+M39+M40+M41+M42+M43+M45+M44)*3.5% -> 427 | E14: =-(M47) -> 305 | F14: =D14-E14 -> 122
A16: Readings | B16: 43556 | C16: 43586 | D16: 43617 | E16: 43647 | F16: 43678 | G16: 43709 | H16: 43739 | I16: 43770 | J16: 43800 | K16: 43831 | L16: 43862 | M16: 43891
A17: Starting | B17: 530 | C17: 0 | D17: =C18 -> 0.25 | E17: =D18 -> 3.49 | F17: =E18 -> 4.05 | G17: =F18 -> 4.1 | H17: =G18 -> 5.51 | I17: =H18 -> 0 | J17: =I18 -> 0 | K17: =J18 -> 0 | ... M17: =L18 -> 0
A18: Closing | B18: 555.9 | C18: 0.25 | D18: 3.49 | E18: 4.05 | F18: 4.1 | G18: 5.51
A19: MF Value | B19: 1 | C19: 40 | D19: 40 | E19: 40 | F19: 40 | G19: 40 | H19: 40 | I19: 40 | J19: 40 | K19: 40 | L19: 40 | M19: 40
A20: Consumption | B20: =(B18-B17)*B19 -> 25.9 | C20: =((C18-C17)*C19)+(646-555.9) -> 100.1 | D20: =(D18-D17)*D19 -> 129.6 | E20: =(E18-E17)*E19 -> 22.4 | F20: =(F18-F17)*F19 -> 2 | G20: =(G18-G17)*G19 -> 56.4 | H20: =(H18-H17)*H19 -> -220.4 | I20: =(I18-I17)*I19 -> 0 | J20: =(J18-J17)*J19 -> 0 | K20: =(K18-K17)*K19 -> 0 | ... M20: =(M18-M17)*M19 -> 0
A22: Ellora Electricity Bill Details - Consumer No - 152283599
A23: Month | B23: 43556 | C23: 43586 | D23: 43617 | E23: 43647 | F23: 43678 | G23: 43709 | H23: 43739 | I23: 43770 | J23: 43800 | K23: 43831 | L23: 43862 | M23: 43891
A24: Tariff Cat | B24: LT II (B) | C24: LT II (B) | D24: LT II (B) | E24: LT II (B) | F24: LT II (B) | G24: LT II (B) | H24: LT II (B) | I24: LT II (B) | J24: LT II (B) | K24: LT II (B) | L24: LT II (B) | M24: LT II (B)
A25: Meter no. | B25: 9078662 | C25: 9078662 + L1009720 | D25: L1009720 | E25: L1009720 | F25: L1009720 | G25: L1009720 | H25: L1009720 | I25: L1009720 | J25: L1009720 | K25: L1009720 | L25: L1009720 | M25: L1009720
A26: Bill No | B26: 100668217247 | C26: 100936340917 | D26: 101773066476 | E26: 100308838039 | F26: 100877729853 | G26: 101683343757
A27: Meter Units | B27: =B20 -> 25.9 | C27: =C20 -> 100.1 | D27: =D20 -> 129.6 | E27: =E20 -> 22.4 | F27: =F20 -> 2 | G27: =G20 -> 56.4 | H27: =H20 -> -220.4 | I27: =I20 -> 0 | ... M27: =M20 -> 0
A28: 9:00 Hrs - 12:00 Hrs | B28: 3 | C28: 3 | D28: 18 | E28: 0 | F28: 0 | G28: 0
A29: 18:00 Hrs - 22:00 Hrs | B29: 2 | C29: 20 | D29: 27 | E29: 0 | F29: 0 | G29: 16
A30: 22:00 Hrs - 6:00 Hrs | B30: 6 | C30: 58 | D30: 62 | E30: 22 | F30: 0 | G30: 29
A31: Unit Use Between (6:00 Hrs - 9:00 Hrs and 12:00 Hrs - 18:00 Hrs (No Electricity Extra Charges) | B31: =B27-(B28+B29+B30) -> 14.9 | C31: =C27-(C28+C29+C30) -> 19.1 | D31: =D27-(D28+D29+D30) -> 22.6 | E31: =E27-(E28+E29+E30) -> 0.4 | F31: =F27-(F28+F29+F30) -> 2 | G31: =G27-(G28+G29+G30) -> 11.4 | H31: =H27-(H28+H29+H30) -> -220.4 | I31: =I27-(I28+I29+I30) -> 0 | ... M31: =M27-(M28+M29+M30) -> 0
A32: Sanctioned demand | B32: 30 | C32: 100 | D32: 100 | E32: 100 | F32: 100 | G32: 100 | H32: 100 | I32: 100 | J32: 100 | K32: 100 | L32: 100 | M32: 100
A33: Maximum demand | C33: 14.98 | D33: 5.2 | E33: 4.24 | F33: 1.84 | G33: 5.5
A34: PF Value | B34: 0.2 | C34: 0.507 | D34: 0.916 | E34: 0.826 | F34: 0.707 | G34: 0.962
A35: Billing amount As Per Power Supply Agency | B35: =B63 -> 6511.0466 | C35: =C63 -> 20500.974 | D35: =D63 -> 16330.992 | E35: =E63 -> 15511.54 | F35: =F63 -> 16008.37 | G35: =G63 -> 15379.977 | H35: =H63 -> 11819.859 | I35: =I63 -> 14457 | ... M35: =M63 -> 14457
A37: Calculation | B37: 43556 | C37: 43586 | D37: 43617 | E37: 43647 | F37: 43678 | G37: 43709 | H37: 43739 | I37: 43770 | J37: 43800 | K37: 43831 | L37: 43862 | M37: 43891 | P37: =524.4*275 -> 144210 | Q37: =410.4*275 -> 112860
A38: Demand/Fixed Charge | B38: =IF(B33>12,(B33*305),(12*305)) -> 3660 | C38: =(IF(C33>40,(C33*305),(40*305))) -> 12200 | D38: =(IF(D33>40,(D33*305),(40*305))) -> 12200 | E38: =(IF(E33>40,(E33*305),(40*305))) -> 12200 | F38: =(IF(F33>40,(F33*305),(40*305))) -> 12200 | G38: =(IF(G33>40,(G33*305),(40*305))) -> 12200 | H38: =(IF(H33>40,(H33*305),(40*305))) -> 12200 | I38: =(IF(I33>40,(I33*305),(40*305))) -> 12200 | J38: =(IF(J33>40,(J33*305),(40*305))) -> 12200 | ... M38: =(IF(M33>40,(M33*305),(40*305))) -> 12200
A39: Whelling Charges | B39: =26*1.57 -> 40.82 | C39: =C27*1.57 -> 157.157 | D39: =D27*1.57 -> 203.472 | E39: =E27*1.57 -> 35.168 | F39: =F27*1.57 -> 3.14 | G39: =G27*1.57 -> 88.548 | H39: =H27*1.57 -> -346.028 | I39: =I27*1.57 -> 0 | J39: =J27*1.57 -> 0 | ... M39: =M27*1.57 -> 0
A40: Regulatory Asset Charge | B40: =26*0.45 -> 11.7 | C40: =C27*0.47 -> 47.047 | D40: =D27*0.47 -> 60.912 | E40: =E27*0.47 -> 10.528 | F40: =F27*0.47 -> 0.94 | G40: =G27*0.47 -> 26.508 | H40: =H27*0.47 -> -103.588 | I40: =I27*0.47 -> 0 | J40: =J27*0.47 -> 0 | ... M40: =M27*0.47 -> 0
A41: Energy Charges | B41: =26*6.85 -> 178.1 | C41: =C27*7.15 -> 715.715 | D41: =D27*7.15 -> 926.64 | E41: =E27*7.15 -> 160.16 | F41: =F27*7.15 -> 14.3 | G41: =G27*7.15 -> 403.26 | H41: =H27*7.15 -> -1575.86 | I41: =I27*7.15 -> 0 | J41: =J27*7.15 -> 0 | ... M41: =M27*7.15 -> 0
A42: 9:00 Hrs - 12: Hrs | B42: =B28*0.5 -> 1.5 | C42: =C28*0.5 -> 1.5 | D42: =D28*0.5 -> 9 | E42: =E28*0.5 -> 0 | F42: =F28*0.5 -> 0 | G42: =G28*0.5 -> 0 | H42: =H28*0.5 -> 0 | I42: =I28*0.5 -> 0 | ... M42: =M28*0.5 -> 0
A43: 18:00 Hrs - 22:00 Hrs | B43: =B29*1 -> 2 | C43: =C29*1 -> 20 | D43: =D29*1 -> 27 | E43: =E29*1 -> 0 | F43: =F29*1 -> 0 | G43: =G29*1 -> 16 | H43: =H29*1 -> 0 | I43: =I29*1 -> 0 | ... M43: =M29*1 -> 0
A44: 22:00 Hrs - 6:00 Hrs | B44: =B30*(-0.75) -> -4.5 | C44: =C30*(-0.75) -> -43.5 | D44: =D30*(-0.75) -> -46.5 | E44: =E30*(-0.75) -> -16.5 | F44: =F30*(-0.75) -> 0 | G44: =G30*(-0.75) -> -21.75 | H44: =H30*(-0.75) -> 0 | I44: =I30*(-0.75) -> 0 | ... M44: =M30*(-0.75) -> 0
A45: Fuel Adjustment | B45: =26*0.6 -> 15.6 | C45: =C27*0.63 -> 63.063 | D45: =D27*0.615 -> 79.704 | E45: =E27*0.62 -> 13.888 | F45: =F27*0.615 -> 1.23 | G45: =G27*0.62 -> 34.968 | H45: =H27*0.62 -> -136.648 | I45: =I27*0.62 -> 0 | J45: =J27*0.62 -> 0 | K45: =K27*0.62 -> 0 | L45: =L27*0.62 -> 0 | M45: =M27*0.62 -> 0
A46: Penalty For Exceeding Contract Demand | B46: 0 | C46: 0 | D46: 0 | E46: 0 | F46: 0 | G46: 0 | H46: 0 | I46: 0 | J46: 0 | K46: 0 | L46: 0 | M46: 0
A47: PF(Incentive) | B47: 1776.88 | C47: 4542.112 | D47: 0 | E47: 495.99 | F47: =(F38+F39+F40+F41+F42+F43+F44+F45)*10% -> 1221.961 | G47: =-(G38+G39+G40+G41+G42+G43+G44+G45)*0.5% -> -63.73767 | H47: =-(H38+H39+H40+H41+H42+H43+H44+H45)*2.5% -> -250.9469 | I47: =-(I38+I39+I40+I41+I42+I43+I44+I45)*2.5% -> -305 | J47: =-(J38+J39+J40+J41+J42+J43+J44+J45)*2.5% -> -305 | K47: =-(K38+K39+K40+K41+K42+K43+K44+K45)*2.5% -> -305 | L47: =-(L38+L39+L40+L41+L42+L43+L44+L45)*2.5% -> -305 | M47: =-(M38+M39+M40+M41+M42+M43+M44+M45)*2.5% -> -305
A48: Electricity Duty | B48: =(B38+B39+B40+B41+B42+B43+B44+B45)*21% -> 820.0962 | C48: =(C38+C39+C40+C41+C42+C43+C44+C45)*21% -> 2763.8062 | D48: =(D38+D39+D40+D41+D42+D43+D44+D45)*21% -> 2826.6479 | E48: =(E38+E39+E40+E41+E42+E43+E44+E45)*21% -> 2604.6812 | F48: =(F38+F39+F40+F41+F42+F43+F44+F45)*21% -> 2566.1181 | G48: =(G38+G39+G40+G41+G42+G43+G44+G45)*21% -> 2676.9821 | H48: =(H38+H39+H40+H41+H42+H43+H44+H45)*21% -> 2107.954 | I48: =(I38+I39+I40+I41+I42+I43+I44+I45)*21% -> 2562 | ... M48: =(M38+M39+M40+M41+M42+M43+M44+M45)*21% -> 2562
A49: Tax | B49: =26*0.3404 -> 8.8504 | C49: =C27*0.3404 -> 34.07404 | D49: =D27*0.3404 -> 44.11584 | E49: =E27*0.3404 -> 7.62496 | F49: =F27*0.3404 -> 0.6808 | G49: =G27*0.3404 -> 19.19856 | H49: =H27*0.3404 -> -75.02416 | I49: =I27*0.3404 -> 0 | J49: =J27*0.3404 -> 0 | ... M49: =M27*0.3404 -> 0
A50: Current Month Bill amount (A) | B50: =SUM(B38:B49) -> 6511.0466 | C50: =SUM(C38:C49) -> 20500.974 | D50: =SUM(D38:D49) -> 16330.992 | E50: =SUM(E38:E49) -> 15511.54 | F50: =SUM(F38:F49) -> 16008.37 | G50: =SUM(G38:G49) -> 15379.977 | H50: =SUM(H38:H49) -> 11819.859 | I50: =SUM(I38:I49) -> 14457 | ... M50: =SUM(M38:M49) -> 14457
A51: Load Factor Incentive | B51: 0 | C51: 0 | D51: 0 | E51: 0 | F51: 0 | G51: 0 | H51: 0 | I51: 0 | J51: 0 | K51: 0 | L51: 0 | M51: 0
A52: Digital Payment Discount | B52: 0 | C52: 0 | D52: 0 | E52: 0 | F52: 0 | G52: 0 | H52: 0 | I52: 0 | J52: 0 | K52: 0 | L52: 0 | M52: 0
A53: Others | B53: 0 | C53: 0 | D53: 0 | E53: 0 | F53: 0 | G53: 0 | H53: 0 | I53: 0 | J53: 0 | K53: 0 | L53: 0 | M53: 0
A54: Delay Payment Charge on Rrevious Month Bill | B54: 0 | C54: 0 | D54: 0 | E54: 0 | F54: 0 | G54: 0 | H54: 0 | I54: 0 | J54: 0 | K54: 0 | L54: 0 | M54: 0
A55: Interest Charged on Arrears | B55: 0 | C55: 0 | D55: 0 | E55: 0 | F55: 0 | G55: 0 | H55: 0 | I55: 0 | J55: 0 | K55: 0 | L55: 0 | M55: 0
A56: Adjustement | B56: 0 | C56: 0 | D56: 0 | E56: 0 | F56: 0 | G56: 0 | H56: 0 | I56: 0 | J56: 0 | K56: 0 | L56: 0 | M56: 0
A57: Net Other Charges in Current Bill ( B) | B57: 0 | C57: 0 | D57: 0 | E57: 0 | F57: 0 | G57: 0 | H57: 0 | I57: 0 | J57: 0 | K57: 0 | L57: 0 | M57: 0
A58: Total Current Month Charges ( A + B) | B58: 0 | C58: 0 | D58: 0 | E58: 0 | F58: 0 | G58: 0 | H58: 0 | I58: 0 | J58: 0 | K58: 0 | L58: 0 | M58: 0
A59: Previous Month Bill Amount
A60: Payment Receivied upto 9th of every Maonth | B60: 0 | C60: 0 | D60: 0 | E60: 0 | F60: 0 | G60: 0 | H60: 0 | I60: 0 | J60: 0 | K60: 0 | L60: 0 | M60: 0
A61: Promt Payment Discount | B61: 0 | C61: 0 | D61: 0 | E61: 0 | F61: 0 | G61: 0 | H61: 0 | I61: 0 | J61: 0 | K61: 0 | L61: 0 | M61: 0
A62: Net Prevoius Balance [ C ] | B62: 0 | C62: 0 | D62: 0 | E62: 0 | F62: 0 | G62: 0 | H62: 0 | I62: 0 | J62: 0 | K62: 0 | L62: 0 | M62: 0
A63: Total Bill (A + B + C) | B63: =B62+B57+B50 -> 6511.0466 | C63: =C62+C57+C50 -> 20500.974 | D63: =D50+D57+D62 -> 16330.992 | E63: =E50+E57+E62 -> 15511.54 | F63: =F50+F57+F62 -> 16008.37 | G63: =G50+G57+G62 -> 15379.977 | H63: =H50+H57+H62 -> 11819.859 | I63: =I50+I57+I62 -> 14457 | J63: =J50+J57+J62 -> 14457 | K63: =K50+K57+K62 -> 14457 | ... M63: =M50+M57+M62 -> 14457

Sheet Monthly Unit Losses
B2: Monthly Unit Losses | L2: Main LT Panel Unit Looses | S2: Capacitor Bank Operational Unit Looses | W2: Location LT Panels Energy Meter +- 1% unit Tolerance and Cable Looses
B3: Month | C3: Transformer Unit Looses | E3: Capacitor Bank Operational Unit Looses | G3: Main LT Panel Energy +- 1% Unit Tolerance Looses | I3: Location LT Panels Energy Meter +- 1% unit Tolerance and Cable Looses | K3: Total Looses | L3: Month | M3: Ellora Main LT Panel Meter Units | P3: Capacitor Bank Operational Unit Losses | Q3: Main LT Panel Energy +- 1% Unit Tolerance Looses | S3: Month | T3: Fixed Capacitor Bank (50 KVA)Operational Unit Losses | U3: Variable Capacitor Bank Operational Unit Losses | V3: Capacitor Bank Operatinal Unit Losses | W3: Month | X3: Sum Of Main LT Panel O/P Meter Units | Y3: Sum Of All Location LT Panel I/P Meter Units | Z3: Unit Looses
C4: Units | D4: in % | E4: Unit | F4: in % | G4: Units | H4: in % | I4: Units | J4: in % | M4: Incomer Meter Units | N4: All O/P Meter Units | O4: Unit Looses | Q4: Units | R4: in % | Z4: Units | AA4: in %
B5: 43556 | C5: =O22 -> 3430 | D5: =W22/100 -> 0.016035875 | E5: =V5 -> 64.0224 | F5: =E5/M5 -> 0.00095370773 | G5: =Q5 -> 340.9776 | H5: =R5 -> 0.0050793624 | I5: =Z5 -> 1187 | J5: =AA5 -> 0.017789434 | K5: =C5+E5+G5+I5 -> 5022 | L5: 43556 | M5: =N22 -> 67130 | N5: 66725 | O5: =(M5-N5) -> 405 | P5: =V5 -> 64.0224 | Q5: =O5-P5 -> 340.9776 | R5: =Q5/M5 -> 0.0050793624 | S5: 43556 | T5: =V38 -> 16.2 | U5: =U38 -> 47.8224 | V5: =U5+T5 -> 64.0224 | W5: 43556 | X5: 66725 | Y5: 65538 | Z5: =X5-Y5 -> 1187 | AA5: =Z5/X5 -> 0.017789434
B6: 43586 | C6: =O23 -> 4640 | D6: =W23/100 -> 0.025654983 | E6: =V6 -> 66.15648 | F6: =E6/M6 -> 0.00074871526 | G6: =Q6 -> 583.84352 | H6: =R6 -> 0.0066075545 | I6: =Z6 -> 1637 | J6: =AA6 -> 0.018663778 | K6: =C6+E6+G6+I6 -> 6927 | L6: 43586 | M6: =N23 -> 88360 | N6: 87710 | O6: =(M6-N6) -> 650 | P6: =V6 -> 66.15648 | Q6: =O6-P6 -> 583.84352 | R6: =Q6/M6 -> 0.0066075545 | S6: 43586 | T6: =V39 -> 16.74 | U6: =U39 -> 49.41648 | V6: =T6+U6 -> 66.15648 | W6: 43586 | X6: 87710 | Y6: 86073 | Z6: =X6-Y6 -> 1637 | AA6: =Z6/X6 -> 0.018663778
B7: 43617 | C7: =O24 -> 3404 | D7: =W24/100 -> 0.010916601 | E7: =V7 -> 64.0224 | F7: =E7/M7 -> 0.0010631418 | G7: =Q7 -> 653.9776 | H7: =R7 -> 0.010859807 | I7: =Z7 -> 1418 | J7: =AA7 -> 0.023831132 | K7: =C7+E7+G7+I7 -> 5540 | L7: 43617 | M7: =N24 -> 60220 | N7: 59502 | O7: =(M7-N7) -> 718 | P7: =V7 -> 64.0224 | Q7: =O7-P7 -> 653.9776 | R7: =Q7/M7 -> 0.010859807 | S7: 43617 | T7: =V40 -> 16.2 | U7: =U40 -> 47.8224 | V7: =T7+U7 -> 64.0224 | W7: 43617 | X7: 59502 | Y7: 58084 | Z7: =X7-Y7 -> 1418 | AA7: =Z7/X7 -> 0.023831132
B8: 43647 | C8: =O25 -> 3186 | D8: =W25/100 -> 0.0090798171 | E8: =V8 -> 66.15648 | F8: =E8/M8 -> 0.0011188311 | G8: =Q8 -> 907.84352 | H8: =R8 -> 0.015353349 | I8: =Z8 -> 1365 | J8: =AA8 -> 0.023471353 | K8: =C8+E8+G8+I8 -> 5525 | L8: 43647 | M8: =N25 -> 59130 | N8: 58156 | O8: =(M8-N8) -> 974 | P8: =V8 -> 66.15648 | Q8: =O8-P8 -> 907.84352 | R8: =Q8/M8 -> 0.015353349 | S8: 43647 | T8: =V41 -> 16.74 | U8: =U41 -> 49.41648 | V8: =T8+U8 -> 66.15648 | W8: 43647 | X8: 58156 | Y8: 56791 | Z8: =X8-Y8 -> 1365 | AA8: =Z8/X8 -> 0.023471353
B9: 43678 | C9: =O26 -> 3732 | D9: =W26/100 -> 0.011158087 | E9: =V9 -> 66.15648 | F9: =E9/M9 -> 0.001178 | G9: =Q9 -> 2008.8435 | H9: =R9 -> 0.035770006 | I9: =Z9 -> -114 | J9: =AA9 -> -0.0021077933 | K9: =C9+E9+G9+I9 -> 5693 | L9: 43678 | M9: =N26 -> 56160 | N9: 54085 | O9: =(M9-N9) -> 2075 | P9: =V9 -> 66.15648 | Q9: =O9-P9 -> 2008.8435 | R9: =Q9/M9 -> 0.035770006 | S9: 43678 | T9: =V42 -> 16.74 | U9: =U42 -> 49.41648 | V9: =T9+U9 -> 66.15648 | W9: 43678 | X9: 54085 | Y9: 54199 | Z9: =X9-Y9 -> -114 | AA9: =Z9/X9 -> -0.0021077933
B10: 44013 | C10: =O27 -> 2892 | D10: =W27/100 -> 0.0054759641 | E10: =V10 -> 66.15648 | F10: =E10/M10 -> 0.0022602146 | G10: =Q10 -> 43.84352 | H10: =R10 -> 0.0014978996 | I10: =Z10 -> 2527 | J10: =AA10 -> 0.086334131 | K10: =C10+E10+G10+I10 -> 5529 | L10: 44013 | M10: =N27 -> 29270 | N10: 29160 | O10: =(M10-N10) -> 110 | P10: =V10 -> 66.15648 | Q10: =O10-P10 -> 43.84352 | R10: =Q10/M10 -> 0.0014978996 | S10: 44013 | T10: =V43 -> 16.74 | U10: =U43 -> 49.41648 | V10: =T10+U10 -> 66.15648 | W10: 44013 | X10: 29270 | Y10: 26743 | Z10: =X10-Y10 -> 2527 | AA10: =Z10/X10 -> 0.086334131
B11: 44045 | C11: =O28 -> 4158 | D11: =W28/100 -> 0.011581422 | E11: =V11 -> 66.15648 | F11: =E11/M11 -> 0.0011361236 | G11: =Q11 -> 283.84352 | H11: =R11 -> 0.0048745238 | I11: =Z11 -> 3211 | J11: =AA11 -> 0.056331357 | K11: =C11+E11+G11+I11 -> 7719 | L11: 44045 | M11: =N28 -> 58230 | N11: 57880 | O11: =(M11-N11) -> 350 | P11: =V11 -> 66.15648 | Q11: =O11-P11 -> 283.84352 | R11: =Q11/M11 -> 0.0048745238 | S11: 44045 | T11: =V44 -> 16.74 | U11: =U44 -> 49.41648 | V11: =T11+U11 -> 66.15648 | W11: 44045 | X11: 57002 | Y11: 53791 | Z11: =X11-Y11 -> 3211 | AA11: =Z11/X11 -> 0.056331357
B12: 44077 | C12: =O29 -> 4428 | D12: =W29/100 -> 0.01027143 | E12: =V12 -> 64.0224 | F12: =E12/M12 -> 0.00092866841 | G12: =Q12 -> 315.9776 | H12: =R12 -> 0.004583371 | I12: =Z12 -> 1233 | J12: =AA12 -> 0.0183403 | K12: =C12+E12+G12+I12 -> 6041 | L12: 44077 | M12: =N29 -> 68940 | N12: 68560 | O12: =(M12-N12) -> 380 | P12: =V12 -> 64.0224 | Q12: =O12-P12 -> 315.9776 | R12: =Q12/M12 -> 0.004583371 | S12: 44077 | T12: =V45 -> 16.2 | U12: =U45 -> 47.8224 | V12: =T12+U12 -> 64.0224 | W12: 44077 | X12: 67229 | Y12: 65996 | Z12: =X12-Y12 -> 1233 | AA12: =Z12/X12 -> 0.0183403
B13: 44109 | C13: =O30 -> 3226 | D13: =W30/100 -> 0.005122342 | E13: =V13 -> 66.15648 | F13: =E13/M13 -> 0.0014665591 | G13: =Q13 -> -346.15648 | H13: =R13 -> -0.0076736085 | I13: =Z13 -> 550 | J13: =AA13 -> 0.012117206 | K13: =C13+E13+G13+I13 -> 3496 | L13: 44109 | M13: 45110 | N13: 45390 | O13: =(M13-N13) -> -280 | P13: =V13 -> 66.15648 | Q13: =O13-P13 -> -346.15648 | R13: =Q13/M13 -> -0.0076736085 | S13: 44109 | T13: =V46 -> 16.74 | U13: =U46 -> 49.41648 | V13: =T13+U13 -> 66.15648 | W13: 44109 | X13: 45390 | Y13: 44840 | Z13: =X13-Y13 -> 550 | AA13: =Z13/X13 -> 0.012117206
B14: 44141 | C14: =O31 -> 3350 | D14: =W31/100 -> 0.014125058 | E14: =V14 -> 64.0224 | F14: =E14/M14 -> 0.00152398 | G14: =Q14 -> 598.9776 | H14: =R14 -> 0.014257977 | I14: =Z14 -> 663 | J14: =AA14 -> 0.015781957 | K14: =C14+E14+G14+I14 -> 4676 | L14: 44141 | M14: =N31 -> 42010 | N14: 41347 | O14: =(M14-N14) -> 663 | P14: =V14 -> 64.0224 | Q14: =O14-P14 -> 598.9776 | R14: =Q14/M14 -> 0.014257977 | S14: 44141 | T14: =V47 -> 16.2 | U14: =U47 -> 47.8224 | V14: =T14+U14 -> 64.0224 | W14: 44141 | X14: 42010 | Y14: 41347 | Z14: =X14-Y14 -> 663 | AA14: =Z14/X14 -> 0.015781957
L19: Transformer Monthly Losses Details
L20: Month | M20: Reliance/Adani Billing Units | N20: Ellora Main LT Panel Incomer Meter Units | O20: Unit Losses | P20: Transformer Losses | U20: Maximum Demand (KVA) | V20: % of Load Utilized Compare With Transformer Full Load | W20: Load Losses in %
P21: Monthly Iron Losses(fixed 1.5 unit(KWH) consumed per hour | Q21: Cu losses( I²R, Depend on load) | R21: Power Factor | S21: Iron Losses in % | T21: cu Losses in %
L22: 43556 | M22: 70560 | N22: 67130 | O22: =M22-N22 -> 3430 | P22: =1.5*24*30 -> 1080 | Q22: =O22-P22 -> 2350 | R22: 0.991 | S22: =(P22/M22)*100 -> 1.5306122 | T22: =(Q22/M22)*100 -> 3.3304989 | U22: 484.8 | V22: =(U22/1250) -> 0.38784 | W22: =+((3*37.87*V22*37.87*V22*0.882*1.5)+(3*1667*V22*1667*V22*0.596)/1000)/1000 -> 1.6035875
L23: 43586 | M23: 93000 | N23: 88360 | O23: =M23-N23 -> 4640 | P23: =1.5*24*31 -> 1116 | Q23: =O23-P23 -> 3524 | R23: 0.995 | S23: =(P23/M23)*100 -> 1.2 | T23: =(Q23/M23)*100 -> 3.7892473 | U23: 613.2 | V23: =(U23/1250) -> 0.49056 | W23: =+((3*37.87*V23*37.87*V23*0.882*1.5)+(3*1667*V23*1667*V23*0.596)/1000)/1000 -> 2.5654983
L24: 43617 | M24: 63624 | N24: 60220 | O24: =M24-N24 -> 3404 | P24: =1.5*24*30 -> 1080 | Q24: =O24-P24 -> 2324 | R24: 0.996 | S24: =(P24/M24)*100 -> 1.6974727 | T24: =(Q24/M24)*100 -> 3.6527097 | U24: 400 | V24: =(U24/1250) -> 0.32 | W24: =+((3*37.87*V24*37.87*V24*0.882*1.5)+(3*1667*V24*1667*V24*0.596)/1000)/1000 -> 1.0916601
L25: 43647 | M25: 62316 | N25: 59130 | O25: =M25-N25 -> 3186 | P25: =1.5*24*31 -> 1116 | Q25: =O25-P25 -> 2070 | R25: 0.995 | S25: =(P25/M25)*100 -> 1.7908723 | T25: =(Q25/M25)*100 -> 3.3217793 | U25: 364.8 | V25: =(U25/1250) -> 0.29184 | W25: =+((3*37.87*V25*37.87*V25*0.882*1.5)+(3*1667*V25*1667*V25*0.596)/1000)/1000 -> 0.90798171
L26: 43678 | M26: 59892 | N26: 56160 | O26: =M26-N26 -> 3732 | P26: =1.5*24*31 -> 1116 | Q26: =O26-P26 -> 2616 | R26: 0.986 | S26: =(P26/M26)*100 -> 1.863354 | T26: =(Q26/M26)*100 -> 4.3678622 | U26: 404.4 | V26: =(U26/1250) -> 0.32352 | W26: =+((3*37.87*V26*37.87*V26*0.882*1.5)+(3*1667*V26*1667*V26*0.596)/1000)/1000 -> 1.1158087
L27: 44013 | M27: 32162 | N27: 29270 | O27: =M27-N27 -> 2892 | P27: =1.5*24*30 -> 1080 | Q27: =O27-P27 -> 1812 | R27: 0.977 | S27: =(P27/M27)*100 -> 3.3580001 | T27: =(Q27/M27)*100 -> 5.633978 | U27: 283.3 | V27: =(U27/1250) -> 0.22664 | W27: =+((3*37.87*V27*37.87*V27*0.882*1.5)+(3*1667*V27*1667*V27*0.596)/1000)/1000 -> 0.54759641
L28: 44045 | M28: 62388 | N28: 58230 | O28: =M28-N28 -> 4158 | P28: =1.5*24*31 -> 1116 | Q28: =O28-P28 -> 3042 | R28: 0.996 | S28: =(P28/M28)*100 -> 1.7888055 | T28: =(Q28/M28)*100 -> 4.8759377 | U28: 412 | V28: =(U28/1250) -> 0.3296 | W28: =+((3*37.87*V28*37.87*V28*0.882*1.5)+(3*1667*V28*1667*V28*0.596)/1000)/1000 -> 1.1581422
L29: 44077 | M29: 73368 | N29: 68940 | O29: =M29-N29 -> 4428 | P29: =1.5*24*30 -> 1080 | Q29: =O29-P29 -> 3348 | R29: 0.996 | S29: =(P29/M29)*100 -> 1.4720314 | T29: =(Q29/M29)*100 -> 4.5632974 | U29: 388 | V29: =(U29/1250) -> 0.3104 | W29: =+((3*37.87*V29*37.87*V29*0.882*1.5)+(3*1667*V29*1667*V29*0.596)/1000)/1000 -> 1.027143
L30: 44109 | M30: 48336 | N30: 45110 | O30: =M30-N30 -> 3226 | P30: =1.5*24*31 -> 1116 | Q30: =O30-P30 -> 2110 | R30: 0.996 | S30: =(P30/M30)*100 -> 2.3088381 | T30: =(Q30/M30)*100 -> 4.3652764 | U30: 274 | V30: =(U30/1250) -> 0.2192 | W30: =+((3*37.87*V30*37.87*V30*0.882*1.5)+(3*1667*V30*1667*V30*0.596)/1000)/1000 -> 0.5122342
L31: 44141 | M31: 45360 | N31: 42010 | O31: =M31-N31 -> 3350 | P31: =1.5*24*31 -> 1116 | Q31: =O31-P31 -> 2234 | R31: 0.996 | S31: =(P31/M31)*100 -> 2.4603175 | T31: =(Q31/M31)*100 -> 4.9250441 | U31: 455 | V31: =(U31/1250) -> 0.364 | W31: =+((3*37.87*V31*37.87*V31*0.882*1.5)+(3*1667*V31*1667*V31*0.596)/1000)/1000 -> 1.4125058
B35: Transformer full Load cu losses is per hour 12.5 Unit/KWH - Confirm by Transformer manufacturer | K35: Capacitor Bank Operational Unit Looses
B36: Transformer fixed losses/Iron losses is per hour 1.5 Unit/KWH - Confirm by Transformer manufacturer. | K36: Month | L36: Ellora Capacitor Bank Capacity (KVA) | M36: Fixed/Continously ON Capacitor Bank Capacity(KVA) | N36: Variable Capacitor Bank Capacity(KVA) | O36: As per Manufecturer Per KVR KW Looses | P36: Variable Capacitor Bank Per day uses in % | Q36: Variable Capacitor Bank Per Hrs. Uses in KVA | R36: Variable Capacitor Bank Per Day Uses in KVA | T36: No of Days of that Month | U36: Capacitor Bank Monthly Operational Unit Looses | X36: Unit Reading As Per Capacitor Bank Unit KWH Meter | Y36: Difference Between Capacitor Bank Meter Unit and OEM Calculated Capacitor Bank Operational Unit | Z36: Difference Between Capacitor Bank Meter Unit and LT Panel Unit Looses | AA36: Difference Between LT Panel Unit Looses and OEM Calculation Unit (Non - identified Load Losses)
B37: Maximum is recorded on Power supply Agency, when a load run for minimum 30 minutes. | R37: Hrs. | S37: Variable Capacitor Bank Per Day Uses in KVA | U37: Variable Capacitor Monthly KW Looses | V37: Fixed Capacitor Monthly KW Losses | W37: Total Unit Looses For using of Capacitor Bank
B38: Transformer given maximum efficiency when no load loos equal to cu loss. | K38: 43556 | L38: 419 | M38: 50 | N38: =L38-M38 -> 369 | O38: =0.45/1000 -> 0.00045 | P38: 0.8 | Q38: =N38*P38 -> 295.2 | R38: 12 | S38: =Q38*R38 -> 3542.4 | T38: 30 | U38: =S38*T38*O38 -> 47.8224 | V38: =M38*O38*24*T38 -> 16.2 | W38: =U38+V38 -> 64.0224 | X38: 1458 | Y38: =X38-W38 -> 1393.9776 | Z38: =X38-O5 -> 1053 | AA38: =O5-W38 -> 340.9776
B39: Transformer % of Losses should be ≤3% of monthly unit value. | K39: 43586 | L39: 419 | M39: 50 | N39: =L39-M39 -> 369 | O39: =0.45/1000 -> 0.00045 | P39: 0.8 | Q39: =N39*P39 -> 295.2 | R39: 12 | S39: =Q39*R39 -> 3542.4 | T39: 31 | U39: =S39*T39*O39 -> 49.41648 | V39: =M39*O39*24*T39 -> 16.74 | W39: =U39+V39 -> 66.15648 | X39: 774 | Y39: =X39-W39 -> 707.84352 | Z39: =X39-O6 -> 124 | AA39: =O6-W39 -> 583.84352
K40: 43617 | L40: 419 | M40: 50 | N40: =L40-M40 -> 369 | O40: =0.45/1000 -> 0.00045 | P40: 0.8 | Q40: =N40*P40 -> 295.2 | R40: 12 | S40: =Q40*R40 -> 3542.4 | T40: 30 | U40: =S40*T40*O40 -> 47.8224 | V40: =M40*O40*24*T40 -> 16.2 | W40: =U40+V40 -> 64.0224 | X40: 894 | Y40: =X40-W40 -> 829.9776 | Z40: =X40-O7 -> 176 | AA40: =O7-W40 -> 653.9776
B41: Capacitor Bank Operational Unit Losses | K41: 43647 | L41: 419 | M41: 50 | N41: =L41-M41 -> 369 | O41: =0.45/1000 -> 0.00045 | P41: 0.8 | Q41: =N41*P41 -> 295.2 | R41: 12 | S41: =Q41*R41 -> 3542.4 | T41: 31 | U41: =S41*T41*O41 -> 49.41648 | V41: =M41*O41*24*T41 -> 16.74 | W41: =U41+V41 -> 66.15648 | X41: 732 | Y41: =X41-W41 -> 665.84352 | Z41: =X41-O8 -> -242 | AA41: =O8-W41 -> 907.84352
B42: Note - Fixed/continously ON Capacitor capacity is the 5% of Transformer capacity. | K42: 43678 | L42: 419 | M42: 50 | N42: =L42-M42 -> 369 | O42: =0.45/1000 -> 0.00045 | P42: 0.8 | Q42: =N42*P42 -> 295.2 | R42: 12 | S42: =Q42*R42 -> 3542.4 | T42: 31 | U42: =S42*T42*O42 -> 49.41648 | V42: =M42*O42*24*T42 -> 16.74 | W42: =U42+V42 -> 66.15648 | X42: 582 | Y42: =X42-W42 -> 515.84352 | Z42: =X42-O9 -> -1493 | AA42: =O9-W42 -> 2008.8435
K43: 44013 | L43: 419 | M43: 50 | N43: =L43-M43 -> 369 | O43: =0.45/1000 -> 0.00045 | P43: 0.8 | Q43: =N43*P43 -> 295.2 | R43: 12 | S43: =Q43*R43 -> 3542.4 | T43: 31 | U43: =S43*T43*O43 -> 49.41648 | V43: =M43*O43*24*T43 -> 16.74 | W43: =U43+V43 -> 66.15648 | X43: 306 | Y43: =X43-W43 -> 239.84352 | Z43: =X43-O10 -> 196 | AA43: =O10-W43 -> 43.84352
K44: 44044 | L44: 419 | M44: 50 | N44: =L44-M44 -> 369 | O44: =0.45/1000 -> 0.00045 | P44: 0.8 | Q44: =N44*P44 -> 295.2 | R44: 12 | S44: =Q44*R44 -> 3542.4 | T44: 31 | U44: =S44*T44*O44 -> 49.41648 | V44: =M44*O44*24*T44 -> 16.74 | W44: =U44+V44 -> 66.15648 | X44: 2274 | Y44: =X44-W44 -> 2207.8435 | Z44: =X44-O11 -> 1924 | AA44: =O11-W44 -> 283.84352
K45: 44075 | L45: 419 | M45: 50 | N45: =L45-M45 -> 369 | O45: =0.45/1000 -> 0.00045 | P45: 0.8 | Q45: =N45*P45 -> 295.2 | R45: 12 | S45: =Q45*R45 -> 3542.4 | T45: 30 | U45: =S45*T45*O45 -> 47.8224 | V45: =M45*O45*24*T45 -> 16.2 | W45: =U45+V45 -> 64.0224 | X45: 4428 | Y45: =X45-W45 -> 4363.9776 | Z45: =X45-O12 -> 4048 | AA45: =O12-W45 -> 315.9776
K46: 44105 | L46: 419 | M46: 50 | N46: =L46-M46 -> 369 | O46: =0.45/1000 -> 0.00045 | P46: 0.8 | Q46: =N46*P46 -> 295.2 | R46: 12 | S46: =Q46*R46 -> 3542.4 | T46: 31 | U46: =S46*T46*O46 -> 49.41648 | V46: =M46*O46*24*T46 -> 16.74 | W46: =U46+V46 -> 66.15648 | X46: 504 | Y46: =X46-W46 -> 437.84352 | Z46: =X46-O13 -> 784 | AA46: =O13-W46 -> -346.15648
K47: 44136 | L47: 419 | M47: 50 | N47: =L47-M47 -> 369 | O47: =0.45/1000 -> 0.00045 | P47: 0.8 | Q47: =N47*P47 -> 295.2 | R47: 12 | S47: =Q47*R47 -> 3542.4 | T47: 30 | U47: =S47*T47*O47 -> 47.8224 | V47: =M47*O47*24*T47 -> 16.2 | W47: =U47+V47 -> 64.0224 | X47: 1278 | Y47: =X47-W47 -> 1213.9776 | Z47: =X47-O14 -> 615 | AA47: =O14-W47 -> 598.9776

Sheet Meterwise Billing Details
A1: Unit Consumption of Different Energy Meter Billed To Customer Account Used by Production Team
A3: Day | B3: Meter Name - Hospital LT With Makeup Room 201,202 & 203 | D3: Meter Name - Hospital Out Door | F3: Meter Name -Bungalow 1 LT | H3: Meter Name - Bungalow 1 Out Door | J3: Meter Name - Office Set | L3: Meter Name - Police Station | N3: Meter Name - 8000 sqft | P3: Meter Name - Restaurant | R3: Meter Name - Parsi Bungalow AC | T3: Meter Name - Parsi Bungalow Light | V3: Meter Name - Bungalow 2 LT | X3: Meter Name - Bungalow 2 Makeup Room | Z3: Meter Name - Villa Set AC | AB3: Meter Name - Villa Set Light | AD3: Meter Name - Villa Set Out Door | AF3: Meter Name - Road Light | AH3: Meter Name - Hill
B4: Production Name | C4: Unit | D4: Production Name | E4: Unit | F4: Production Name | G4: Unit | H4: Production Name | I4: Unit | J4: Production Name | K4: Unit | L4: Production Name | M4: Unit | N4: Production Name | O4: Unit | P4: Production Name | Q4: Unit | R4: Production Name | S4: Unit | T4: Production Name | U4: Unit | V4: Production Name | W4: Unit | X4: Production Name | Y4: Unit | Z4: Production Name | AA4: Unit | AB4: Production Name | AC4: Unit | AD4: Production Name | AE4: Unit | AF4: Production Name | AG4: Unit | AH4: Production Name | AI4: Unit
A5: 1 | B5: =IF(AND(Hospital!R4=Hospital!$B$40,(Hospital!AJ4>0)),Hospital!T4,"") -> Bambai Dreams Entertainment (Opc) Private Limited | C5: =Hospital!AJ4 -> 368 | D5: =IF(AND(Hospital!BD4=Hospital!$B$40,(Hospital!BV4>0)),Hospital!BF4,"") | E5: =Hospital!BV4 -> 0 | F5: =IF(AND('Bungalow 1'!R4='Bungalow 1'!$B$40,('Bungalow 1'!AJ4>0)),'Bungalow 1'!T4,"") -> Classic Films | G5: ='Bungalow 1'!AJ4 -> 692 | H5: =IF(AND('Bungalow 1'!BD4='Bungalow 1'!$B$40,('Bungalow 1'!BV4>0)),'Bungalow 1'!BF4,"") | I5: ='Bungalow 1'!BV4 -> 0 | J5: =IF(AND('Office Set'!R3='Office Set'!$B$39,('Office Set'!AJ3>0)),'Office Set'!T3,"") | K5: ='Office Set'!AJ3 -> 0 | L5: =IF(AND('Police Station'!R4='Police Station'!$B$40,('Police Station'!AJ4>0)),'Police Station'!T4,"") | M5: ='Police Station'!AJ4 -> 0 | N5: =IF(AND('8000 sqft'!R4='8000 sqft'!$B$40,('8000 sqft'!AJ4>0)),'8000 sqft'!T4,"") | O5: ='8000 sqft'!AJ4 -> 0 | P5: =IF(AND('Restaurant '!R4='Restaurant '!$B$40,('Restaurant '!AJ4>0)),'Restaurant '!T4,"") | Q5: ='Restaurant '!AJ4 -> 0 | R5: =IF(AND('Parsi Bungalow'!Y4='Parsi Bungalow'!$B$40,('Parsi Bungalow'!AQ4>0)),'Parsi Bungalow'!AA4,"") | S5: ='Parsi Bungalow'!AQ4 -> 0 | T5: =IF(AND('Parsi Bungalow'!BK4='Parsi Bungalow'!$B$40,('Parsi Bungalow'!CC4>0)),'Parsi Bungalow'!BM4,"") | U5: ='Parsi Bungalow'!CC4 -> 0 | V5: =IF(AND('Bungalow 2'!R4='Bungalow 2'!$B$40,('Bungalow 2'!AJ4>0)),'Bungalow 2'!T4,"") | W5: ='Bungalow 2'!AJ4 -> 0 | X5: =IF(AND('Bungalow 2'!BD4='Bungalow 2'!$B$40,('Bungalow 2'!BV4>0)),'Bungalow 2'!BF4,"") | Y5: ='Bungalow 2'!BV4 -> 0 | Z5: =IF(AND('Villa Set '!Y4='Villa Set '!$B$40,('Villa Set '!AQ4>0)),'Villa Set '!AA4,"") -> Sabir Khan Films Private Limited | AA5: ='Villa Set '!AQ4 -> 836 | AB5: =IF(AND('Villa Set '!BK4='Villa Set '!$B$40,('Villa Set '!CC4>0)),'Villa Set '!BM4,"") -> Sabir Khan Films Private Limited | AC5: ='Villa Set '!CC4 -> 168 | AD5: =IF(AND('Villa Set '!CW4='Villa Set '!$B$40,('Villa Set '!DO4>0)),'Villa Set '!CY4,"") | AE5: ='Villa Set '!DO4 -> 0 | AF5: =IF('Road Light'!R4>0,'Road Light'!M4,"") | AG5: ='Road Light'!R4 -> 0 | AH5: =IF(AND(Hill!R4=Hill!$B$40,(Hill!AJ4>0)),Hill!T4,"") | AI5: =Hill!AJ4 -> 0
A6: 2 | B6: =IF(AND(Hospital!R5=Hospital!$B$40,(Hospital!AJ5>0)),Hospital!T5,"") | C6: =Hospital!AJ5 -> 0 | D6: =IF(AND(Hospital!BD5=Hospital!$B$40,(Hospital!BV5>0)),Hospital!BF5,"") | E6: =Hospital!BV5 -> 0 | F6: =IF(AND('Bungalow 1'!R5='Bungalow 1'!$B$40,('Bungalow 1'!AJ5>0)),'Bungalow 1'!T5,"") -> Rohan Paresh Pujara | G6: ='Bungalow 1'!AJ5 -> 606 | H6: =IF(AND('Bungalow 1'!BD5='Bungalow 1'!$B$40,('Bungalow 1'!BV5>0)),'Bungalow 1'!BF5,"") | I6: ='Bungalow 1'!BV5 -> 0 | J6: =IF(AND('Office Set'!R4='Office Set'!$B$39,('Office Set'!AJ4>0)),'Office Set'!T4,"") | K6: ='Office Set'!AJ4 -> 0 | L6: =IF(AND('Police Station'!R5='Police Station'!$B$40,('Police Station'!AJ5>0)),'Police Station'!T5,"") | M6: ='Police Station'!AJ5 -> 0 | N6: =IF(AND('8000 sqft'!R5='8000 sqft'!$B$40,('8000 sqft'!AJ5>0)),'8000 sqft'!T5,"") | O6: ='8000 sqft'!AJ5 -> 0 | P6: =IF(AND('Restaurant '!R5='Restaurant '!$B$40,('Restaurant '!AJ5>0)),'Restaurant '!T5,"") | Q6: ='Restaurant '!AJ5 -> 0 | R6: =IF(AND('Parsi Bungalow'!Y5='Parsi Bungalow'!$B$40,('Parsi Bungalow'!AQ5>0)),'Parsi Bungalow'!AA5,"") | S6: ='Parsi Bungalow'!AQ5 -> 0 | T6: =IF(AND('Parsi Bungalow'!BK5='Parsi Bungalow'!$B$40,('Parsi Bungalow'!CC5>0)),'Parsi Bungalow'!BM5,"") | U6: ='Parsi Bungalow'!CC5 -> 0 | V6: =IF(AND('Bungalow 2'!R5='Bungalow 2'!$B$40,('Bungalow 2'!AJ5>0)),'Bungalow 2'!T5,"") | W6: ='Bungalow 2'!AJ5 -> 0 | X6: =IF(AND('Bungalow 2'!BD5='Bungalow 2'!$B$40,('Bungalow 2'!BV5>0)),'Bungalow 2'!BF5,"") | Y6: ='Bungalow 2'!BV5 -> 0 | Z6: =IF(AND('Villa Set '!Y5='Villa Set '!$B$40,('Villa Set '!AQ5>0)),'Villa Set '!AA5,"") -> Sabir Khan Films Private Limited | AA6: ='Villa Set '!AQ5 -> 529 | AB6: =IF(AND('Villa Set '!BK5='Villa Set '!$B$40,('Villa Set '!CC5>0)),'Villa Set '!BM5,"") -> Sabir Khan Films Private Limited | AC6: ='Villa Set '!CC5 -> 129 | AD6: =IF(AND('Villa Set '!CW5='Villa Set '!$B$40,('Villa Set '!DO5>0)),'Villa Set '!CY5,"") | AE6: ='Villa Set '!DO5 -> 0 | AG6: ='Road Light'!R5 -> 0 | AH6: =IF(AND(Hill!R5=Hill!$B$40,(Hill!AJ5>0)),Hill!T5,"") | AI6: =Hill!AJ5 -> 0
A7: 3 | B7: =IF(AND(Hospital!R6=Hospital!$B$40,(Hospital!AJ6>0)),Hospital!T6,"") -> Sabir Khan Films Private Limited | C7: =Hospital!AJ6 -> 227 | D7: =IF(AND(Hospital!BD6=Hospital!$B$40,(Hospital!BV6>0)),Hospital!BF6,"") | E7: =Hospital!BV6 -> 0 | F7: =IF(AND('Bungalow 1'!R6='Bungalow 1'!$B$40,('Bungalow 1'!AJ6>0)),'Bungalow 1'!T6,"") -> Sabir Khan Films Private Limited | G7: ='Bungalow 1'!AJ6 -> 7 | H7: =IF(AND('Bungalow 1'!BD6='Bungalow 1'!$B$40,('Bungalow 1'!BV6>0)),'Bungalow 1'!BF6,"") | I7: ='Bungalow 1'!BV6 -> 0 | J7: =IF(AND('Office Set'!R5='Office Set'!$B$39,('Office Set'!AJ5>0)),'Office Set'!T5,"") | K7: ='Office Set'!AJ5 -> 0 | L7: =IF(AND('Police Station'!R6='Police Station'!$B$40,('Police Station'!AJ6>0)),'Police Station'!T6,"") | M7: ='Police Station'!AJ6 -> 0 | N7: =IF(AND('8000 sqft'!R6='8000 sqft'!$B$40,('8000 sqft'!AJ6>0)),'8000 sqft'!T6,"") | O7: ='8000 sqft'!AJ6 -> 0 | P7: =IF(AND('Restaurant '!R6='Restaurant '!$B$40,('Restaurant '!AJ6>0)),'Restaurant '!T6,"") -> Flying Elephant Studios Pvt.Ltd. | Q7: ='Restaurant '!AJ6 -> 559 | R7: =IF(AND('Parsi Bungalow'!Y6='Parsi Bungalow'!$B$40,('Parsi Bungalow'!AQ6>0)),'Parsi Bungalow'!AA6,"") | S7: ='Parsi Bungalow'!AQ6 -> 0 | T7: =IF(AND('Parsi Bungalow'!BK6='Parsi Bungalow'!$B$40,('Parsi Bungalow'!CC6>0)),'Parsi Bungalow'!BM6,"") | U7: ='Parsi Bungalow'!CC6 -> 0 | V7: =IF(AND('Bungalow 2'!R6='Bungalow 2'!$B$40,('Bungalow 2'!AJ6>0)),'Bungalow 2'!T6,"") | W7: ='Bungalow 2'!AJ6 -> 0 | X7: =IF(AND('Bungalow 2'!BD6='Bungalow 2'!$B$40,('Bungalow 2'!BV6>0)),'Bungalow 2'!BF6,"") | Y7: ='Bungalow 2'!BV6 -> 0 | Z7: =IF(AND('Villa Set '!Y6='Villa Set '!$B$40,('Villa Set '!AQ6>0)),'Villa Set '!AA6,"") | AA7: ='Villa Set '!AQ6 -> 0 | AB7: =IF(AND('Villa Set '!BK6='Villa Set '!$B$40,('Villa Set '!CC6>0)),'Villa Set '!BM6,"") -> Sabir Khan Films Private Limited | AC7: ='Villa Set '!CC6 -> 119 | AD7: =IF(AND('Villa Set '!CW6='Villa Set '!$B$40,('Villa Set '!DO6>0)),'Villa Set '!CY6,"") | AE7: ='Villa Set '!DO6 -> 0 | AG7: ='Road Light'!R6 -> 0 | AH7: =IF(AND(Hill!R6=Hill!$B$40,(Hill!AJ6>0)),Hill!T6,"") | AI7: =Hill!AJ6 -> 0
A8: 4 | B8: =IF(AND(Hospital!R7=Hospital!$B$40,(Hospital!AJ7>0)),Hospital!T7,"") | C8: =Hospital!AJ7 -> 0 | D8: =IF(AND(Hospital!BD7=Hospital!$B$40,(Hospital!BV7>0)),Hospital!BF7,"") | E8: =Hospital!BV7 -> 0 | F8: =IF(AND('Bungalow 1'!R7='Bungalow 1'!$B$40,('Bungalow 1'!AJ7>0)),'Bungalow 1'!T7,"") | G8: ='Bungalow 1'!AJ7 -> 0 | H8: =IF(AND('Bungalow 1'!BD7='Bungalow 1'!$B$40,('Bungalow 1'!BV7>0)),'Bungalow 1'!BF7,"") | I8: ='Bungalow 1'!BV7 -> 0 | J8: =IF(AND('Office Set'!R6='Office Set'!$B$39,('Office Set'!AJ6>0)),'Office Set'!T6,"") | K8: ='Office Set'!AJ6 -> 0 | L8: =IF(AND('Police Station'!R7='Police Station'!$B$40,('Police Station'!AJ7>0)),'Police Station'!T7,"") | M8: ='Police Station'!AJ7 -> 0 | N8: =IF(AND('8000 sqft'!R7='8000 sqft'!$B$40,('8000 sqft'!AJ7>0)),'8000 sqft'!T7,"") | O8: ='8000 sqft'!AJ7 -> 0 | P8: =IF(AND('Restaurant '!R7='Restaurant '!$B$40,('Restaurant '!AJ7>0)),'Restaurant '!T7,"") | Q8: ='Restaurant '!AJ7 -> 0 | R8: =IF(AND('Parsi Bungalow'!Y7='Parsi Bungalow'!$B$40,('Parsi Bungalow'!AQ7>0)),'Parsi Bungalow'!AA7,"") | S8: ='Parsi Bungalow'!AQ7 -> 0 | T8: =IF(AND('Parsi Bungalow'!BK7='Parsi Bungalow'!$B$40,('Parsi Bungalow'!CC7>0)),'Parsi Bungalow'!BM7,"") | U8: ='Parsi Bungalow'!CC7 -> 0 | V8: =IF(AND('Bungalow 2'!R7='Bungalow 2'!$B$40,('Bungalow 2'!AJ7>0)),'Bungalow 2'!T7,"") | W8: ='Bungalow 2'!AJ7 -> 0 | X8: =IF(AND('Bungalow 2'!BD7='Bungalow 2'!$B$40,('Bungalow 2'!BV7>0)),'Bungalow 2'!BF7,"") | Y8: ='Bungalow 2'!BV7 -> 0 | Z8: =IF(AND('Villa Set '!Y7='Villa Set '!$B$40,('Villa Set '!AQ7>0)),'Villa Set '!AA7,"") | AA8: ='Villa Set '!AQ7 -> 0 | AB8: =IF(AND('Villa Set '!BK7='Villa Set '!$B$40,('Villa Set '!CC7>0)),'Villa Set '!BM7,"") | AC8: ='Villa Set '!CC7 -> 0 | AD8: =IF(AND('Villa Set '!CW7='Villa Set '!$B$40,('Villa Set '!DO7>0)),'Villa Set '!CY7,"") | AE8: ='Villa Set '!DO7 -> 0 | AG8: ='Road Light'!R7 -> 0 | AH8: =IF(AND(Hill!R7=Hill!$B$40,(Hill!AJ7>0)),Hill!T7,"") | AI8: =Hill!AJ7 -> 0
A9: 5 | B9: =IF(AND(Hospital!R8=Hospital!$B$40,(Hospital!AJ8>0)),Hospital!T8,"") -> White Rivers Media Solutions Private Limited | C9: =Hospital!AJ8 -> 506 | D9: =IF(AND(Hospital!BD8=Hospital!$B$40,(Hospital!BV8>0)),Hospital!BF8,"") | E9: =Hospital!BV8 -> 0 | F9: =IF(AND('Bungalow 1'!R8='Bungalow 1'!$B$40,('Bungalow 1'!AJ8>0)),'Bungalow 1'!T8,"") | G9: ='Bungalow 1'!AJ8 -> 0 | H9: =IF(AND('Bungalow 1'!BD8='Bungalow 1'!$B$40,('Bungalow 1'!BV8>0)),'Bungalow 1'!BF8,"") | I9: ='Bungalow 1'!BV8 -> 0 | J9: =IF(AND('Office Set'!R7='Office Set'!$B$39,('Office Set'!AJ7>0)),'Office Set'!T7,"") | K9: ='Office Set'!AJ7 -> 0 | L9: =IF(AND('Police Station'!R8='Police Station'!$B$40,('Police Station'!AJ8>0)),'Police Station'!T8,"") | M9: ='Police Station'!AJ8 -> 0 | N9: =IF(AND('8000 sqft'!R8='8000 sqft'!$B$40,('8000 sqft'!AJ8>0)),'8000 sqft'!T8,"") | O9: ='8000 sqft'!AJ8 -> 0 | P9: =IF(AND('Restaurant '!R8='Restaurant '!$B$40,('Restaurant '!AJ8>0)),'Restaurant '!T8,"") -> Vijaya Entertainment India | Q9: ='Restaurant '!AJ8 -> 1 | R9: =IF(AND('Parsi Bungalow'!Y8='Parsi Bungalow'!$B$40,('Parsi Bungalow'!AQ8>0)),'Parsi Bungalow'!AA8,"") | S9: ='Parsi Bungalow'!AQ8 -> 0 | T9: =IF(AND('Parsi Bungalow'!BK8='Parsi Bungalow'!$B$40,('Parsi Bungalow'!CC8>0)),'Parsi Bungalow'!BM8,"") | U9: ='Parsi Bungalow'!CC8 -> 0 | V9: =IF(AND('Bungalow 2'!R8='Bungalow 2'!$B$40,('Bungalow 2'!AJ8>0)),'Bungalow 2'!T8,"") | W9: ='Bungalow 2'!AJ8 -> 0 | X9: =IF(AND('Bungalow 2'!BD8='Bungalow 2'!$B$40,('Bungalow 2'!BV8>0)),'Bungalow 2'!BF8,"") | Y9: ='Bungalow 2'!BV8 -> 0 | Z9: =IF(AND('Villa Set '!Y8='Villa Set '!$B$40,('Villa Set '!AQ8>0)),'Villa Set '!AA8,"") -> Vijaya Entertainment India | AA9: ='Villa Set '!AQ8 -> 403 | AB9: =IF(AND('Villa Set '!BK8='Villa Set '!$B$40,('Villa Set '!CC8>0)),'Villa Set '!BM8,"") -> Vijaya Entertainment India | AC9: ='Villa Set '!CC8 -> 520 | AD9: =IF(AND('Villa Set '!CW8='Villa Set '!$B$40,('Villa Set '!DO8>0)),'Villa Set '!CY8,"") | AE9: ='Villa Set '!DO8 -> 0 | AG9: ='Road Light'!R8 -> 0 | AH9: =IF(AND(Hill!R8=Hill!$B$40,(Hill!AJ8>0)),Hill!T8,"") | AI9: =Hill!AJ8 -> 0
A10: 6 | B10: =IF(AND(Hospital!R9=Hospital!$B$40,(Hospital!AJ9>0)),Hospital!T9,"") -> Superfly Films Private Limited | C10: =Hospital!AJ9 -> 19 | D10: =IF(AND(Hospital!BD9=Hospital!$B$40,(Hospital!BV9>0)),Hospital!BF9,"") | E10: =Hospital!BV9 -> 0 | F10: =IF(AND('Bungalow 1'!R9='Bungalow 1'!$B$40,('Bungalow 1'!AJ9>0)),'Bungalow 1'!T9,"") | G10: ='Bungalow 1'!AJ9 -> 0 | H10: =IF(AND('Bungalow 1'!BD9='Bungalow 1'!$B$40,('Bungalow 1'!BV9>0)),'Bungalow 1'!BF9,"") | I10: ='Bungalow 1'!BV9 -> 0 | J10: =IF(AND('Office Set'!R8='Office Set'!$B$39,('Office Set'!AJ8>0)),'Office Set'!T8,"") | K10: ='Office Set'!AJ8 -> 0 | L10: =IF(AND('Police Station'!R9='Police Station'!$B$40,('Police Station'!AJ9>0)),'Police Station'!T9,"") | M10: ='Police Station'!AJ9 -> 0 | N10: =IF(AND('8000 sqft'!R9='8000 sqft'!$B$40,('8000 sqft'!AJ9>0)),'8000 sqft'!T9,"") | O10: ='8000 sqft'!AJ9 -> 0 | P10: =IF(AND('Restaurant '!R9='Restaurant '!$B$40,('Restaurant '!AJ9>0)),'Restaurant '!T9,"") -> High Rise Films Private Limited | Q10: ='Restaurant '!AJ9 -> 370 | R10: =IF(AND('Parsi Bungalow'!Y9='Parsi Bungalow'!$B$40,('Parsi Bungalow'!AQ9>0)),'Parsi Bungalow'!AA9,"") -> High Rise Films Private Limited | S10: ='Parsi Bungalow'!AQ9 -> 967 | T10: =IF(AND('Parsi Bungalow'!BK9='Parsi Bungalow'!$B$40,('Parsi Bungalow'!CC9>0)),'Parsi Bungalow'!BM9,"") -> High Rise Films Private Limited | U10: ='Parsi Bungalow'!CC9 -> 557 | V10: =IF(AND('Bungalow 2'!R9='Bungalow 2'!$B$40,('Bungalow 2'!AJ9>0)),'Bungalow 2'!T9,"") -> Four Lions Films Private Limited | W10: ='Bungalow 2'!AJ9 -> 60 | X10: =IF(AND('Bungalow 2'!BD9='Bungalow 2'!$B$40,('Bungalow 2'!BV9>0)),'Bungalow 2'!BF9,"") | Y10: ='Bungalow 2'!BV9 -> 0 | Z10: =IF(AND('Villa Set '!Y9='Villa Set '!$B$40,('Villa Set '!AQ9>0)),'Villa Set '!AA9,"") | AA10: ='Villa Set '!AQ9 -> 0 | AB10: =IF(AND('Villa Set '!BK9='Villa Set '!$B$40,('Villa Set '!CC9>0)),'Villa Set '!BM9,"") | AC10: ='Villa Set '!CC9 -> 0 | AD10: =IF(AND('Villa Set '!CW9='Villa Set '!$B$40,('Villa Set '!DO9>0)),'Villa Set '!CY9,"") | AE10: ='Villa Set '!DO9 -> 0 | AG10: ='Road Light'!R9 -> 0 | AH10: =IF(AND(Hill!R9=Hill!$B$40,(Hill!AJ9>0)),Hill!T9,"") | AI10: =Hill!AJ9 -> 0
A11: 7 | B11: =IF(AND(Hospital!R10=Hospital!$B$40,(Hospital!AJ10>0)),Hospital!T10,"") -> Superfly Films Private Limited | C11: =Hospital!AJ10 -> 281 | D11: =IF(AND(Hospital!BD10=Hospital!$B$40,(Hospital!BV10>0)),Hospital!BF10,"") | E11: =Hospital!BV10 -> 0 | F11: =IF(AND('Bungalow 1'!R10='Bungalow 1'!$B$40,('Bungalow 1'!AJ10>0)),'Bungalow 1'!T10,"") | G11: ='Bungalow 1'!AJ10 -> 0 | H11: =IF(AND('Bungalow 1'!BD10='Bungalow 1'!$B$40,('Bungalow 1'!BV10>0)),'Bungalow 1'!BF10,"") | I11: ='Bungalow 1'!BV10 -> 0 | J11: =IF(AND('Office Set'!R9='Office Set'!$B$39,('Office Set'!AJ9>0)),'Office Set'!T9,"") | K11: ='Office Set'!AJ9 -> 0 | L11: =IF(AND('Police Station'!R10='Police Station'!$B$40,('Police Station'!AJ10>0)),'Police Station'!T10,"") | M11: ='Police Station'!AJ10 -> 0 | N11: =IF(AND('8000 sqft'!R10='8000 sqft'!$B$40,('8000 sqft'!AJ10>0)),'8000 sqft'!T10,"") | O11: ='8000 sqft'!AJ10 -> 0 | P11: =IF(AND('Restaurant '!R10='Restaurant '!$B$40,('Restaurant '!AJ10>0)),'Restaurant '!T10,"") | Q11: ='Restaurant '!AJ10 -> 0 | R11: =IF(AND('Parsi Bungalow'!Y10='Parsi Bungalow'!$B$40,('Parsi Bungalow'!AQ10>0)),'Parsi Bungalow'!AA10,"") | S11: ='Parsi Bungalow'!AQ10 -> 0 | T11: =IF(AND('Parsi Bungalow'!BK10='Parsi Bungalow'!$B$40,('Parsi Bungalow'!CC10>0)),'Parsi Bungalow'!BM10,"") | U11: ='Parsi Bungalow'!CC10 -> 0 | V11: =IF(AND('Bungalow 2'!R10='Bungalow 2'!$B$40,('Bungalow 2'!AJ10>0)),'Bungalow 2'!T10,"") -> Rising Star | W11: ='Bungalow 2'!AJ10 -> 67 | X11: =IF(AND('Bungalow 2'!BD10='Bungalow 2'!$B$40,('Bungalow 2'!BV10>0)),'Bungalow 2'!BF10,"") | Y11: ='Bungalow 2'!BV10 -> 0 | Z11: =IF(AND('Villa Set '!Y10='Villa Set '!$B$40,('Villa Set '!AQ10>0)),'Villa Set '!AA10,"") | AA11: ='Villa Set '!AQ10 -> 0 | AB11: =IF(AND('Villa Set '!BK10='Villa Set '!$B$40,('Villa Set '!CC10>0)),'Villa Set '!BM10,"") | AC11: ='Villa Set '!CC10 -> 0 | AD11: =IF(AND('Villa Set '!CW10='Villa Set '!$B$40,('Villa Set '!DO10>0)),'Villa Set '!CY10,"") | AE11: ='Villa Set '!DO10 -> 0 | AG11: ='Road Light'!R10 -> 0 | AH11: =IF(AND(Hill!R10=Hill!$B$40,(Hill!AJ10>0)),Hill!T10,"") | AI11: =Hill!AJ10 -> 0
A12: 8 | B12: =IF(AND(Hospital!R11=Hospital!$B$40,(Hospital!AJ11>0)),Hospital!T11,"") | C12: =Hospital!AJ11 -> 0 | D12: =IF(AND(Hospital!BD11=Hospital!$B$40,(Hospital!BV11>0)),Hospital!BF11,"") | E12: =Hospital!BV11 -> 0 | F12: =IF(AND('Bungalow 1'!R11='Bungalow 1'!$B$40,('Bungalow 1'!AJ11>0)),'Bungalow 1'!T11,"") -> Boathouse Media Private Limited | G12: ='Bungalow 1'!AJ11 -> 620 | H12: =IF(AND('Bungalow 1'!BD11='Bungalow 1'!$B$40,('Bungalow 1'!BV11>0)),'Bungalow 1'!BF11,"") | I12: ='Bungalow 1'!BV11 -> 0 | J12: =IF(AND('Office Set'!R10='Office Set'!$B$39,('Office Set'!AJ10>0)),'Office Set'!T10,"") | K12: ='Office Set'!AJ10 -> 0 | L12: =IF(AND('Police Station'!R11='Police Station'!$B$40,('Police Station'!AJ11>0)),'Police Station'!T11,"") | M12: ='Police Station'!AJ11 -> 0 | N12: =IF(AND('8000 sqft'!R11='8000 sqft'!$B$40,('8000 sqft'!AJ11>0)),'8000 sqft'!T11,"") | O12: ='8000 sqft'!AJ11 -> 0 | P12: =IF(AND('Restaurant '!R11='Restaurant '!$B$40,('Restaurant '!AJ11>0)),'Restaurant '!T11,"") -> Rising Star | Q12: ='Restaurant '!AJ11 -> 46 | R12: =IF(AND('Parsi Bungalow'!Y11='Parsi Bungalow'!$B$40,('Parsi Bungalow'!AQ11>0)),'Parsi Bungalow'!AA11,"") | S12: ='Parsi Bungalow'!AQ11 -> 0 | T12: =IF(AND('Parsi Bungalow'!BK11='Parsi Bungalow'!$B$40,('Parsi Bungalow'!CC11>0)),'Parsi Bungalow'!BM11,"") | U12: ='Parsi Bungalow'!CC11 -> 0 | V12: =IF(AND('Bungalow 2'!R11='Bungalow 2'!$B$40,('Bungalow 2'!AJ11>0)),'Bungalow 2'!T11,"") -> Rising Star | W12: ='Bungalow 2'!AJ11 -> 973 | X12: =IF(AND('Bungalow 2'!BD11='Bungalow 2'!$B$40,('Bungalow 2'!BV11>0)),'Bungalow 2'!BF11,"") | Y12: ='Bungalow 2'!BV11 -> 0 | Z12: =IF(AND('Villa Set '!Y11='Villa Set '!$B$40,('Villa Set '!AQ11>0)),'Villa Set '!AA11,"") | AA12: ='Villa Set '!AQ11 -> 0 | AB12: =IF(AND('Villa Set '!BK11='Villa Set '!$B$40,('Villa Set '!CC11>0)),'Villa Set '!BM11,"") -> Rising Star | AC12: ='Villa Set '!CC11 -> 43 | AD12: =IF(AND('Villa Set '!CW11='Villa Set '!$B$40,('Villa Set '!DO11>0)),'Villa Set '!CY11,"") | AE12: ='Villa Set '!DO11 -> 0 | AG12: ='Road Light'!R11 -> 0 | AH12: =IF(AND(Hill!R11=Hill!$B$40,(Hill!AJ11>0)),Hill!T11,"") | AI12: =Hill!AJ11 -> 0
A13: 9 | B13: =IF(AND(Hospital!R12=Hospital!$B$40,(Hospital!AJ12>0)),Hospital!T12,"") | C13: =Hospital!AJ12 -> 0 | D13: =IF(AND(Hospital!BD12=Hospital!$B$40,(Hospital!BV12>0)),Hospital!BF12,"") | E13: =Hospital!BV12 -> 0 | F13: =IF(AND('Bungalow 1'!R12='Bungalow 1'!$B$40,('Bungalow 1'!AJ12>0)),'Bungalow 1'!T12,"") | G13: ='Bungalow 1'!AJ12 -> 0 | H13: =IF(AND('Bungalow 1'!BD12='Bungalow 1'!$B$40,('Bungalow 1'!BV12>0)),'Bungalow 1'!BF12,"") | I13: ='Bungalow 1'!BV12 -> 0 | J13: =IF(AND('Office Set'!R11='Office Set'!$B$39,('Office Set'!AJ11>0)),'Office Set'!T11,"") | K13: ='Office Set'!AJ11 -> 0 | L13: =IF(AND('Police Station'!R12='Police Station'!$B$40,('Police Station'!AJ12>0)),'Police Station'!T12,"") | M13: ='Police Station'!AJ12 -> 0 | N13: =IF(AND('8000 sqft'!R12='8000 sqft'!$B$40,('8000 sqft'!AJ12>0)),'8000 sqft'!T12,"") | O13: ='8000 sqft'!AJ12 -> 0 | P13: =IF(AND('Restaurant '!R12='Restaurant '!$B$40,('Restaurant '!AJ12>0)),'Restaurant '!T12,"") | Q13: ='Restaurant '!AJ12 -> 0 | R13: =IF(AND('Parsi Bungalow'!Y12='Parsi Bungalow'!$B$40,('Parsi Bungalow'!AQ12>0)),'Parsi Bungalow'!AA12,"") | S13: ='Parsi Bungalow'!AQ12 -> 0 | T13: =IF(AND('Parsi Bungalow'!BK12='Parsi Bungalow'!$B$40,('Parsi Bungalow'!CC12>0)),'Parsi Bungalow'!BM12,"") | U13: ='Parsi Bungalow'!CC12 -> 0 | V13: =IF(AND('Bungalow 2'!R12='Bungalow 2'!$B$40,('Bungalow 2'!AJ12>0)),'Bungalow 2'!T12,"") -> Rising Star | W13: ='Bungalow 2'!AJ12 -> 8 | X13: =IF(AND('Bungalow 2'!BD12='Bungalow 2'!$B$40,('Bungalow 2'!BV12>0)),'Bungalow 2'!BF12,"") | Y13: ='Bungalow 2'!BV12 -> 0 | Z13: =IF(AND('Villa Set '!Y12='Villa Set '!$B$40,('Villa Set '!AQ12>0)),'Villa Set '!AA12,"") | AA13: ='Villa Set '!AQ12 -> 0 | AB13: =IF(AND('Villa Set '!BK12='Villa Set '!$B$40,('Villa Set '!CC12>0)),'Villa Set '!BM12,"") | AC13: ='Villa Set '!CC12 -> 0 | AD13: =IF(AND('Villa Set '!CW12='Villa Set '!$B$40,('Villa Set '!DO12>0)),'Villa Set '!CY12,"") | AE13: ='Villa Set '!DO12 -> 0 | AG13: ='Road Light'!R12 -> 0 | AH13: =IF(AND(Hill!R12=Hill!$B$40,(Hill!AJ12>0)),Hill!T12,"") | AI13: =Hill!AJ12 -> 0
A14: 10 | B14: =IF(AND(Hospital!R13=Hospital!$B$40,(Hospital!AJ13>0)),Hospital!T13,"") | C14: =Hospital!AJ13 -> 0 | D14: =IF(AND(Hospital!BD13=Hospital!$B$40,(Hospital!BV13>0)),Hospital!BF13,"") | E14: =Hospital!BV13 -> 0 | F14: =IF(AND('Bungalow 1'!R13='Bungalow 1'!$B$40,('Bungalow 1'!AJ13>0)),'Bungalow 1'!T13,"") -> Gulliver Motion Pictures LLP | G14: ='Bungalow 1'!AJ13 -> 35 | H14: =IF(AND('Bungalow 1'!BD13='Bungalow 1'!$B$40,('Bungalow 1'!BV13>0)),'Bungalow 1'!BF13,"") | I14: ='Bungalow 1'!BV13 -> 0 | J14: =IF(AND('Office Set'!R12='Office Set'!$B$39,('Office Set'!AJ12>0)),'Office Set'!T12,"") -> In 10 Media Pvt.Ltd. | K14: ='Office Set'!AJ12 -> 59 | L14: =IF(AND('Police Station'!R13='Police Station'!$B$40,('Police Station'!AJ13>0)),'Police Station'!T13,"") | M14: ='Police Station'!AJ13 -> 0 | N14: =IF(AND('8000 sqft'!R13='8000 sqft'!$B$40,('8000 sqft'!AJ13>0)),'8000 sqft'!T13,"") | O14: ='8000 sqft'!AJ13 -> 0 | P14: =IF(AND('Restaurant '!R13='Restaurant '!$B$40,('Restaurant '!AJ13>0)),'Restaurant '!T13,"") | Q14: ='Restaurant '!AJ13 -> 0 | R14: =IF(AND('Parsi Bungalow'!Y13='Parsi Bungalow'!$B$40,('Parsi Bungalow'!AQ13>0)),'Parsi Bungalow'!AA13,"") | S14: ='Parsi Bungalow'!AQ13 -> 0 | T14: =IF(AND('Parsi Bungalow'!BK13='Parsi Bungalow'!$B$40,('Parsi Bungalow'!CC13>0)),'Parsi Bungalow'!BM13,"") | U14: ='Parsi Bungalow'!CC13 -> 0 | V14: =IF(AND('Bungalow 2'!R13='Bungalow 2'!$B$40,('Bungalow 2'!AJ13>0)),'Bungalow 2'!T13,"") -> Rising Star | W14: ='Bungalow 2'!AJ13 -> 61 | X14: =IF(AND('Bungalow 2'!BD13='Bungalow 2'!$B$40,('Bungalow 2'!BV13>0)),'Bungalow 2'!BF13,"") | Y14: ='Bungalow 2'!BV13 -> 0 | Z14: =IF(AND('Villa Set '!Y13='Villa Set '!$B$40,('Villa Set '!AQ13>0)),'Villa Set '!AA13,"") | AA14: ='Villa Set '!AQ13 -> 0 | AB14: =IF(AND('Villa Set '!BK13='Villa Set '!$B$40,('Villa Set '!CC13>0)),'Villa Set '!BM13,"") | AC14: ='Villa Set '!CC13 -> 0 | AD14: =IF(AND('Villa Set '!CW13='Villa Set '!$B$40,('Villa Set '!DO13>0)),'Villa Set '!CY13,"") | AE14: ='Villa Set '!DO13 -> 0 | AG14: ='Road Light'!R13 -> 0 | AH14: =IF(AND(Hill!R13=Hill!$B$40,(Hill!AJ13>0)),Hill!T13,"") | AI14: =Hill!AJ13 -> 0
A15: 11 | B15: =IF(AND(Hospital!R14=Hospital!$B$40,(Hospital!AJ14>0)),Hospital!T14,"") | C15: =Hospital!AJ14 -> 0 | D15: =IF(AND(Hospital!BD14=Hospital!$B$40,(Hospital!BV14>0)),Hospital!BF14,"") | E15: =Hospital!BV14 -> 0 | F15: =IF(AND('Bungalow 1'!R14='Bungalow 1'!$B$40,('Bungalow 1'!AJ14>0)),'Bungalow 1'!T14,"") -> Gulliver Motion Pictures LLP | G15: ='Bungalow 1'!AJ14 -> 109 | H15: =IF(AND('Bungalow 1'!BD14='Bungalow 1'!$B$40,('Bungalow 1'!BV14>0)),'Bungalow 1'!BF14,"") | I15: ='Bungalow 1'!BV14 -> 0 | J15: =IF(AND('Office Set'!R13='Office Set'!$B$39,('Office Set'!AJ13>0)),'Office Set'!T13,"") | K15: ='Office Set'!AJ13 -> 0 | L15: =IF(AND('Police Station'!R14='Police Station'!$B$40,('Police Station'!AJ14>0)),'Police Station'!T14,"") | M15: ='Police Station'!AJ14 -> 0 | N15: =IF(AND('8000 sqft'!R14='8000 sqft'!$B$40,('8000 sqft'!AJ14>0)),'8000 sqft'!T14,"") | O15: ='8000 sqft'!AJ14 -> 0 | P15: =IF(AND('Restaurant '!R14='Restaurant '!$B$40,('Restaurant '!AJ14>0)),'Restaurant '!T14,"") | Q15: ='Restaurant '!AJ14 -> 0 | R15: =IF(AND('Parsi Bungalow'!Y14='Parsi Bungalow'!$B$40,('Parsi Bungalow'!AQ14>0)),'Parsi Bungalow'!AA14,"") | S15: ='Parsi Bungalow'!AQ14 -> 0 | T15: =IF(AND('Parsi Bungalow'!BK14='Parsi Bungalow'!$B$40,('Parsi Bungalow'!CC14>0)),'Parsi Bungalow'!BM14,"") | U15: ='Parsi Bungalow'!CC14 -> 0 | V15: =IF(AND('Bungalow 2'!R14='Bungalow 2'!$B$40,('Bungalow 2'!AJ14>0)),'Bungalow 2'!T14,"") -> Rising Star | W15: ='Bungalow 2'!AJ14 -> 465 | X15: =IF(AND('Bungalow 2'!BD14='Bungalow 2'!$B$40,('Bungalow 2'!BV14>0)),'Bungalow 2'!BF14,"") | Y15: ='Bungalow 2'!BV14 -> 0 | Z15: =IF(AND('Villa Set '!Y14='Villa Set '!$B$40,('Villa Set '!AQ14>0)),'Villa Set '!AA14,"") | AA15: ='Villa Set '!AQ14 -> 0 | AB15: =IF(AND('Villa Set '!BK14='Villa Set '!$B$40,('Villa Set '!CC14>0)),'Villa Set '!BM14,"") -> Viniyard Films | AC15: ='Villa Set '!CC14 -> 38 | AD15: =IF(AND('Villa Set '!CW14='Villa Set '!$B$40,('Villa Set '!DO14>0)),'Villa Set '!CY14,"") | AE15: ='Villa Set '!DO14 -> 0 | AG15: ='Road Light'!R14 -> 0 | AH15: =IF(AND(Hill!R14=Hill!$B$40,(Hill!AJ14>0)),Hill!T14,"") | AI15: =Hill!AJ14 -> 0
A16: 12 | B16: =IF(AND(Hospital!R15=Hospital!$B$40,(Hospital!AJ15>0)),Hospital!T15,"") | C16: =Hospital!AJ15 -> 0 | D16: =IF(AND(Hospital!BD15=Hospital!$B$40,(Hospital!BV15>0)),Hospital!BF15,"") | E16: =Hospital!BV15 -> 0 | F16: =IF(AND('Bungalow 1'!R15='Bungalow 1'!$B$40,('Bungalow 1'!AJ15>0)),'Bungalow 1'!T15,"") -> Gulliver Motion Pictures LLP | G16: ='Bungalow 1'!AJ15 -> 590 | H16: =IF(AND('Bungalow 1'!BD15='Bungalow 1'!$B$40,('Bungalow 1'!BV15>0)),'Bungalow 1'!BF15,"") | I16: ='Bungalow 1'!BV15 -> 0 | J16: =IF(AND('Office Set'!R14='Office Set'!$B$39,('Office Set'!AJ14>0)),'Office Set'!T14,"") | K16: ='Office Set'!AJ14 -> 0 | L16: =IF(AND('Police Station'!R15='Police Station'!$B$40,('Police Station'!AJ15>0)),'Police Station'!T15,"") | M16: ='Police Station'!AJ15 -> 0 | N16: =IF(AND('8000 sqft'!R15='8000 sqft'!$B$40,('8000 sqft'!AJ15>0)),'8000 sqft'!T15,"") | O16: ='8000 sqft'!AJ15 -> 0 | P16: =IF(AND('Restaurant '!R15='Restaurant '!$B$40,('Restaurant '!AJ15>0)),'Restaurant '!T15,"") | Q16: ='Restaurant '!AJ15 -> 0 | R16: =IF(AND('Parsi Bungalow'!Y15='Parsi Bungalow'!$B$40,('Parsi Bungalow'!AQ15>0)),'Parsi Bungalow'!AA15,"") | S16: ='Parsi Bungalow'!AQ15 -> 0 | T16: =IF(AND('Parsi Bungalow'!BK15='Parsi Bungalow'!$B$40,('Parsi Bungalow'!CC15>0)),'Parsi Bungalow'!BM15,"") | U16: ='Parsi Bungalow'!CC15 -> 0 | V16: =IF(AND('Bungalow 2'!R15='Bungalow 2'!$B$40,('Bungalow 2'!AJ15>0)),'Bungalow 2'!T15,"") | W16: ='Bungalow 2'!AJ15 -> 0 | X16: =IF(AND('Bungalow 2'!BD15='Bungalow 2'!$B$40,('Bungalow 2'!BV15>0)),'Bungalow 2'!BF15,"") | Y16: ='Bungalow 2'!BV15 -> 0 | Z16: =IF(AND('Villa Set '!Y15='Villa Set '!$B$40,('Villa Set '!AQ15>0)),'Villa Set '!AA15,"") | AA16: ='Villa Set '!AQ15 -> 0 | AB16: =IF(AND('Villa Set '!BK15='Villa Set '!$B$40,('Villa Set '!CC15>0)),'Villa Set '!BM15,"") -> Viniyard Films | AC16: ='Villa Set '!CC15 -> 53 | AD16: =IF(AND('Villa Set '!CW15='Villa Set '!$B$40,('Villa Set '!DO15>0)),'Villa Set '!CY15,"") | AE16: ='Villa Set '!DO15 -> 0 | AG16: ='Road Light'!R15 -> 0 | AH16: =IF(AND(Hill!R15=Hill!$B$40,(Hill!AJ15>0)),Hill!T15,"") | AI16: =Hill!AJ15 -> 0
A17: 13 | B17: =IF(AND(Hospital!R16=Hospital!$B$40,(Hospital!AJ16>0)),Hospital!T16,"") | C17: =Hospital!AJ16 -> 0 | D17: =IF(AND(Hospital!BD16=Hospital!$B$40,(Hospital!BV16>0)),Hospital!BF16,"") | E17: =Hospital!BV16 -> 0 | F17: =IF(AND('Bungalow 1'!R16='Bungalow 1'!$B$40,('Bungalow 1'!AJ16>0)),'Bungalow 1'!T16,"") -> Gulliver Motion Pictures LLP | G17: ='Bungalow 1'!AJ16 -> 9 | H17: =IF(AND('Bungalow 1'!BD16='Bungalow 1'!$B$40,('Bungalow 1'!BV16>0)),'Bungalow 1'!BF16,"") | I17: ='Bungalow 1'!BV16 -> 0 | J17: =IF(AND('Office Set'!R15='Office Set'!$B$39,('Office Set'!AJ15>0)),'Office Set'!T15,"") | K17: ='Office Set'!AJ15 -> 0 | L17: =IF(AND('Police Station'!R16='Police Station'!$B$40,('Police Station'!AJ16>0)),'Police Station'!T16,"") | M17: ='Police Station'!AJ16 -> 0 | N17: =IF(AND('8000 sqft'!R16='8000 sqft'!$B$40,('8000 sqft'!AJ16>0)),'8000 sqft'!T16,"") | O17: ='8000 sqft'!AJ16 -> 0 | P17: =IF(AND('Restaurant '!R16='Restaurant '!$B$40,('Restaurant '!AJ16>0)),'Restaurant '!T16,"") | Q17: ='Restaurant '!AJ16 -> 0 | R17: =IF(AND('Parsi Bungalow'!Y16='Parsi Bungalow'!$B$40,('Parsi Bungalow'!AQ16>0)),'Parsi Bungalow'!AA16,"") | S17: ='Parsi Bungalow'!AQ16 -> 0 | T17: =IF(AND('Parsi Bungalow'!BK16='Parsi Bungalow'!$B$40,('Parsi Bungalow'!CC16>0)),'Parsi Bungalow'!BM16,"") | U17: ='Parsi Bungalow'!CC16 -> 0 | V17: =IF(AND('Bungalow 2'!R16='Bungalow 2'!$B$40,('Bungalow 2'!AJ16>0)),'Bungalow 2'!T16,"") | W17: ='Bungalow 2'!AJ16 -> 0 | X17: =IF(AND('Bungalow 2'!BD16='Bungalow 2'!$B$40,('Bungalow 2'!BV16>0)),'Bungalow 2'!BF16,"") | Y17: ='Bungalow 2'!BV16 -> 0 | Z17: =IF(AND('Villa Set '!Y16='Villa Set '!$B$40,('Villa Set '!AQ16>0)),'Villa Set '!AA16,"") | AA17: ='Villa Set '!AQ16 -> 0 | AB17: =IF(AND('Villa Set '!BK16='Villa Set '!$B$40,('Villa Set '!CC16>0)),'Villa Set '!BM16,"") -> Viniyard Films | AC17: ='Villa Set '!CC16 -> 51 | AD17: =IF(AND('Villa Set '!CW16='Villa Set '!$B$40,('Villa Set '!DO16>0)),'Villa Set '!CY16,"") | AE17: ='Villa Set '!DO16 -> 0 | AG17: ='Road Light'!R16 -> 0 | AH17: =IF(AND(Hill!R16=Hill!$B$40,(Hill!AJ16>0)),Hill!T16,"") | AI17: =Hill!AJ16 -> 0
... A35: 31 | B35: =IF(AND(Hospital!R34=Hospital!$B$40,(Hospital!AJ34>0)),Hospital!T34,"") | C35: =Hospital!AJ34 -> 0 | D35: =IF(AND(Hospital!BD34=Hospital!$B$40,(Hospital!BV34>0)),Hospital!BF34,"") | E35: =Hospital!BV34 -> 0 | F35: =IF(AND('Bungalow 1'!R34='Bungalow 1'!$B$40,('Bungalow 1'!AJ34>0)),'Bungalow 1'!T34,"") | G35: ='Bungalow 1'!AJ34 -> 0 | H35: =IF(AND('Bungalow 1'!BD34='Bungalow 1'!$B$40,('Bungalow 1'!BV34>0)),'Bungalow 1'!BF34,"") | I35: ='Bungalow 1'!BV34 -> 0 | J35: =IF(AND('Office Set'!R33='Office Set'!$B$39,('Office Set'!AJ33>0)),'Office Set'!T33,"") | K35: ='Office Set'!AJ33 -> 0 | L35: =IF(AND('Police Station'!R34='Police Station'!$B$40,('Police Station'!AJ34>0)),'Police Station'!T34,"") | M35: ='Police Station'!AJ34 -> 0 | N35: =IF(AND('8000 sqft'!R34='8000 sqft'!$B$40,('8000 sqft'!AJ34>0)),'8000 sqft'!T34,"") | O35: ='8000 sqft'!AJ34 -> 0 | P35: =IF(AND('Restaurant '!R34='Restaurant '!$B$40,('Restaurant '!AJ34>0)),'Restaurant '!T34,"") | Q35: ='Restaurant '!AJ34 -> 0 | R35: =IF(AND('Parsi Bungalow'!Y34='Parsi Bungalow'!$B$40,('Parsi Bungalow'!AQ34>0)),'Parsi Bungalow'!AA34,"") | S35: ='Parsi Bungalow'!AQ34 -> 0 | T35: =IF(AND('Parsi Bungalow'!BK34='Parsi Bungalow'!$B$40,('Parsi Bungalow'!CC34>0)),'Parsi Bungalow'!BM34,"") | U35: ='Parsi Bungalow'!CC34 -> 0 | V35: =IF(AND('Bungalow 2'!R34='Bungalow 2'!$B$40,('Bungalow 2'!AJ34>0)),'Bungalow 2'!T34,"") | W35: ='Bungalow 2'!AJ34 -> 0 | X35: =IF(AND('Bungalow 2'!BD34='Bungalow 2'!$B$40,('Bungalow 2'!BV34>0)),'Bungalow 2'!BF34,"") | Y35: ='Bungalow 2'!BV34 -> 0 | Z35: =IF(AND('Villa Set '!Y34='Villa Set '!$B$40,('Villa Set '!AQ34>0)),'Villa Set '!AA34,"") | AA35: ='Villa Set '!AQ34 -> 0 | AB35: =IF(AND('Villa Set '!BK34='Villa Set '!$B$40,('Villa Set '!CC34>0)),'Villa Set '!BM34,"") | AC35: ='Villa Set '!CC34 -> 0 | AD35: =IF(AND('Villa Set '!CW34='Villa Set '!$B$40,('Villa Set '!DO34>0)),'Villa Set '!CY34,"") | AE35: ='Villa Set '!DO34 -> 0 | AG35: ='Road Light'!R34 -> 0 | AH35: =IF(AND(Hill!R34=Hill!$B$40,(Hill!AJ34>0)),Hill!T34,"") | AI35: =Hill!AJ34 -> 0
A36: 1. Total Unit Consumption of Above Meter As Per Details | C36: =SUM(C5:C35) -> 2163 | E36: =SUM(E5:E35) -> 315 | G36: =SUM(G5:G35) -> 4921 | I36: =SUM(I5:I35) -> 40 | K36: =SUM(K5:K35) -> 1665 | M36: =SUM(M5:M35) -> 584 | O36: =SUM(O5:O34) -> 961 | Q36: =SUM(Q5:Q35) -> 1646 | S36: =SUM(S5:S35) -> 967 | U36: =SUM(U5:U35) -> 557 | W36: =SUM(W5:W35) -> 5142 | Y36: =SUM(Y5:Y35) -> 0 | AA36: =SUM(AA5:AA35) -> 6416 | AC36: =SUM(AC5:AC35) -> 3018 | AE36: =SUM(AE5:AE35) -> 0 | AG36: =SUM(AG5:AG35) -> 0 | AI36: =SUM(AI5:AI35) -> 0
A37: 2. Total Unit Consumption of Above Meter As per Sheet Details. | C37: =Hospital!AJ35 -> 2163 | E37: =Hospital!BV35 -> 315 | G37: ='Bungalow 1'!AJ35 -> 4921 | I37: ='Bungalow 1'!BV35 -> 40 | K37: ='Office Set'!AJ34 -> 1665 | M37: ='Police Station'!AJ35 -> 584 | O37: ='8000 sqft'!AJ35 -> 961 | Q37: ='Restaurant '!AJ35 -> 1646 | S37: ='Parsi Bungalow'!AQ35 -> 967 | U37: ='Parsi Bungalow'!CC35 -> 557 | W37: ='Bungalow 2'!AJ35 -> 5142 | Y37: ='Bungalow 2'!BV35 -> 0 | AA37: ='Villa Set '!AQ35 -> 6416 | AC37: ='Villa Set '!CC35 -> 3018 | AE37: ='Villa Set '!DO35 -> 0 | AG37: ='Road Light'!R35 -> 0 | AI37: =Hill!AJ35 -> 0
A38: Variation between 1 and 2 (Ideally it should be Zero) | C38: =C36-C37 -> 0 | E38: =E36-E37 -> 0 | G38: =G36-G37 -> 0 | I38: =I36-I37 -> 0 | K38: =K36-K37 -> 0 | M38: =M36-M37 -> 0 | O38: =O36-O37 -> 0 | Q38: =Q36-Q37 -> 0 | S38: =S36-S37 -> 0 | U38: =U36-U37 -> 0 | W38: =W36-W37 -> 0 | Y38: =Y36-Y37 -> 0 | AA38: =AA36-AA37 -> 0 | AC38: =AC36-AC37 -> 0 | AE38: =AE36-AE37 -> 0 | AG38: =AG36-AG37 -> 0 | AI38: =AI36-AI37 -> 0
A40: Unit Consumption of Different Energy Meter Billed To Ellora Account Used by Production Team/Ellora Team
A42: Day | B42: Meter Name - Hospital LT With Makeup Room 201,202 & 203 | D42: Meter Name - Hospital Out Door | F42: Meter Name -Bungalow 1 LT | H42: Meter Name - Bungalow 1 Out Door | J42: Meter Name - Office Set | L42: Meter Name - Police Station | N42: Meter Name - 8000 sqft | P42: Meter Name - Restaurant | R42: Meter Name - Parsi Bungalow AC | T42: Meter Name - Parsi Bungalow Light | V42: Meter Name - Bungalow 2 LT | X42: Meter Name - Bungalow 2 Makeup Room | Z42: Meter Name - Villa Set AC | AB42: Meter Name - Villa Set Light | AD42: Meter Name - Villa Set Out Door | AF42: Meter Name - Road Light | AH42: Meter Name - Hill
B43: Using For | C43: Unit | D43: Using For | E43: Unit | F43: Using For | G43: Unit | H43: Using For | I43: Unit | J43: Using For | K43: Unit | L43: Using For | M43: Unit | N43: Using For | O43: Unit | P43: Using For | Q43: Unit | R43: Using For | S43: Unit | T43: Using For | U43: Unit | V43: Using For | W43: Unit | X43: Using For | Y43: Unit | Z43: Using For | AA43: Unit | AB43: Using For | AC43: Unit | AD43: Using For | AE43: Unit | AF43: Using For | AG43: Unit | AH43: Using For | AI43: Unit
A44: 1 | B44: =IF(AND(Hospital!AV4>0,(OR(Hospital!R4=Hospital!$B$39,(Hospital!R4=Hospital!$B$40)))),Hospital!S4,"") | C44: =Hospital!AV4 -> 0 | D44: =IF(AND(Hospital!CH4>0,(OR(Hospital!BD4=Hospital!$B$39,(Hospital!BD4=Hospital!$B$40)))),Hospital!BE4,"") | E44: =Hospital!CH4 -> 0 | F44: =IF(AND('Bungalow 1'!AV4>0*(OR('Bungalow 1'!R4='Bungalow 1'!$B$39,('Bungalow 1'!R4='Bungalow 1'!$B$40)))),'Bungalow 1'!S4,"") | G44: ='Bungalow 1'!AV4 -> 0 | H44: =IF(AND('Bungalow 1'!CH4>0,(OR('Bungalow 1'!BD4='Bungalow 1'!$B$39,('Bungalow 1'!BD4='Bungalow 1'!$B$40)))),'Bungalow 1'!BE4,"") | I44: ='Bungalow 1'!CH4 -> 0 | J44: =IF(AND('Office Set'!AV3>0,(OR('Office Set'!R3='Office Set'!$B$38,('Office Set'!R3='Office Set'!$B$39)))),'Office Set'!S3,"") | K44: ='Office Set'!AV3 -> 0 | L44: =IF(AND('Police Station'!AV4>0,(OR('Police Station'!R4='Police Station'!$B$39,('Police Station'!R4='Police Station'!$B$40)))),'Police Station'!S4,"") | M44: ='Police Station'!AV4 -> 0 | N44: =IF(AND('8000 sqft'!AV4>0,(OR('8000 sqft'!R4='8000 sqft'!$B$39,('8000 sqft'!R4='8000 sqft'!$B$40)))),'8000 sqft'!S4,"") -> Makeup Room | O44: ='8000 sqft'!AV4 -> 7 | P44: =IF(AND('Restaurant '!AV4>0,(OR('Restaurant '!R4='Restaurant '!$B$39,('Restaurant '!R4='Restaurant '!$B$40)))),'Restaurant '!S4,"") -> Makeup Room | Q44: ='Restaurant '!AV4 -> 47 | R44: =IF(AND('Parsi Bungalow'!BC4>0,(OR('Parsi Bungalow'!Y4='Parsi Bungalow'!$B$39,('Parsi Bungalow'!Y4='Parsi Bungalow'!$B$40)))),'Parsi Bungalow'!Z4,"") | S44: ='Parsi Bungalow'!BC4 -> 0 | T44: =IF(AND('Parsi Bungalow'!CO4>0,(OR('Parsi Bungalow'!BK4='Parsi Bungalow'!$B$39,('Parsi Bungalow'!BK4='Parsi Bungalow'!$B$40)))),'Parsi Bungalow'!BL4,"") -> Ellora HK Team | U44: ='Parsi Bungalow'!CO4 -> 1 | V44: =IF(AND('Bungalow 2'!AV4>0,(OR('Bungalow 2'!R4='Bungalow 2'!$B$39,('Bungalow 2'!R4='Bungalow 2'!$B$40)))),'Bungalow 2'!S4,"") | W44: ='Bungalow 2'!AV4 -> 0 | X44: =IF(AND('Bungalow 2'!CH4>0,(OR('Bungalow 2'!BD4='Bungalow 2'!$B$39,('Bungalow 2'!BD4='Bungalow 2'!$B$40)))),'Bungalow 2'!BE4,"") -> Makeup Room | Y44: ='Bungalow 2'!CH4 -> 32 | Z44: =IF(AND('Villa Set '!BC4>0,(OR('Villa Set '!Y4='Villa Set '!$B$39,('Villa Set '!Y4='Villa Set '!$B$40)))),'Villa Set '!Z4,"") | AA44: ='Villa Set '!BC4 -> 0 | AB44: =IF(AND('Villa Set '!CO4>0,(OR('Villa Set '!BK4='Villa Set '!$B$39,('Villa Set '!BK4='Villa Set '!$B$40)))),'Villa Set '!BL4,"") | AC44: ='Villa Set '!CO4 -> 0 | AD44: =IF(AND('Villa Set '!EA4>0,(OR('Villa Set '!CW4='Villa Set '!$B$39,('Villa Set '!CW4='Villa Set '!$B$40)))),'Villa Set '!CX4,"") | AE44: ='Villa Set '!EA4 -> 0 | AF44: Ellora Infra/Maintenance Others | AG44: ='Road Light'!J4-'Road Light'!R4 -> 57 | AH44: =IF(AND(Hill!AV4>0,(OR(Hill!R4=Hill!$B$39,(Hill!R4=Hill!$B$40)))),Hill!S4,"") | AI44: =Hill!AV4 -> 0
A45: 2 | B45: =IF(AND(Hospital!AV5>0,(OR(Hospital!R5=Hospital!$B$39,(Hospital!R5=Hospital!$B$40)))),Hospital!S5,"") -> Ellora AC Team | C45: =Hospital!AV5 -> 17 | D45: =IF(AND(Hospital!CH5>0,(OR(Hospital!BD5=Hospital!$B$39,(Hospital!BD5=Hospital!$B$40)))),Hospital!BE5,"") | E45: =Hospital!CH5 -> 0 | F45: =IF(AND('Bungalow 1'!AV5>0*(OR('Bungalow 1'!R5='Bungalow 1'!$B$39,('Bungalow 1'!R5='Bungalow 1'!$B$40)))),'Bungalow 1'!S5,"") | G45: ='Bungalow 1'!AV5 -> 0 | H45: =IF(AND('Bungalow 1'!CH5>0,(OR('Bungalow 1'!BD5='Bungalow 1'!$B$39,('Bungalow 1'!BD5='Bungalow 1'!$B$40)))),'Bungalow 1'!BE5,"") | I45: ='Bungalow 1'!CH5 -> 0 | J45: =IF(AND('Office Set'!AV4>0,(OR('Office Set'!R4='Office Set'!$B$38,('Office Set'!R4='Office Set'!$B$39)))),'Office Set'!S4,"") -> Ellora HK Team | K45: ='Office Set'!AV4 -> 4 | L45: =IF(AND('Police Station'!AV5>0,(OR('Police Station'!R5='Police Station'!$B$39,('Police Station'!R5='Police Station'!$B$40)))),'Police Station'!S5,"") | M45: ='Police Station'!AV5 -> 0 | N45: =IF(AND('8000 sqft'!AV5>0,(OR('8000 sqft'!R5='8000 sqft'!$B$39,('8000 sqft'!R5='8000 sqft'!$B$40)))),'8000 sqft'!S5,"") -> Makeup Room | O45: ='8000 sqft'!AV5 -> 4 | P45: =IF(AND('Restaurant '!AV5>0,(OR('Restaurant '!R5='Restaurant '!$B$39,('Restaurant '!R5='Restaurant '!$B$40)))),'Restaurant '!S5,"") -> Ellora HK Team | Q45: ='Restaurant '!AV5 -> 14 | R45: =IF(AND('Parsi Bungalow'!BC5>0,(OR('Parsi Bungalow'!Y5='Parsi Bungalow'!$B$39,('Parsi Bungalow'!Y5='Parsi Bungalow'!$B$40)))),'Parsi Bungalow'!Z5,"") | S45: ='Parsi Bungalow'!BC5 -> 0 | T45: =IF(AND('Parsi Bungalow'!CO5>0,(OR('Parsi Bungalow'!BK5='Parsi Bungalow'!$B$39,('Parsi Bungalow'!BK5='Parsi Bungalow'!$B$40)))),'Parsi Bungalow'!BL5,"") -> Ellora HK Team | U45: ='Parsi Bungalow'!CO5 -> 3 | V45: =IF(AND('Bungalow 2'!AV5>0,(OR('Bungalow 2'!R5='Bungalow 2'!$B$39,('Bungalow 2'!R5='Bungalow 2'!$B$40)))),'Bungalow 2'!S5,"") -> Ellora HK Team | W45: ='Bungalow 2'!AV5 -> 5 | X45: =IF(AND('Bungalow 2'!CH5>0,(OR('Bungalow 2'!BD5='Bungalow 2'!$B$39,('Bungalow 2'!BD5='Bungalow 2'!$B$40)))),'Bungalow 2'!BE5,"") -> Makeup Room | Y45: ='Bungalow 2'!CH5 -> 47 | Z45: =IF(AND('Villa Set '!BC5>0,(OR('Villa Set '!Y5='Villa Set '!$B$39,('Villa Set '!Y5='Villa Set '!$B$40)))),'Villa Set '!Z5,"") | AA45: ='Villa Set '!BC5 -> 0 | AB45: =IF(AND('Villa Set '!CO5>0,(OR('Villa Set '!BK5='Villa Set '!$B$39,('Villa Set '!BK5='Villa Set '!$B$40)))),'Villa Set '!BL5,"") | AC45: ='Villa Set '!CO5 -> 0 | AD45: =IF(AND('Villa Set '!EA5>0,(OR('Villa Set '!CW5='Villa Set '!$B$39,('Villa Set '!CW5='Villa Set '!$B$40)))),'Villa Set '!CX5,"") | AE45: ='Villa Set '!EA5 -> 0 | AF45: Ellora Infra/Maintenance Others | AG45: ='Road Light'!J5-'Road Light'!R5 -> 52 | AH45: =IF(AND(Hill!AV5>0,(OR(Hill!R5=Hill!$B$39,(Hill!R5=Hill!$B$40)))),Hill!S5,"") | AI45: =Hill!AV5 -> 0
A46: 3 | B46: =IF(AND(Hospital!AV6>0,(OR(Hospital!R6=Hospital!$B$39,(Hospital!R6=Hospital!$B$40)))),Hospital!S6,"") | C46: =Hospital!AV6 -> 0 | D46: =IF(AND(Hospital!CH6>0,(OR(Hospital!BD6=Hospital!$B$39,(Hospital!BD6=Hospital!$B$40)))),Hospital!BE6,"") | E46: =Hospital!CH6 -> 0 | F46: =IF(AND('Bungalow 1'!AV6>0*(OR('Bungalow 1'!R6='Bungalow 1'!$B$39,('Bungalow 1'!R6='Bungalow 1'!$B$40)))),'Bungalow 1'!S6,"") | G46: ='Bungalow 1'!AV6 -> 0 | H46: =IF(AND('Bungalow 1'!CH6>0,(OR('Bungalow 1'!BD6='Bungalow 1'!$B$39,('Bungalow 1'!BD6='Bungalow 1'!$B$40)))),'Bungalow 1'!BE6,"") | I46: ='Bungalow 1'!CH6 -> 0 | J46: =IF(AND('Office Set'!AV5>0,(OR('Office Set'!R5='Office Set'!$B$38,('Office Set'!R5='Office Set'!$B$39)))),'Office Set'!S5,"") | K46: ='Office Set'!AV5 -> 0 | L46: =IF(AND('Police Station'!AV6>0,(OR('Police Station'!R6='Police Station'!$B$39,('Police Station'!R6='Police Station'!$B$40)))),'Police Station'!S6,"") | M46: ='Police Station'!AV6 -> 0 | N46: =IF(AND('8000 sqft'!AV6>0,(OR('8000 sqft'!R6='8000 sqft'!$B$39,('8000 sqft'!R6='8000 sqft'!$B$40)))),'8000 sqft'!S6,"") -> Makeup Room | O46: ='8000 sqft'!AV6 -> 3 | P46: =IF(AND('Restaurant '!AV6>0,(OR('Restaurant '!R6='Restaurant '!$B$39,('Restaurant '!R6='Restaurant '!$B$40)))),'Restaurant '!S6,"") | Q46: ='Restaurant '!AV6 -> 0 | R46: =IF(AND('Parsi Bungalow'!BC6>0,(OR('Parsi Bungalow'!Y6='Parsi Bungalow'!$B$39,('Parsi Bungalow'!Y6='Parsi Bungalow'!$B$40)))),'Parsi Bungalow'!Z6,"") -> Ellora HK Team | S46: ='Parsi Bungalow'!BC6 -> 1 | T46: =IF(AND('Parsi Bungalow'!CO6>0,(OR('Parsi Bungalow'!BK6='Parsi Bungalow'!$B$39,('Parsi Bungalow'!BK6='Parsi Bungalow'!$B$40)))),'Parsi Bungalow'!BL6,"") | U46: ='Parsi Bungalow'!CO6 -> 0 | V46: =IF(AND('Bungalow 2'!AV6>0,(OR('Bungalow 2'!R6='Bungalow 2'!$B$39,('Bungalow 2'!R6='Bungalow 2'!$B$40)))),'Bungalow 2'!S6,"") -> Ellora HK Team | W46: ='Bungalow 2'!AV6 -> 1 | X46: =IF(AND('Bungalow 2'!CH6>0,(OR('Bungalow 2'!BD6='Bungalow 2'!$B$39,('Bungalow 2'!BD6='Bungalow 2'!$B$40)))),'Bungalow 2'!BE6,"") -> Makeup Room | Y46: ='Bungalow 2'!CH6 -> 43 | Z46: =IF(AND('Villa Set '!BC6>0,(OR('Villa Set '!Y6='Villa Set '!$B$39,('Villa Set '!Y6='Villa Set '!$B$40)))),'Villa Set '!Z6,"") | AA46: ='Villa Set '!BC6 -> 0 | AB46: =IF(AND('Villa Set '!CO6>0,(OR('Villa Set '!BK6='Villa Set '!$B$39,('Villa Set '!BK6='Villa Set '!$B$40)))),'Villa Set '!BL6,"") | AC46: ='Villa Set '!CO6 -> 0 | AD46: =IF(AND('Villa Set '!EA6>0,(OR('Villa Set '!CW6='Villa Set '!$B$39,('Villa Set '!CW6='Villa Set '!$B$40)))),'Villa Set '!CX6,"") | AE46: ='Villa Set '!EA6 -> 0 | AF46: Ellora Infra/Maintenance Others | AG46: ='Road Light'!J6-'Road Light'!R6 -> 55 | AH46: =IF(AND(Hill!AV6>0,(OR(Hill!R6=Hill!$B$39,(Hill!R6=Hill!$B$40)))),Hill!S6,"") | AI46: =Hill!AV6 -> 0
A47: 4 | B47: =IF(AND(Hospital!AV7>0,(OR(Hospital!R7=Hospital!$B$39,(Hospital!R7=Hospital!$B$40)))),Hospital!S7,"") -> Makeup Room | C47: =Hospital!AV7 -> 36 | D47: =IF(AND(Hospital!CH7>0,(OR(Hospital!BD7=Hospital!$B$39,(Hospital!BD7=Hospital!$B$40)))),Hospital!BE7,"") | E47: =Hospital!CH7 -> 0 | F47: =IF(AND('Bungalow 1'!AV7>0*(OR('Bungalow 1'!R7='Bungalow 1'!$B$39,('Bungalow 1'!R7='Bungalow 1'!$B$40)))),'Bungalow 1'!S7,"") | G47: ='Bungalow 1'!AV7 -> 0 | H47: =IF(AND('Bungalow 1'!CH7>0,(OR('Bungalow 1'!BD7='Bungalow 1'!$B$39,('Bungalow 1'!BD7='Bungalow 1'!$B$40)))),'Bungalow 1'!BE7,"") | I47: ='Bungalow 1'!CH7 -> 0 | J47: =IF(AND('Office Set'!AV6>0,(OR('Office Set'!R6='Office Set'!$B$38,('Office Set'!R6='Office Set'!$B$39)))),'Office Set'!S6,"") -> Ellora HK Team | K47: ='Office Set'!AV6 -> 10 | L47: =IF(AND('Police Station'!AV7>0,(OR('Police Station'!R7='Police Station'!$B$39,('Police Station'!R7='Police Station'!$B$40)))),'Police Station'!S7,"") | M47: ='Police Station'!AV7 -> 0 | N47: =IF(AND('8000 sqft'!AV7>0,(OR('8000 sqft'!R7='8000 sqft'!$B$39,('8000 sqft'!R7='8000 sqft'!$B$40)))),'8000 sqft'!S7,"") -> Makeup Room | O47: ='8000 sqft'!AV7 -> 10 | P47: =IF(AND('Restaurant '!AV7>0,(OR('Restaurant '!R7='Restaurant '!$B$39,('Restaurant '!R7='Restaurant '!$B$40)))),'Restaurant '!S7,"") -> Ellora Reiki Purpose | Q47: ='Restaurant '!AV7 -> 10 | R47: =IF(AND('Parsi Bungalow'!BC7>0,(OR('Parsi Bungalow'!Y7='Parsi Bungalow'!$B$39,('Parsi Bungalow'!Y7='Parsi Bungalow'!$B$40)))),'Parsi Bungalow'!Z7,"") | S47: ='Parsi Bungalow'!BC7 -> 0 | T47: =IF(AND('Parsi Bungalow'!CO7>0,(OR('Parsi Bungalow'!BK7='Parsi Bungalow'!$B$39,('Parsi Bungalow'!BK7='Parsi Bungalow'!$B$40)))),'Parsi Bungalow'!BL7,"") -> Ellora HK Team | U47: ='Parsi Bungalow'!CO7 -> 8 | V47: =IF(AND('Bungalow 2'!AV7>0,(OR('Bungalow 2'!R7='Bungalow 2'!$B$39,('Bungalow 2'!R7='Bungalow 2'!$B$40)))),'Bungalow 2'!S7,"") -> Ellora HK Team | W47: ='Bungalow 2'!AV7 -> 1 | X47: =IF(AND('Bungalow 2'!CH7>0,(OR('Bungalow 2'!BD7='Bungalow 2'!$B$39,('Bungalow 2'!BD7='Bungalow 2'!$B$40)))),'Bungalow 2'!BE7,"") -> Makeup Room | Y47: ='Bungalow 2'!CH7 -> 37 | Z47: =IF(AND('Villa Set '!BC7>0,(OR('Villa Set '!Y7='Villa Set '!$B$39,('Villa Set '!Y7='Villa Set '!$B$40)))),'Villa Set '!Z7,"") -> Ellora HK Team | AA47: ='Villa Set '!BC7 -> 17 | AB47: =IF(AND('Villa Set '!CO7>0,(OR('Villa Set '!BK7='Villa Set '!$B$39,('Villa Set '!BK7='Villa Set '!$B$40)))),'Villa Set '!BL7,"") -> Ellora HK Team | AC47: ='Villa Set '!CO7 -> 3 | AD47: =IF(AND('Villa Set '!EA7>0,(OR('Villa Set '!CW7='Villa Set '!$B$39,('Villa Set '!CW7='Villa Set '!$B$40)))),'Villa Set '!CX7,"") | AE47: ='Villa Set '!EA7 -> 0 | AF47: Ellora Infra/Maintenance Others | AG47: ='Road Light'!J7-'Road Light'!R7 -> 29 | AH47: =IF(AND(Hill!AV7>0,(OR(Hill!R7=Hill!$B$39,(Hill!R7=Hill!$B$40)))),Hill!S7,"") | AI47: =Hill!AV7 -> 0
A48: 5 | B48: =IF(AND(Hospital!AV8>0,(OR(Hospital!R8=Hospital!$B$39,(Hospital!R8=Hospital!$B$40)))),Hospital!S8,"") | C48: =Hospital!AV8 -> 0 | D48: =IF(AND(Hospital!CH8>0,(OR(Hospital!BD8=Hospital!$B$39,(Hospital!BD8=Hospital!$B$40)))),Hospital!BE8,"") | E48: =Hospital!CH8 -> 0 | F48: =IF(AND('Bungalow 1'!AV8>0*(OR('Bungalow 1'!R8='Bungalow 1'!$B$39,('Bungalow 1'!R8='Bungalow 1'!$B$40)))),'Bungalow 1'!S8,"") | G48: ='Bungalow 1'!AV8 -> 0 | H48: =IF(AND('Bungalow 1'!CH8>0,(OR('Bungalow 1'!BD8='Bungalow 1'!$B$39,('Bungalow 1'!BD8='Bungalow 1'!$B$40)))),'Bungalow 1'!BE8,"") | I48: ='Bungalow 1'!CH8 -> 0 | J48: =IF(AND('Office Set'!AV7>0,(OR('Office Set'!R7='Office Set'!$B$38,('Office Set'!R7='Office Set'!$B$39)))),'Office Set'!S7,"") -> Ellora HK Team | K48: ='Office Set'!AV7 -> 4 | L48: =IF(AND('Police Station'!AV8>0,(OR('Police Station'!R8='Police Station'!$B$39,('Police Station'!R8='Police Station'!$B$40)))),'Police Station'!S8,"") | M48: ='Police Station'!AV8 -> 0 | N48: =IF(AND('8000 sqft'!AV8>0,(OR('8000 sqft'!R8='8000 sqft'!$B$39,('8000 sqft'!R8='8000 sqft'!$B$40)))),'8000 sqft'!S8,"") -> Makeup Room | O48: ='8000 sqft'!AV8 -> 16 | P48: =IF(AND('Restaurant '!AV8>0,(OR('Restaurant '!R8='Restaurant '!$B$39,('Restaurant '!R8='Restaurant '!$B$40)))),'Restaurant '!S8,"") | Q48: ='Restaurant '!AV8 -> 0 | R48: =IF(AND('Parsi Bungalow'!BC8>0,(OR('Parsi Bungalow'!Y8='Parsi Bungalow'!$B$39,('Parsi Bungalow'!Y8='Parsi Bungalow'!$B$40)))),'Parsi Bungalow'!Z8,"") | S48: ='Parsi Bungalow'!BC8 -> 0 | T48: =IF(AND('Parsi Bungalow'!CO8>0,(OR('Parsi Bungalow'!BK8='Parsi Bungalow'!$B$39,('Parsi Bungalow'!BK8='Parsi Bungalow'!$B$40)))),'Parsi Bungalow'!BL8,"") -> Ellora HK Team | U48: ='Parsi Bungalow'!CO8 -> 2 | V48: =IF(AND('Bungalow 2'!AV8>0,(OR('Bungalow 2'!R8='Bungalow 2'!$B$39,('Bungalow 2'!R8='Bungalow 2'!$B$40)))),'Bungalow 2'!S8,"") -> Ellora HK Team | W48: ='Bungalow 2'!AV8 -> 2 | X48: =IF(AND('Bungalow 2'!CH8>0,(OR('Bungalow 2'!BD8='Bungalow 2'!$B$39,('Bungalow 2'!BD8='Bungalow 2'!$B$40)))),'Bungalow 2'!BE8,"") -> Makeup Room | Y48: ='Bungalow 2'!CH8 -> 26 | Z48: =IF(AND('Villa Set '!BC8>0,(OR('Villa Set '!Y8='Villa Set '!$B$39,('Villa Set '!Y8='Villa Set '!$B$40)))),'Villa Set '!Z8,"") | AA48: ='Villa Set '!BC8 -> 0 | AB48: =IF(AND('Villa Set '!CO8>0,(OR('Villa Set '!BK8='Villa Set '!$B$39,('Villa Set '!BK8='Villa Set '!$B$40)))),'Villa Set '!BL8,"") | AC48: ='Villa Set '!CO8 -> 0 | AD48: =IF(AND('Villa Set '!EA8>0,(OR('Villa Set '!CW8='Villa Set '!$B$39,('Villa Set '!CW8='Villa Set '!$B$40)))),'Villa Set '!CX8,"") | AE48: ='Villa Set '!EA8 -> 0 | AF48: Ellora Infra/Maintenance Others | AG48: ='Road Light'!J8-'Road Light'!R8 -> 61 | AH48: =IF(AND(Hill!AV8>0,(OR(Hill!R8=Hill!$B$39,(Hill!R8=Hill!$B$40)))),Hill!S8,"") | AI48: =Hill!AV8 -> 0
A49: 6 | B49: =IF(AND(Hospital!AV9>0,(OR(Hospital!R9=Hospital!$B$39,(Hospital!R9=Hospital!$B$40)))),Hospital!S9,"") | C49: =Hospital!AV9 -> 0 | D49: =IF(AND(Hospital!CH9>0,(OR(Hospital!BD9=Hospital!$B$39,(Hospital!BD9=Hospital!$B$40)))),Hospital!BE9,"") | E49: =Hospital!CH9 -> 0 | F49: =IF(AND('Bungalow 1'!AV9>0*(OR('Bungalow 1'!R9='Bungalow 1'!$B$39,('Bungalow 1'!R9='Bungalow 1'!$B$40)))),'Bungalow 1'!S9,"") | G49: ='Bungalow 1'!AV9 -> 0 | H49: =IF(AND('Bungalow 1'!CH9>0,(OR('Bungalow 1'!BD9='Bungalow 1'!$B$39,('Bungalow 1'!BD9='Bungalow 1'!$B$40)))),'Bungalow 1'!BE9,"") | I49: ='Bungalow 1'!CH9 -> 0 | J49: =IF(AND('Office Set'!AV8>0,(OR('Office Set'!R8='Office Set'!$B$38,('Office Set'!R8='Office Set'!$B$39)))),'Office Set'!S8,"") | K49: ='Office Set'!AV8 -> 0 | L49: =IF(AND('Police Station'!AV9>0,(OR('Police Station'!R9='Police Station'!$B$39,('Police Station'!R9='Police Station'!$B$40)))),'Police Station'!S9,"") | M49: ='Police Station'!AV9 -> 0 | N49: =IF(AND('8000 sqft'!AV9>0,(OR('8000 sqft'!R9='8000 sqft'!$B$39,('8000 sqft'!R9='8000 sqft'!$B$40)))),'8000 sqft'!S9,"") -> Makeup Room | O49: ='8000 sqft'!AV9 -> 17 | P49: =IF(AND('Restaurant '!AV9>0,(OR('Restaurant '!R9='Restaurant '!$B$39,('Restaurant '!R9='Restaurant '!$B$40)))),'Restaurant '!S9,"") | Q49: ='Restaurant '!AV9 -> 0 | R49: =IF(AND('Parsi Bungalow'!BC9>0,(OR('Parsi Bungalow'!Y9='Parsi Bungalow'!$B$39,('Parsi Bungalow'!Y9='Parsi Bungalow'!$B$40)))),'Parsi Bungalow'!Z9,"") | S49: ='Parsi Bungalow'!BC9 -> 0 | T49: =IF(AND('Parsi Bungalow'!CO9>0,(OR('Parsi Bungalow'!BK9='Parsi Bungalow'!$B$39,('Parsi Bungalow'!BK9='Parsi Bungalow'!$B$40)))),'Parsi Bungalow'!BL9,"") | U49: ='Parsi Bungalow'!CO9 -> 0 | V49: =IF(AND('Bungalow 2'!AV9>0,(OR('Bungalow 2'!R9='Bungalow 2'!$B$39,('Bungalow 2'!R9='Bungalow 2'!$B$40)))),'Bungalow 2'!S9,"") -> Shooting | W49: ='Bungalow 2'!AV9 -> 300 | X49: =IF(AND('Bungalow 2'!CH9>0,(OR('Bungalow 2'!BD9='Bungalow 2'!$B$39,('Bungalow 2'!BD9='Bungalow 2'!$B$40)))),'Bungalow 2'!BE9,"") -> Makeup Room | Y49: ='Bungalow 2'!CH9 -> 61 | Z49: =IF(AND('Villa Set '!BC9>0,(OR('Villa Set '!Y9='Villa Set '!$B$39,('Villa Set '!Y9='Villa Set '!$B$40)))),'Villa Set '!Z9,"") | AA49: ='Villa Set '!BC9 -> 0 | AB49: =IF(AND('Villa Set '!CO9>0,(OR('Villa Set '!BK9='Villa Set '!$B$39,('Villa Set '!BK9='Villa Set '!$B$40)))),'Villa Set '!BL9,"") -> Ellora HK Team | AC49: ='Villa Set '!CO9 -> 7 | AD49: =IF(AND('Villa Set '!EA9>0,(OR('Villa Set '!CW9='Villa Set '!$B$39,('Villa Set '!CW9='Villa Set '!$B$40)))),'Villa Set '!CX9,"") | AE49: ='Villa Set '!EA9 -> 0 | AF49: Ellora Infra/Maintenance Others | AG49: ='Road Light'!J9-'Road Light'!R9 -> 52 | AH49: =IF(AND(Hill!AV9>0,(OR(Hill!R9=Hill!$B$39,(Hill!R9=Hill!$B$40)))),Hill!S9,"") | AI49: =Hill!AV9 -> 0
A50: 7 | B50: =IF(AND(Hospital!AV10>0,(OR(Hospital!R10=Hospital!$B$39,(Hospital!R10=Hospital!$B$40)))),Hospital!S10,"") | C50: =Hospital!AV10 -> 0 | D50: =IF(AND(Hospital!CH10>0,(OR(Hospital!BD10=Hospital!$B$39,(Hospital!BD10=Hospital!$B$40)))),Hospital!BE10,"") | E50: =Hospital!CH10 -> 0 | F50: =IF(AND('Bungalow 1'!AV10>0*(OR('Bungalow 1'!R10='Bungalow 1'!$B$39,('Bungalow 1'!R10='Bungalow 1'!$B$40)))),'Bungalow 1'!S10,"") | G50: ='Bungalow 1'!AV10 -> 0 | H50: =IF(AND('Bungalow 1'!CH10>0,(OR('Bungalow 1'!BD10='Bungalow 1'!$B$39,('Bungalow 1'!BD10='Bungalow 1'!$B$40)))),'Bungalow 1'!BE10,"") | I50: ='Bungalow 1'!CH10 -> 0 | J50: =IF(AND('Office Set'!AV9>0,(OR('Office Set'!R9='Office Set'!$B$38,('Office Set'!R9='Office Set'!$B$39)))),'Office Set'!S9,"") -> Ellora HK Team | K50: ='Office Set'!AV9 -> 2 | L50: =IF(AND('Police Station'!AV10>0,(OR('Police Station'!R10='Police Station'!$B$39,('Police Station'!R10='Police Station'!$B$40)))),'Police Station'!S10,"") | M50: ='Police Station'!AV10 -> 0 | N50: =IF(AND('8000 sqft'!AV10>0,(OR('8000 sqft'!R10='8000 sqft'!$B$39,('8000 sqft'!R10='8000 sqft'!$B$40)))),'8000 sqft'!S10,"") -> Makeup Room | O50: ='8000 sqft'!AV10 -> 12 | P50: =IF(AND('Restaurant '!AV10>0,(OR('Restaurant '!R10='Restaurant '!$B$39,('Restaurant '!R10='Restaurant '!$B$40)))),'Restaurant '!S10,"") | Q50: ='Restaurant '!AV10 -> 0 | R50: =IF(AND('Parsi Bungalow'!BC10>0,(OR('Parsi Bungalow'!Y10='Parsi Bungalow'!$B$39,('Parsi Bungalow'!Y10='Parsi Bungalow'!$B$40)))),'Parsi Bungalow'!Z10,"") | S50: ='Parsi Bungalow'!BC10 -> 0 | T50: =IF(AND('Parsi Bungalow'!CO10>0,(OR('Parsi Bungalow'!BK10='Parsi Bungalow'!$B$39,('Parsi Bungalow'!BK10='Parsi Bungalow'!$B$40)))),'Parsi Bungalow'!BL10,"") -> Ellora HK Team | U50: ='Parsi Bungalow'!CO10 -> 23 | V50: =IF(AND('Bungalow 2'!AV10>0,(OR('Bungalow 2'!R10='Bungalow 2'!$B$39,('Bungalow 2'!R10='Bungalow 2'!$B$40)))),'Bungalow 2'!S10,"") | W50: ='Bungalow 2'!AV10 -> 0 | X50: =IF(AND('Bungalow 2'!CH10>0,(OR('Bungalow 2'!BD10='Bungalow 2'!$B$39,('Bungalow 2'!BD10='Bungalow 2'!$B$40)))),'Bungalow 2'!BE10,"") -> Makeup Room | Y50: ='Bungalow 2'!CH10 -> 2 | Z50: =IF(AND('Villa Set '!BC10>0,(OR('Villa Set '!Y10='Villa Set '!$B$39,('Villa Set '!Y10='Villa Set '!$B$40)))),'Villa Set '!Z10,"") | AA50: ='Villa Set '!BC10 -> 0 | AB50: =IF(AND('Villa Set '!CO10>0,(OR('Villa Set '!BK10='Villa Set '!$B$39,('Villa Set '!BK10='Villa Set '!$B$40)))),'Villa Set '!BL10,"") -> Ellora HK Team | AC50: ='Villa Set '!CO10 -> 2 | AD50: =IF(AND('Villa Set '!EA10>0,(OR('Villa Set '!CW10='Villa Set '!$B$39,('Villa Set '!CW10='Villa Set '!$B$40)))),'Villa Set '!CX10,"") | AE50: ='Villa Set '!EA10 -> 0 | AF50: Ellora Infra/Maintenance Others | AG50: ='Road Light'!J10-'Road Light'!R10 -> 51 | AH50: =IF(AND(Hill!AV10>0,(OR(Hill!R10=Hill!$B$39,(Hill!R10=Hill!$B$40)))),Hill!S10,"") | AI50: =Hill!AV10 -> 0
A51: 8 | B51: =IF(AND(Hospital!AV11>0,(OR(Hospital!R11=Hospital!$B$39,(Hospital!R11=Hospital!$B$40)))),Hospital!S11,"") -> Makeup Room | C51: =Hospital!AV11 -> 24 | D51: =IF(AND(Hospital!CH11>0,(OR(Hospital!BD11=Hospital!$B$39,(Hospital!BD11=Hospital!$B$40)))),Hospital!BE11,"") | E51: =Hospital!CH11 -> 0 | F51: =IF(AND('Bungalow 1'!AV11>0*(OR('Bungalow 1'!R11='Bungalow 1'!$B$39,('Bungalow 1'!R11='Bungalow 1'!$B$40)))),'Bungalow 1'!S11,"") | G51: ='Bungalow 1'!AV11 -> 0 | H51: =IF(AND('Bungalow 1'!CH11>0,(OR('Bungalow 1'!BD11='Bungalow 1'!$B$39,('Bungalow 1'!BD11='Bungalow 1'!$B$40)))),'Bungalow 1'!BE11,"") | I51: ='Bungalow 1'!CH11 -> 0 | J51: =IF(AND('Office Set'!AV10>0,(OR('Office Set'!R10='Office Set'!$B$38,('Office Set'!R10='Office Set'!$B$39)))),'Office Set'!S10,"") -> Ellora HK Team | K51: ='Office Set'!AV10 -> 9 | L51: =IF(AND('Police Station'!AV11>0,(OR('Police Station'!R11='Police Station'!$B$39,('Police Station'!R11='Police Station'!$B$40)))),'Police Station'!S11,"") | M51: ='Police Station'!AV11 -> 0 | N51: =IF(AND('8000 sqft'!AV11>0,(OR('8000 sqft'!R11='8000 sqft'!$B$39,('8000 sqft'!R11='8000 sqft'!$B$40)))),'8000 sqft'!S11,"") -> Makeup Room | O51: ='8000 sqft'!AV11 -> 6 | P51: =IF(AND('Restaurant '!AV11>0,(OR('Restaurant '!R11='Restaurant '!$B$39,('Restaurant '!R11='Restaurant '!$B$40)))),'Restaurant '!S11,"") | Q51: ='Restaurant '!AV11 -> 0 | R51: =IF(AND('Parsi Bungalow'!BC11>0,(OR('Parsi Bungalow'!Y11='Parsi Bungalow'!$B$39,('Parsi Bungalow'!Y11='Parsi Bungalow'!$B$40)))),'Parsi Bungalow'!Z11,"") | S51: ='Parsi Bungalow'!BC11 -> 0 | T51: =IF(AND('Parsi Bungalow'!CO11>0,(OR('Parsi Bungalow'!BK11='Parsi Bungalow'!$B$39,('Parsi Bungalow'!BK11='Parsi Bungalow'!$B$40)))),'Parsi Bungalow'!BL11,"") -> Ellora HK Team | U51: ='Parsi Bungalow'!CO11 -> 1 | V51: =IF(AND('Bungalow 2'!AV11>0,(OR('Bungalow 2'!R11='Bungalow 2'!$B$39,('Bungalow 2'!R11='Bungalow 2'!$B$40)))),'Bungalow 2'!S11,"") | W51: ='Bungalow 2'!AV11 -> 0 | X51: =IF(AND('Bungalow 2'!CH11>0,(OR('Bungalow 2'!BD11='Bungalow 2'!$B$39,('Bungalow 2'!BD11='Bungalow 2'!$B$40)))),'Bungalow 2'!BE11,"") -> Makeup Room | Y51: ='Bungalow 2'!CH11 -> 33 | Z51: =IF(AND('Villa Set '!BC11>0,(OR('Villa Set '!Y11='Villa Set '!$B$39,('Villa Set '!Y11='Villa Set '!$B$40)))),'Villa Set '!Z11,"") | AA51: ='Villa Set '!BC11 -> 0 | AB51: =IF(AND('Villa Set '!CO11>0,(OR('Villa Set '!BK11='Villa Set '!$B$39,('Villa Set '!BK11='Villa Set '!$B$40)))),'Villa Set '!BL11,"") | AC51: ='Villa Set '!CO11 -> 0 | AD51: =IF(AND('Villa Set '!EA11>0,(OR('Villa Set '!CW11='Villa Set '!$B$39,('Villa Set '!CW11='Villa Set '!$B$40)))),'Villa Set '!CX11,"") | AE51: ='Villa Set '!EA11 -> 0 | AF51: Ellora Infra/Maintenance Others | AG51: ='Road Light'!J11-'Road Light'!R11 -> 57 | AH51: =IF(AND(Hill!AV11>0,(OR(Hill!R11=Hill!$B$39,(Hill!R11=Hill!$B$40)))),Hill!S11,"") | AI51: =Hill!AV11 -> 0
A52: 9 | B52: =IF(AND(Hospital!AV12>0,(OR(Hospital!R12=Hospital!$B$39,(Hospital!R12=Hospital!$B$40)))),Hospital!S12,"") | C52: =Hospital!AV12 -> 0 | D52: =IF(AND(Hospital!CH12>0,(OR(Hospital!BD12=Hospital!$B$39,(Hospital!BD12=Hospital!$B$40)))),Hospital!BE12,"") -> Ellora HK Team | E52: =Hospital!CH12 -> 2 | F52: =IF(AND('Bungalow 1'!AV12>0*(OR('Bungalow 1'!R12='Bungalow 1'!$B$39,('Bungalow 1'!R12='Bungalow 1'!$B$40)))),'Bungalow 1'!S12,"") -> Ellora HK Team | G52: ='Bungalow 1'!AV12 -> 12 | H52: =IF(AND('Bungalow 1'!CH12>0,(OR('Bungalow 1'!BD12='Bungalow 1'!$B$39,('Bungalow 1'!BD12='Bungalow 1'!$B$40)))),'Bungalow 1'!BE12,"") -> Ellora AC Team | I52: ='Bungalow 1'!CH12 -> 10 | J52: =IF(AND('Office Set'!AV11>0,(OR('Office Set'!R11='Office Set'!$B$38,('Office Set'!R11='Office Set'!$B$39)))),'Office Set'!S11,"") -> Ellora HK Team | K52: ='Office Set'!AV11 -> 15 | L52: =IF(AND('Police Station'!AV12>0,(OR('Police Station'!R12='Police Station'!$B$39,('Police Station'!R12='Police Station'!$B$40)))),'Police Station'!S12,"") | M52: ='Police Station'!AV12 -> 0 | N52: =IF(AND('8000 sqft'!AV12>0,(OR('8000 sqft'!R12='8000 sqft'!$B$39,('8000 sqft'!R12='8000 sqft'!$B$40)))),'8000 sqft'!S12,"") -> Makeup Room | O52: ='8000 sqft'!AV12 -> 29 | P52: =IF(AND('Restaurant '!AV12>0,(OR('Restaurant '!R12='Restaurant '!$B$39,('Restaurant '!R12='Restaurant '!$B$40)))),'Restaurant '!S12,"") | Q52: ='Restaurant '!AV12 -> 0 | R52: =IF(AND('Parsi Bungalow'!BC12>0,(OR('Parsi Bungalow'!Y12='Parsi Bungalow'!$B$39,('Parsi Bungalow'!Y12='Parsi Bungalow'!$B$40)))),'Parsi Bungalow'!Z12,"") | S52: ='Parsi Bungalow'!BC12 -> 0 | T52: =IF(AND('Parsi Bungalow'!CO12>0,(OR('Parsi Bungalow'!BK12='Parsi Bungalow'!$B$39,('Parsi Bungalow'!BK12='Parsi Bungalow'!$B$40)))),'Parsi Bungalow'!BL12,"") -> Ellora HK Team | U52: ='Parsi Bungalow'!CO12 -> 1 | V52: =IF(AND('Bungalow 2'!AV12>0,(OR('Bungalow 2'!R12='Bungalow 2'!$B$39,('Bungalow 2'!R12='Bungalow 2'!$B$40)))),'Bungalow 2'!S12,"") | W52: ='Bungalow 2'!AV12 -> 0 | X52: =IF(AND('Bungalow 2'!CH12>0,(OR('Bungalow 2'!BD12='Bungalow 2'!$B$39,('Bungalow 2'!BD12='Bungalow 2'!$B$40)))),'Bungalow 2'!BE12,"") -> Makeup Room | Y52: ='Bungalow 2'!CH12 -> 46 | Z52: =IF(AND('Villa Set '!BC12>0,(OR('Villa Set '!Y12='Villa Set '!$B$39,('Villa Set '!Y12='Villa Set '!$B$40)))),'Villa Set '!Z12,"") | AA52: ='Villa Set '!BC12 -> 0 | AB52: =IF(AND('Villa Set '!CO12>0,(OR('Villa Set '!BK12='Villa Set '!$B$39,('Villa Set '!BK12='Villa Set '!$B$40)))),'Villa Set '!BL12,"") -> Makeup Room | AC52: ='Villa Set '!CO12 -> 46 | AD52: =IF(AND('Villa Set '!EA12>0,(OR('Villa Set '!CW12='Villa Set '!$B$39,('Villa Set '!CW12='Villa Set '!$B$40)))),'Villa Set '!CX12,"") | AE52: ='Villa Set '!EA12 -> 0 | AF52: Ellora Infra/Maintenance Others | AG52: ='Road Light'!J12-'Road Light'!R12 -> 40 | AH52: =IF(AND(Hill!AV12>0,(OR(Hill!R12=Hill!$B$39,(Hill!R12=Hill!$B$40)))),Hill!S12,"") | AI52: =Hill!AV12 -> 0
A53: 10 | B53: =IF(AND(Hospital!AV13>0,(OR(Hospital!R13=Hospital!$B$39,(Hospital!R13=Hospital!$B$40)))),Hospital!S13,"") -> Makeup Room | C53: =Hospital!AV13 -> 6 | D53: =IF(AND(Hospital!CH13>0,(OR(Hospital!BD13=Hospital!$B$39,(Hospital!BD13=Hospital!$B$40)))),Hospital!BE13,"") | E53: =Hospital!CH13 -> 0 | F53: =IF(AND('Bungalow 1'!AV13>0*(OR('Bungalow 1'!R13='Bungalow 1'!$B$39,('Bungalow 1'!R13='Bungalow 1'!$B$40)))),'Bungalow 1'!S13,"") | G53: ='Bungalow 1'!AV13 -> 0 | H53: =IF(AND('Bungalow 1'!CH13>0,(OR('Bungalow 1'!BD13='Bungalow 1'!$B$39,('Bungalow 1'!BD13='Bungalow 1'!$B$40)))),'Bungalow 1'!BE13,"") | I53: ='Bungalow 1'!CH13 -> 0 | J53: =IF(AND('Office Set'!AV12>0,(OR('Office Set'!R12='Office Set'!$B$38,('Office Set'!R12='Office Set'!$B$39)))),'Office Set'!S12,"") -> Shooting | K53: ='Office Set'!AV12 -> 300 | L53: =IF(AND('Police Station'!AV13>0,(OR('Police Station'!R13='Police Station'!$B$39,('Police Station'!R13='Police Station'!$B$40)))),'Police Station'!S13,"") | M53: ='Police Station'!AV13 -> 0 | N53: =IF(AND('8000 sqft'!AV13>0,(OR('8000 sqft'!R13='8000 sqft'!$B$39,('8000 sqft'!R13='8000 sqft'!$B$40)))),'8000 sqft'!S13,"") -> Makeup Room | O53: ='8000 sqft'!AV13 -> 12 | P53: =IF(AND('Restaurant '!AV13>0,(OR('Restaurant '!R13='Restaurant '!$B$39,('Restaurant '!R13='Restaurant '!$B$40)))),'Restaurant '!S13,"") -> Makeup Room | Q53: ='Restaurant '!AV13 -> 47 | R53: =IF(AND('Parsi Bungalow'!BC13>0,(OR('Parsi Bungalow'!Y13='Parsi Bungalow'!$B$39,('Parsi Bungalow'!Y13='Parsi Bungalow'!$B$40)))),'Parsi Bungalow'!Z13,"") | S53: ='Parsi Bungalow'!BC13 -> 0 | T53: =IF(AND('Parsi Bungalow'!CO13>0,(OR('Parsi Bungalow'!BK13='Parsi Bungalow'!$B$39,('Parsi Bungalow'!BK13='Parsi Bungalow'!$B$40)))),'Parsi Bungalow'!BL13,"") | U53: ='Parsi Bungalow'!CO13 -> 0 | V53: =IF(AND('Bungalow 2'!AV13>0,(OR('Bungalow 2'!R13='Bungalow 2'!$B$39,('Bungalow 2'!R13='Bungalow 2'!$B$40)))),'Bungalow 2'!S13,"") | W53: ='Bungalow 2'!AV13 -> 0 | X53: =IF(AND('Bungalow 2'!CH13>0,(OR('Bungalow 2'!BD13='Bungalow 2'!$B$39,('Bungalow 2'!BD13='Bungalow 2'!$B$40)))),'Bungalow 2'!BE13,"") -> Makeup Room | Y53: ='Bungalow 2'!CH13 -> 13 | Z53: =IF(AND('Villa Set '!BC13>0,(OR('Villa Set '!Y13='Villa Set '!$B$39,('Villa Set '!Y13='Villa Set '!$B$40)))),'Villa Set '!Z13,"") | AA53: ='Villa Set '!BC13 -> 0 | AB53: =IF(AND('Villa Set '!CO13>0,(OR('Villa Set '!BK13='Villa Set '!$B$39,('Villa Set '!BK13='Villa Set '!$B$40)))),'Villa Set '!BL13,"") -> Makeup Room | AC53: ='Villa Set '!CO13 -> 26 | AD53: =IF(AND('Villa Set '!EA13>0,(OR('Villa Set '!CW13='Villa Set '!$B$39,('Villa Set '!CW13='Villa Set '!$B$40)))),'Villa Set '!CX13,"") | AE53: ='Villa Set '!EA13 -> 0 | AF53: Ellora Infra/Maintenance Others | AG53: ='Road Light'!J13-'Road Light'!R13 -> 65 | AH53: =IF(AND(Hill!AV13>0,(OR(Hill!R13=Hill!$B$39,(Hill!R13=Hill!$B$40)))),Hill!S13,"") | AI53: =Hill!AV13 -> 0
A54: 11 | B54: =IF(AND(Hospital!AV14>0,(OR(Hospital!R14=Hospital!$B$39,(Hospital!R14=Hospital!$B$40)))),Hospital!S14,"") -> Makeup Room | C54: =Hospital!AV14 -> 7 | D54: =IF(AND(Hospital!CH14>0,(OR(Hospital!BD14=Hospital!$B$39,(Hospital!BD14=Hospital!$B$40)))),Hospital!BE14,"") | E54: =Hospital!CH14 -> 0 | F54: =IF(AND('Bungalow 1'!AV14>0*(OR('Bungalow 1'!R14='Bungalow 1'!$B$39,('Bungalow 1'!R14='Bungalow 1'!$B$40)))),'Bungalow 1'!S14,"") | G54: ='Bungalow 1'!AV14 -> 0 | H54: =IF(AND('Bungalow 1'!CH14>0,(OR('Bungalow 1'!BD14='Bungalow 1'!$B$39,('Bungalow 1'!BD14='Bungalow 1'!$B$40)))),'Bungalow 1'!BE14,"") | I54: ='Bungalow 1'!CH14 -> 0 | J54: =IF(AND('Office Set'!AV13>0,(OR('Office Set'!R13='Office Set'!$B$38,('Office Set'!R13='Office Set'!$B$39)))),'Office Set'!S13,"") -> Shooting | K54: ='Office Set'!AV13 -> 276 | L54: =IF(AND('Police Station'!AV14>0,(OR('Police Station'!R14='Police Station'!$B$39,('Police Station'!R14='Police Station'!$B$40)))),'Police Station'!S14,"") | M54: ='Police Station'!AV14 -> 0 | N54: =IF(AND('8000 sqft'!AV14>0,(OR('8000 sqft'!R14='8000 sqft'!$B$39,('8000 sqft'!R14='8000 sqft'!$B$40)))),'8000 sqft'!S14,"") -> Makeup Room | O54: ='8000 sqft'!AV14 -> 3 | P54: =IF(AND('Restaurant '!AV14>0,(OR('Restaurant '!R14='Restaurant '!$B$39,('Restaurant '!R14='Restaurant '!$B$40)))),'Restaurant '!S14,"") -> Makeup Room | Q54: ='Restaurant '!AV14 -> 36 | R54: =IF(AND('Parsi Bungalow'!BC14>0,(OR('Parsi Bungalow'!Y14='Parsi Bungalow'!$B$39,('Parsi Bungalow'!Y14='Parsi Bungalow'!$B$40)))),'Parsi Bungalow'!Z14,"") | S54: ='Parsi Bungalow'!BC14 -> 0 | T54: =IF(AND('Parsi Bungalow'!CO14>0,(OR('Parsi Bungalow'!BK14='Parsi Bungalow'!$B$39,('Parsi Bungalow'!BK14='Parsi Bungalow'!$B$40)))),'Parsi Bungalow'!BL14,"") -> Ellora HK Team | U54: ='Parsi Bungalow'!CO14 -> 4 | V54: =IF(AND('Bungalow 2'!AV14>0,(OR('Bungalow 2'!R14='Bungalow 2'!$B$39,('Bungalow 2'!R14='Bungalow 2'!$B$40)))),'Bungalow 2'!S14,"") | W54: ='Bungalow 2'!AV14 -> 0 | X54: =IF(AND('Bungalow 2'!CH14>0,(OR('Bungalow 2'!BD14='Bungalow 2'!$B$39,('Bungalow 2'!BD14='Bungalow 2'!$B$40)))),'Bungalow 2'!BE14,"") -> Makeup Room | Y54: ='Bungalow 2'!CH14 -> 60 | Z54: =IF(AND('Villa Set '!BC14>0,(OR('Villa Set '!Y14='Villa Set '!$B$39,('Villa Set '!Y14='Villa Set '!$B$40)))),'Villa Set '!Z14,"") | AA54: ='Villa Set '!BC14 -> 0 | AB54: =IF(AND('Villa Set '!CO14>0,(OR('Villa Set '!BK14='Villa Set '!$B$39,('Villa Set '!BK14='Villa Set '!$B$40)))),'Villa Set '!BL14,"") | AC54: ='Villa Set '!CO14 -> 0 | AD54: =IF(AND('Villa Set '!EA14>0,(OR('Villa Set '!CW14='Villa Set '!$B$39,('Villa Set '!CW14='Villa Set '!$B$40)))),'Villa Set '!CX14,"") | AE54: ='Villa Set '!EA14 -> 0 | AF54: Ellora Infra/Maintenance Others | AG54: ='Road Light'!J14-'Road Light'!R14 -> 47 | AH54: =IF(AND(Hill!AV14>0,(OR(Hill!R14=Hill!$B$39,(Hill!R14=Hill!$B$40)))),Hill!S14,"") | AI54: =Hill!AV14 -> 0
A55: 12 | B55: =IF(AND(Hospital!AV15>0,(OR(Hospital!R15=Hospital!$B$39,(Hospital!R15=Hospital!$B$40)))),Hospital!S15,"") | C55: =Hospital!AV15 -> 0 | D55: =IF(AND(Hospital!CH15>0,(OR(Hospital!BD15=Hospital!$B$39,(Hospital!BD15=Hospital!$B$40)))),Hospital!BE15,"") | E55: =Hospital!CH15 -> 0 | F55: =IF(AND('Bungalow 1'!AV15>0*(OR('Bungalow 1'!R15='Bungalow 1'!$B$39,('Bungalow 1'!R15='Bungalow 1'!$B$40)))),'Bungalow 1'!S15,"") | G55: ='Bungalow 1'!AV15 -> 0 | H55: =IF(AND('Bungalow 1'!CH15>0,(OR('Bungalow 1'!BD15='Bungalow 1'!$B$39,('Bungalow 1'!BD15='Bungalow 1'!$B$40)))),'Bungalow 1'!BE15,"") | I55: ='Bungalow 1'!CH15 -> 0 | J55: =IF(AND('Office Set'!AV14>0,(OR('Office Set'!R14='Office Set'!$B$38,('Office Set'!R14='Office Set'!$B$39)))),'Office Set'!S14,"") -> Shooting | K55: ='Office Set'!AV14 -> 281 | L55: =IF(AND('Police Station'!AV15>0,(OR('Police Station'!R15='Police Station'!$B$39,('Police Station'!R15='Police Station'!$B$40)))),'Police Station'!S15,"") | M55: ='Police Station'!AV15 -> 0 | N55: =IF(AND('8000 sqft'!AV15>0,(OR('8000 sqft'!R15='8000 sqft'!$B$39,('8000 sqft'!R15='8000 sqft'!$B$40)))),'8000 sqft'!S15,"") -> Makeup Room | O55: ='8000 sqft'!AV15 -> 4 | P55: =IF(AND('Restaurant '!AV15>0,(OR('Restaurant '!R15='Restaurant '!$B$39,('Restaurant '!R15='Restaurant '!$B$40)))),'Restaurant '!S15,"") -> Makeup Room | Q55: ='Restaurant '!AV15 -> 41 | R55: =IF(AND('Parsi Bungalow'!BC15>0,(OR('Parsi Bungalow'!Y15='Parsi Bungalow'!$B$39,('Parsi Bungalow'!Y15='Parsi Bungalow'!$B$40)))),'Parsi Bungalow'!Z15,"") | S55: ='Parsi Bungalow'!BC15 -> 0 | T55: =IF(AND('Parsi Bungalow'!CO15>0,(OR('Parsi Bungalow'!BK15='Parsi Bungalow'!$B$39,('Parsi Bungalow'!BK15='Parsi Bungalow'!$B$40)))),'Parsi Bungalow'!BL15,"") | U55: ='Parsi Bungalow'!CO15 -> 0 | V55: =IF(AND('Bungalow 2'!AV15>0,(OR('Bungalow 2'!R15='Bungalow 2'!$B$39,('Bungalow 2'!R15='Bungalow 2'!$B$40)))),'Bungalow 2'!S15,"") -> Ellora HK Team | W55: ='Bungalow 2'!AV15 -> 3 | X55: =IF(AND('Bungalow 2'!CH15>0,(OR('Bungalow 2'!BD15='Bungalow 2'!$B$39,('Bungalow 2'!BD15='Bungalow 2'!$B$40)))),'Bungalow 2'!BE15,"") -> Makeup Room | Y55: ='Bungalow 2'!CH15 -> 95 | Z55: =IF(AND('Villa Set '!BC15>0,(OR('Villa Set '!Y15='Villa Set '!$B$39,('Villa Set '!Y15='Villa Set '!$B$40)))),'Villa Set '!Z15,"") | AA55: ='Villa Set '!BC15 -> 0 | AB55: =IF(AND('Villa Set '!CO15>0,(OR('Villa Set '!BK15='Villa Set '!$B$39,('Villa Set '!BK15='Villa Set '!$B$40)))),'Villa Set '!BL15,"") | AC55: ='Villa Set '!CO15 -> 0 | AD55: =IF(AND('Villa Set '!EA15>0,(OR('Villa Set '!CW15='Villa Set '!$B$39,('Villa Set '!CW15='Villa Set '!$B$40)))),'Villa Set '!CX15,"") | AE55: ='Villa Set '!EA15 -> 0 | AF55: Ellora Infra/Maintenance Others | AG55: ='Road Light'!J15-'Road Light'!R15 -> 65 | AH55: =IF(AND(Hill!AV15>0,(OR(Hill!R15=Hill!$B$39,(Hill!R15=Hill!$B$40)))),Hill!S15,"") | AI55: =Hill!AV15 -> 0
... A59: 16 | B59: =IF(AND(Hospital!AV19>0,(OR(Hospital!R19=Hospital!$B$39,(Hospital!R19=Hospital!$B$40)))),Hospital!S19,"") -> Shooting | C59: =Hospital!AV19 -> 300 | D59: =IF(AND(Hospital!CH19>0,(OR(Hospital!BD19=Hospital!$B$39,(Hospital!BD19=Hospital!$B$40)))),Hospital!BE19,"") | E59: =Hospital!CH19 -> 0 | F59: =IF(AND('Bungalow 1'!AV19>0*(OR('Bungalow 1'!R19='Bungalow 1'!$B$39,('Bungalow 1'!R19='Bungalow 1'!$B$40)))),'Bungalow 1'!S19,"") | G59: ='Bungalow 1'!AV19 -> 0 | H59: =IF(AND('Bungalow 1'!CH19>0,(OR('Bungalow 1'!BD19='Bungalow 1'!$B$39,('Bungalow 1'!BD19='Bungalow 1'!$B$40)))),'Bungalow 1'!BE19,"") -> Ellora AC Team | I59: ='Bungalow 1'!CH19 -> 2 | J59: =IF(AND('Office Set'!AV18>0,(OR('Office Set'!R18='Office Set'!$B$38,('Office Set'!R18='Office Set'!$B$39)))),'Office Set'!S18,"") | K59: ='Office Set'!AV18 -> 0 | L59: =IF(AND('Police Station'!AV19>0,(OR('Police Station'!R19='Police Station'!$B$39,('Police Station'!R19='Police Station'!$B$40)))),'Police Station'!S19,"") | M59: ='Police Station'!AV19 -> 0 | N59: =IF(AND('8000 sqft'!AV19>0,(OR('8000 sqft'!R19='8000 sqft'!$B$39,('8000 sqft'!R19='8000 sqft'!$B$40)))),'8000 sqft'!S19,"") -> Makeup Room | O59: ='8000 sqft'!AV19 -> 5 | P59: =IF(AND('Restaurant '!AV19>0,(OR('Restaurant '!R19='Restaurant '!$B$39,('Restaurant '!R19='Restaurant '!$B$40)))),'Restaurant '!S19,"") | Q59: ='Restaurant '!AV19 -> 0 | R59: =IF(AND('Parsi Bungalow'!BC19>0,(OR('Parsi Bungalow'!Y19='Parsi Bungalow'!$B$39,('Parsi Bungalow'!Y19='Parsi Bungalow'!$B$40)))),'Parsi Bungalow'!Z19,"") | S59: ='Parsi Bungalow'!BC19 -> 0 | T59: =IF(AND('Parsi Bungalow'!CO19>0,(OR('Parsi Bungalow'!BK19='Parsi Bungalow'!$B$39,('Parsi Bungalow'!BK19='Parsi Bungalow'!$B$40)))),'Parsi Bungalow'!BL19,"") | U59: ='Parsi Bungalow'!CO19 -> 0 | V59: =IF(AND('Bungalow 2'!AV19>0,(OR('Bungalow 2'!R19='Bungalow 2'!$B$39,('Bungalow 2'!R19='Bungalow 2'!$B$40)))),'Bungalow 2'!S19,"") -> Shooting | W59: ='Bungalow 2'!AV19 -> 300 | X59: =IF(AND('Bungalow 2'!CH19>0,(OR('Bungalow 2'!BD19='Bungalow 2'!$B$39,('Bungalow 2'!BD19='Bungalow 2'!$B$40)))),'Bungalow 2'!BE19,"") -> Makeup Room | Y59: ='Bungalow 2'!CH19 -> 97 | Z59: =IF(AND('Villa Set '!BC19>0,(OR('Villa Set '!Y19='Villa Set '!$B$39,('Villa Set '!Y19='Villa Set '!$B$40)))),'Villa Set '!Z19,"") | AA59: ='Villa Set '!BC19 -> 0 | AB59: =IF(AND('Villa Set '!CO19>0,(OR('Villa Set '!BK19='Villa Set '!$B$39,('Villa Set '!BK19='Villa Set '!$B$40)))),'Villa Set '!BL19,"") | AC59: ='Villa Set '!CO19 -> 0 | AD59: =IF(AND('Villa Set '!EA19>0,(OR('Villa Set '!CW19='Villa Set '!$B$39,('Villa Set '!CW19='Villa Set '!$B$40)))),'Villa Set '!CX19,"") | AE59: ='Villa Set '!EA19 -> 0 | AF59: Ellora Infra/Maintenance Others | AG59: ='Road Light'!J19-'Road Light'!R19 -> 89 | AH59: =IF(AND(Hill!AV19>0,(OR(Hill!R19=Hill!$B$39,(Hill!R19=Hill!$B$40)))),Hill!S19,"") | AI59: =Hill!AV19 -> 0
A60: 17 | B60: =IF(AND(Hospital!AV20>0,(OR(Hospital!R20=Hospital!$B$39,(Hospital!R20=Hospital!$B$40)))),Hospital!S20,"") -> Shooting | C60: =Hospital!AV20 -> 300 | D60: =IF(AND(Hospital!CH20>0,(OR(Hospital!BD20=Hospital!$B$39,(Hospital!BD20=Hospital!$B$40)))),Hospital!BE20,"") | E60: =Hospital!CH20 -> 0 | F60: =IF(AND('Bungalow 1'!AV20>0*(OR('Bungalow 1'!R20='Bungalow 1'!$B$39,('Bungalow 1'!R20='Bungalow 1'!$B$40)))),'Bungalow 1'!S20,"") | G60: ='Bungalow 1'!AV20 -> 0 | H60: =IF(AND('Bungalow 1'!CH20>0,(OR('Bungalow 1'!BD20='Bungalow 1'!$B$39,('Bungalow 1'!BD20='Bungalow 1'!$B$40)))),'Bungalow 1'!BE20,"") | I60: ='Bungalow 1'!CH20 -> 0 | J60: =IF(AND('Office Set'!AV19>0,(OR('Office Set'!R19='Office Set'!$B$38,('Office Set'!R19='Office Set'!$B$39)))),'Office Set'!S19,"") -> Ellora HK Team | K60: ='Office Set'!AV19 -> 9 | L60: =IF(AND('Police Station'!AV20>0,(OR('Police Station'!R20='Police Station'!$B$39,('Police Station'!R20='Police Station'!$B$40)))),'Police Station'!S20,"") | M60: ='Police Station'!AV20 -> 0 | N60: =IF(AND('8000 sqft'!AV20>0,(OR('8000 sqft'!R20='8000 sqft'!$B$39,('8000 sqft'!R20='8000 sqft'!$B$40)))),'8000 sqft'!S20,"") -> Makeup Room | O60: ='8000 sqft'!AV20 -> 6 | P60: =IF(AND('Restaurant '!AV20>0,(OR('Restaurant '!R20='Restaurant '!$B$39,('Restaurant '!R20='Restaurant '!$B$40)))),'Restaurant '!S20,"") | Q60: ='Restaurant '!AV20 -> 0 | R60: =IF(AND('Parsi Bungalow'!BC20>0,(OR('Parsi Bungalow'!Y20='Parsi Bungalow'!$B$39,('Parsi Bungalow'!Y20='Parsi Bungalow'!$B$40)))),'Parsi Bungalow'!Z20,"") | S60: ='Parsi Bungalow'!BC20 -> 0 | T60: =IF(AND('Parsi Bungalow'!CO20>0,(OR('Parsi Bungalow'!BK20='Parsi Bungalow'!$B$39,('Parsi Bungalow'!BK20='Parsi Bungalow'!$B$40)))),'Parsi Bungalow'!BL20,"") | U60: ='Parsi Bungalow'!CO20 -> 0 | V60: =IF(AND('Bungalow 2'!AV20>0,(OR('Bungalow 2'!R21='Bungalow 2'!$B$39,('Bungalow 2'!R21='Bungalow 2'!$B$40)))),'Bungalow 2'!S21,"") | W60: ='Bungalow 2'!AV20 -> 3 | X60: =IF(AND('Bungalow 2'!CH20>0,(OR('Bungalow 2'!BD20='Bungalow 2'!$B$39,('Bungalow 2'!BD20='Bungalow 2'!$B$40)))),'Bungalow 2'!BE20,"") -> Makeup Room | Y60: ='Bungalow 2'!CH20 -> 5 | Z60: =IF(AND('Villa Set '!BC20>0,(OR('Villa Set '!Y20='Villa Set '!$B$39,('Villa Set '!Y20='Villa Set '!$B$40)))),'Villa Set '!Z20,"") | AA60: ='Villa Set '!BC20 -> 0 | AB60: =IF(AND('Villa Set '!CO20>0,(OR('Villa Set '!BK20='Villa Set '!$B$39,('Villa Set '!BK20='Villa Set '!$B$40)))),'Villa Set '!BL20,"") | AC60: ='Villa Set '!CO20 -> 0 | AD60: =IF(AND('Villa Set '!EA20>0,(OR('Villa Set '!CW20='Villa Set '!$B$39,('Villa Set '!CW20='Villa Set '!$B$40)))),'Villa Set '!CX20,"") | AE60: ='Villa Set '!EA20 -> 0 | AF60: Ellora Infra/Maintenance Others | AG60: ='Road Light'!J20-'Road Light'!R20 -> 61 | AH60: =IF(AND(Hill!AV20>0,(OR(Hill!R20=Hill!$B$39,(Hill!R20=Hill!$B$40)))),Hill!S20,"") | AI60: =Hill!AV20 -> 0
A61: 18 | B61: =IF(AND(Hospital!AV21>0,(OR(Hospital!R21=Hospital!$B$39,(Hospital!R21=Hospital!$B$40)))),Hospital!S21,"") -> Ellora HK Team | C61: =Hospital!AV21 -> 28 | D61: =IF(AND(Hospital!CH21>0,(OR(Hospital!BD21=Hospital!$B$39,(Hospital!BD21=Hospital!$B$40)))),Hospital!BE21,"") | E61: =Hospital!CH21 -> 0 | F61: =IF(AND('Bungalow 1'!AV21>0*(OR('Bungalow 1'!R21='Bungalow 1'!$B$39,('Bungalow 1'!R21='Bungalow 1'!$B$40)))),'Bungalow 1'!S21,"") -> Shooting | G61: ='Bungalow 1'!AV21 -> 300 | H61: =IF(AND('Bungalow 1'!CH21>0,(OR('Bungalow 1'!BD21='Bungalow 1'!$B$39,('Bungalow 1'!BD21='Bungalow 1'!$B$40)))),'Bungalow 1'!BE21,"") | I61: ='Bungalow 1'!CH21 -> 0 | J61: =IF(AND('Office Set'!AV20>0,(OR('Office Set'!R20='Office Set'!$B$38,('Office Set'!R20='Office Set'!$B$39)))),'Office Set'!S20,"") | K61: ='Office Set'!AV20 -> 0 | L61: =IF(AND('Police Station'!AV21>0,(OR('Police Station'!R21='Police Station'!$B$39,('Police Station'!R21='Police Station'!$B$40)))),'Police Station'!S21,"") | M61: ='Police Station'!AV21 -> 0 | N61: =IF(AND('8000 sqft'!AV21>0,(OR('8000 sqft'!R21='8000 sqft'!$B$39,('8000 sqft'!R21='8000 sqft'!$B$40)))),'8000 sqft'!S21,"") -> Makeup Room | O61: ='8000 sqft'!AV21 -> 10 | P61: =IF(AND('Restaurant '!AV21>0,(OR('Restaurant '!R21='Restaurant '!$B$39,('Restaurant '!R21='Restaurant '!$B$40)))),'Restaurant '!S21,"") | Q61: ='Restaurant '!AV21 -> 0 | R61: =IF(AND('Parsi Bungalow'!BC21>0,(OR('Parsi Bungalow'!Y21='Parsi Bungalow'!$B$39,('Parsi Bungalow'!Y21='Parsi Bungalow'!$B$40)))),'Parsi Bungalow'!Z21,"") | S61: ='Parsi Bungalow'!BC21 -> 0 | T61: =IF(AND('Parsi Bungalow'!CO21>0,(OR('Parsi Bungalow'!BK21='Parsi Bungalow'!$B$39,('Parsi Bungalow'!BK21='Parsi Bungalow'!$B$40)))),'Parsi Bungalow'!BL21,"") -> Ellora HK Team | U61: ='Parsi Bungalow'!CO21 -> 7 | V61: =IF(AND('Bungalow 2'!AV21>0,(OR('Bungalow 2'!R22='Bungalow 2'!$B$39,('Bungalow 2'!R22='Bungalow 2'!$B$40)))),'Bungalow 2'!S22,"") | W61: ='Bungalow 2'!AV21 -> 0 | X61: =IF(AND('Bungalow 2'!CH21>0,(OR('Bungalow 2'!BD21='Bungalow 2'!$B$39,('Bungalow 2'!BD21='Bungalow 2'!$B$40)))),'Bungalow 2'!BE21,"") -> Makeup Room | Y61: ='Bungalow 2'!CH21 -> 227 | Z61: =IF(AND('Villa Set '!BC21>0,(OR('Villa Set '!Y21='Villa Set '!$B$39,('Villa Set '!Y21='Villa Set '!$B$40)))),'Villa Set '!Z21,"") | AA61: ='Villa Set '!BC21 -> 0 | AB61: =IF(AND('Villa Set '!CO21>0,(OR('Villa Set '!BK21='Villa Set '!$B$39,('Villa Set '!BK21='Villa Set '!$B$40)))),'Villa Set '!BL21,"") | AC61: ='Villa Set '!CO21 -> 0 | AD61: =IF(AND('Villa Set '!EA21>0,(OR('Villa Set '!CW21='Villa Set '!$B$39,('Villa Set '!CW21='Villa Set '!$B$40)))),'Villa Set '!CX21,"") | AE61: ='Villa Set '!EA21 -> 0 | AF61: Ellora Infra/Maintenance Others | AG61: ='Road Light'!J21-'Road Light'!R21 -> 68 | AH61: =IF(AND(Hill!AV21>0,(OR(Hill!R21=Hill!$B$39,(Hill!R21=Hill!$B$40)))),Hill!S21,"") | AI61: =Hill!AV21 -> 0
A62: 19 | B62: =IF(AND(Hospital!AV22>0,(OR(Hospital!R22=Hospital!$B$39,(Hospital!R22=Hospital!$B$40)))),Hospital!S22,"") -> Ellora HK Team | C62: =Hospital!AV22 -> 19 | D62: =IF(AND(Hospital!CH22>0,(OR(Hospital!BD22=Hospital!$B$39,(Hospital!BD22=Hospital!$B$40)))),Hospital!BE22,"") | E62: =Hospital!CH22 -> 0 | F62: =IF(AND('Bungalow 1'!AV22>0*(OR('Bungalow 1'!R22='Bungalow 1'!$B$39,('Bungalow 1'!R22='Bungalow 1'!$B$40)))),'Bungalow 1'!S22,"") -> Ellora HK Team | G62: ='Bungalow 1'!AV22 -> 1 | H62: =IF(AND('Bungalow 1'!CH22>0,(OR('Bungalow 1'!BD22='Bungalow 1'!$B$39,('Bungalow 1'!BD22='Bungalow 1'!$B$40)))),'Bungalow 1'!BE22,"") | I62: ='Bungalow 1'!CH22 -> 0 | J62: =IF(AND('Office Set'!AV21>0,(OR('Office Set'!R21='Office Set'!$B$38,('Office Set'!R21='Office Set'!$B$39)))),'Office Set'!S21,"") | K62: ='Office Set'!AV21 -> 0 | L62: =IF(AND('Police Station'!AV22>0,(OR('Police Station'!R22='Police Station'!$B$39,('Police Station'!R22='Police Station'!$B$40)))),'Police Station'!S22,"") | M62: ='Police Station'!AV22 -> 0 | N62: =IF(AND('8000 sqft'!AV22>0,(OR('8000 sqft'!R22='8000 sqft'!$B$39,('8000 sqft'!R22='8000 sqft'!$B$40)))),'8000 sqft'!S22,"") | O62: ='8000 sqft'!AV22 -> 0 | P62: =IF(AND('Restaurant '!AV22>0,(OR('Restaurant '!R22='Restaurant '!$B$39,('Restaurant '!R22='Restaurant '!$B$40)))),'Restaurant '!S22,"") | Q62: ='Restaurant '!AV22 -> 0 | R62: =IF(AND('Parsi Bungalow'!BC22>0,(OR('Parsi Bungalow'!Y22='Parsi Bungalow'!$B$39,('Parsi Bungalow'!Y22='Parsi Bungalow'!$B$40)))),'Parsi Bungalow'!Z22,"") | S62: ='Parsi Bungalow'!BC22 -> 0 | T62: =IF(AND('Parsi Bungalow'!CO22>0,(OR('Parsi Bungalow'!BK22='Parsi Bungalow'!$B$39,('Parsi Bungalow'!BK22='Parsi Bungalow'!$B$40)))),'Parsi Bungalow'!BL22,"") -> Ellora HK Team | U62: ='Parsi Bungalow'!CO22 -> 2 | V62: =IF(AND('Bungalow 2'!AV22>0,(OR('Bungalow 2'!R23='Bungalow 2'!$B$39,('Bungalow 2'!R23='Bungalow 2'!$B$40)))),'Bungalow 2'!S23,"") | W62: ='Bungalow 2'!AV22 -> 0 | X62: =IF(AND('Bungalow 2'!CH22>0,(OR('Bungalow 2'!BD22='Bungalow 2'!$B$39,('Bungalow 2'!BD22='Bungalow 2'!$B$40)))),'Bungalow 2'!BE22,"") -> Makeup Room | Y62: ='Bungalow 2'!CH22 -> 137 | Z62: =IF(AND('Villa Set '!BC22>0,(OR('Villa Set '!Y22='Villa Set '!$B$39,('Villa Set '!Y22='Villa Set '!$B$40)))),'Villa Set '!Z22,"") | AA62: ='Villa Set '!BC22 -> 0 | AB62: =IF(AND('Villa Set '!CO22>0,(OR('Villa Set '!BK22='Villa Set '!$B$39,('Villa Set '!BK22='Villa Set '!$B$40)))),'Villa Set '!BL22,"") | AC62: ='Villa Set '!CO22 -> 0 | AD62: =IF(AND('Villa Set '!EA22>0,(OR('Villa Set '!CW22='Villa Set '!$B$39,('Villa Set '!CW22='Villa Set '!$B$40)))),'Villa Set '!CX22,"") | AE62: ='Villa Set '!EA22 -> 0 | AF62: Ellora Infra/Maintenance Others | AG62: ='Road Light'!J22-'Road Light'!R22 -> 105 | AH62: =IF(AND(Hill!AV22>0,(OR(Hill!R22=Hill!$B$39,(Hill!R22=Hill!$B$40)))),Hill!S22,"") | AI62: =Hill!AV22 -> 0
A63: 20 | B63: =IF(AND(Hospital!AV23>0,(OR(Hospital!R23=Hospital!$B$39,(Hospital!R23=Hospital!$B$40)))),Hospital!S23,"") | C63: =Hospital!AV23 -> 0 | D63: =IF(AND(Hospital!CH23>0,(OR(Hospital!BD23=Hospital!$B$39,(Hospital!BD23=Hospital!$B$40)))),Hospital!BE23,"") | E63: =Hospital!CH23 -> 0 | F63: =IF(AND('Bungalow 1'!AV23>0*(OR('Bungalow 1'!R23='Bungalow 1'!$B$39,('Bungalow 1'!R23='Bungalow 1'!$B$40)))),'Bungalow 1'!S23,"") | G63: ='Bungalow 1'!AV23 -> 0 | H63: =IF(AND('Bungalow 1'!CH23>0,(OR('Bungalow 1'!BD23='Bungalow 1'!$B$39,('Bungalow 1'!BD23='Bungalow 1'!$B$40)))),'Bungalow 1'!BE23,"") | I63: ='Bungalow 1'!CH23 -> 0 | J63: =IF(AND('Office Set'!AV22>0,(OR('Office Set'!R22='Office Set'!$B$38,('Office Set'!R22='Office Set'!$B$39)))),'Office Set'!S22,"") | K63: ='Office Set'!AV22 -> 0 | L63: =IF(AND('Police Station'!AV23>0,(OR('Police Station'!R23='Police Station'!$B$39,('Police Station'!R23='Police Station'!$B$40)))),'Police Station'!S23,"") | M63: ='Police Station'!AV23 -> 0 | N63: =IF(AND('8000 sqft'!AV23>0,(OR('8000 sqft'!R23='8000 sqft'!$B$39,('8000 sqft'!R23='8000 sqft'!$B$40)))),'8000 sqft'!S23,"") -> Makeup Room | O63: ='8000 sqft'!AV23 -> 14 | P63: =IF(AND('Restaurant '!AV23>0,(OR('Restaurant '!R23='Restaurant '!$B$39,('Restaurant '!R23='Restaurant '!$B$40)))),'Restaurant '!S23,"") | Q63: ='Restaurant '!AV23 -> 0 | R63: =IF(AND('Parsi Bungalow'!BC23>0,(OR('Parsi Bungalow'!Y23='Parsi Bungalow'!$B$39,('Parsi Bungalow'!Y23='Parsi Bungalow'!$B$40)))),'Parsi Bungalow'!Z23,"") -> Ellora AC Team | S63: ='Parsi Bungalow'!BC23 -> 27 | T63: =IF(AND('Parsi Bungalow'!CO23>0,(OR('Parsi Bungalow'!BK23='Parsi Bungalow'!$B$39,('Parsi Bungalow'!BK23='Parsi Bungalow'!$B$40)))),'Parsi Bungalow'!BL23,"") -> Ellora HK Team | U63: ='Parsi Bungalow'!CO23 -> 2 | V63: =IF(AND('Bungalow 2'!AV23>0,(OR('Bungalow 2'!#REF!='Bungalow 2'!$B$39,('Bungalow 2'!#REF!='Bungalow 2'!$B$40)))),'Bungalow 2'!#REF!,"") -> #REF! | W63: ='Bungalow 2'!AV23 -> 0 | X63: =IF(AND('Bungalow 2'!CH23>0,(OR('Bungalow 2'!BD23='Bungalow 2'!$B$39,('Bungalow 2'!BD23='Bungalow 2'!$B$40)))),'Bungalow 2'!BE23,"") -> Makeup Room | Y63: ='Bungalow 2'!CH23 -> 46 | Z63: =IF(AND('Villa Set '!BC23>0,(OR('Villa Set '!Y23='Villa Set '!$B$39,('Villa Set '!Y23='Villa Set '!$B$40)))),'Villa Set '!Z23,"") -> Ellora HK Team | AA63: ='Villa Set '!BC23 -> 4 | AB63: =IF(AND('Villa Set '!CO23>0,(OR('Villa Set '!BK23='Villa Set '!$B$39,('Villa Set '!BK23='Villa Set '!$B$40)))),'Villa Set '!BL23,"") -> Makeup Room | AC63: ='Villa Set '!CO23 -> 87 | AD63: =IF(AND('Villa Set '!EA23>0,(OR('Villa Set '!CW23='Villa Set '!$B$39,('Villa Set '!CW23='Villa Set '!$B$40)))),'Villa Set '!CX23,"") | AE63: ='Villa Set '!EA23 -> 0 | AF63: Ellora Infra/Maintenance Others | AG63: ='Road Light'!J23-'Road Light'!R23 -> 50 | AH63: =IF(AND(Hill!AV23>0,(OR(Hill!R23=Hill!$B$39,(Hill!R23=Hill!$B$40)))),Hill!S23,"") | AI63: =Hill!AV23 -> 0
A64: 21 | B64: =IF(AND(Hospital!AV24>0,(OR(Hospital!R24=Hospital!$B$39,(Hospital!R24=Hospital!$B$40)))),Hospital!S24,"") -> Ellora HK Team | C64: =Hospital!AV24 -> 2 | D64: =IF(AND(Hospital!CH24>0,(OR(Hospital!BD24=Hospital!$B$39,(Hospital!BD24=Hospital!$B$40)))),Hospital!BE24,"") | E64: =Hospital!CH24 -> 0 | F64: =IF(AND('Bungalow 1'!AV24>0*(OR('Bungalow 1'!R24='Bungalow 1'!$B$39,('Bungalow 1'!R24='Bungalow 1'!$B$40)))),'Bungalow 1'!S24,"") | G64: ='Bungalow 1'!AV24 -> 0 | H64: =IF(AND('Bungalow 1'!CH24>0,(OR('Bungalow 1'!BD24='Bungalow 1'!$B$39,('Bungalow 1'!BD24='Bungalow 1'!$B$40)))),'Bungalow 1'!BE24,"") | I64: ='Bungalow 1'!CH24 -> 0 | J64: =IF(AND('Office Set'!AV23>0,(OR('Office Set'!R23='Office Set'!$B$38,('Office Set'!R23='Office Set'!$B$39)))),'Office Set'!S23,"") | K64: ='Office Set'!AV23 -> 0 | L64: =IF(AND('Police Station'!AV24>0,(OR('Police Station'!R24='Police Station'!$B$39,('Police Station'!R24='Police Station'!$B$40)))),'Police Station'!S24,"") | M64: ='Police Station'!AV24 -> 0 | N64: =IF(AND('8000 sqft'!AV24>0,(OR('8000 sqft'!R24='8000 sqft'!$B$39,('8000 sqft'!R24='8000 sqft'!$B$40)))),'8000 sqft'!S24,"") | O64: ='8000 sqft'!AV24 -> 0 | P64: =IF(AND('Restaurant '!AV24>0,(OR('Restaurant '!R24='Restaurant '!$B$39,('Restaurant '!R24='Restaurant '!$B$40)))),'Restaurant '!S24,"") | Q64: ='Restaurant '!AV24 -> 0 | R64: =IF(AND('Parsi Bungalow'!BC24>0,(OR('Parsi Bungalow'!Y24='Parsi Bungalow'!$B$39,('Parsi Bungalow'!Y24='Parsi Bungalow'!$B$40)))),'Parsi Bungalow'!Z24,"") | S64: ='Parsi Bungalow'!BC24 -> 0 | T64: =IF(AND('Parsi Bungalow'!CO24>0,(OR('Parsi Bungalow'!BK24='Parsi Bungalow'!$B$39,('Parsi Bungalow'!BK24='Parsi Bungalow'!$B$40)))),'Parsi Bungalow'!BL24,"") -> Ellora HK Team | U64: ='Parsi Bungalow'!CO24 -> 2 | V64: =IF(AND('Bungalow 2'!AV24>0,(OR('Bungalow 2'!R24='Bungalow 2'!$B$39,('Bungalow 2'!R24='Bungalow 2'!$B$40)))),'Bungalow 2'!S24,"") | W64: ='Bungalow 2'!AV24 -> 0 | X64: =IF(AND('Bungalow 2'!CH24>0,(OR('Bungalow 2'!BD24='Bungalow 2'!$B$39,('Bungalow 2'!BD24='Bungalow 2'!$B$40)))),'Bungalow 2'!BE24,"") -> Makeup Room | Y64: ='Bungalow 2'!CH24 -> 42 | Z64: =IF(AND('Villa Set '!BC24>0,(OR('Villa Set '!Y24='Villa Set '!$B$39,('Villa Set '!Y24='Villa Set '!$B$40)))),'Villa Set '!Z24,"") | AA64: ='Villa Set '!BC24 -> 0 | AB64: =IF(AND('Villa Set '!CO24>0,(OR('Villa Set '!BK24='Villa Set '!$B$39,('Villa Set '!BK24='Villa Set '!$B$40)))),'Villa Set '!BL24,"") | AC64: ='Villa Set '!CO24 -> 0 | AD64: =IF(AND('Villa Set '!EA24>0,(OR('Villa Set '!CW24='Villa Set '!$B$39,('Villa Set '!CW24='Villa Set '!$B$40)))),'Villa Set '!CX24,"") | AE64: ='Villa Set '!EA24 -> 0 | AF64: Ellora Infra/Maintenance Others | AG64: ='Road Light'!J24-'Road Light'!R24 -> 66 | AH64: =IF(AND(Hill!AV24>0,(OR(Hill!R24=Hill!$B$39,(Hill!R24=Hill!$B$40)))),Hill!S24,"") | AI64: =Hill!AV24 -> 0
A65: 22 | B65: =IF(AND(Hospital!AV25>0,(OR(Hospital!R25=Hospital!$B$39,(Hospital!R25=Hospital!$B$40)))),Hospital!S25,"") | C65: =Hospital!AV25 -> 0 | D65: =IF(AND(Hospital!CH25>0,(OR(Hospital!BD25=Hospital!$B$39,(Hospital!BD25=Hospital!$B$40)))),Hospital!BE25,"") | E65: =Hospital!CH25 -> 0 | F65: =IF(AND('Bungalow 1'!AV25>0*(OR('Bungalow 1'!R25='Bungalow 1'!$B$39,('Bungalow 1'!R25='Bungalow 1'!$B$40)))),'Bungalow 1'!S25,"") | G65: ='Bungalow 1'!AV25 -> 0 | H65: =IF(AND('Bungalow 1'!CH25>0,(OR('Bungalow 1'!BD25='Bungalow 1'!$B$39,('Bungalow 1'!BD25='Bungalow 1'!$B$40)))),'Bungalow 1'!BE25,"") | I65: ='Bungalow 1'!CH25 -> 0 | J65: =IF(AND('Office Set'!AV24>0,(OR('Office Set'!R24='Office Set'!$B$38,('Office Set'!R24='Office Set'!$B$39)))),'Office Set'!S24,"") -> Shooting | K65: ='Office Set'!AV24 -> 300 | L65: =IF(AND('Police Station'!AV25>0,(OR('Police Station'!R25='Police Station'!$B$39,('Police Station'!R25='Police Station'!$B$40)))),'Police Station'!S25,"") | M65: ='Police Station'!AV25 -> 0 | N65: =IF(AND('8000 sqft'!AV25>0,(OR('8000 sqft'!R25='8000 sqft'!$B$39,('8000 sqft'!R25='8000 sqft'!$B$40)))),'8000 sqft'!S25,"") -> Makeup Room | O65: ='8000 sqft'!AV25 -> 29 | P65: =IF(AND('Restaurant '!AV25>0,(OR('Restaurant '!R25='Restaurant '!$B$39,('Restaurant '!R25='Restaurant '!$B$40)))),'Restaurant '!S25,"") -> Makeup Room | Q65: ='Restaurant '!AV25 -> 46 | R65: =IF(AND('Parsi Bungalow'!BC25>0,(OR('Parsi Bungalow'!Y25='Parsi Bungalow'!$B$39,('Parsi Bungalow'!Y25='Parsi Bungalow'!$B$40)))),'Parsi Bungalow'!Z25,"") -> Ellora AC Team | S65: ='Parsi Bungalow'!BC25 -> 28 | T65: =IF(AND('Parsi Bungalow'!CO25>0,(OR('Parsi Bungalow'!BK25='Parsi Bungalow'!$B$39,('Parsi Bungalow'!BK25='Parsi Bungalow'!$B$40)))),'Parsi Bungalow'!BL25,"") -> Ellora HK Team | U65: ='Parsi Bungalow'!CO25 -> 68 | V65: =IF(AND('Bungalow 2'!AV25>0,(OR('Bungalow 2'!R25='Bungalow 2'!$B$39,('Bungalow 2'!R25='Bungalow 2'!$B$40)))),'Bungalow 2'!S25,"") | W65: ='Bungalow 2'!AV25 -> 0 | X65: =IF(AND('Bungalow 2'!CH25>0,(OR('Bungalow 2'!BD25='Bungalow 2'!$B$39,('Bungalow 2'!BD25='Bungalow 2'!$B$40)))),'Bungalow 2'!BE25,"") -> Makeup Room | Y65: ='Bungalow 2'!CH25 -> 153 | Z65: =IF(AND('Villa Set '!BC25>0,(OR('Villa Set '!Y25='Villa Set '!$B$39,('Villa Set '!Y25='Villa Set '!$B$40)))),'Villa Set '!Z25,"") | AA65: ='Villa Set '!BC25 -> 0 | AB65: =IF(AND('Villa Set '!CO25>0,(OR('Villa Set '!BK25='Villa Set '!$B$39,('Villa Set '!BK25='Villa Set '!$B$40)))),'Villa Set '!BL25,"") | AC65: ='Villa Set '!CO25 -> 0 | AD65: =IF(AND('Villa Set '!EA25>0,(OR('Villa Set '!CW25='Villa Set '!$B$39,('Villa Set '!CW25='Villa Set '!$B$40)))),'Villa Set '!CX25,"") | AE65: ='Villa Set '!EA25 -> 0 | AF65: Ellora Infra/Maintenance Others | AG65: ='Road Light'!J25-'Road Light'!R25 -> 75 | AH65: =IF(AND(Hill!AV25>0,(OR(Hill!R25=Hill!$B$39,(Hill!R25=Hill!$B$40)))),Hill!S25,"") | AI65: =Hill!AV25 -> 0
A66: 23 | B66: =IF(AND(Hospital!AV26>0,(OR(Hospital!R26=Hospital!$B$39,(Hospital!R26=Hospital!$B$40)))),Hospital!S26,"") -> Ellora HK Team | C66: =Hospital!AV26 -> 29 | D66: =IF(AND(Hospital!CH26>0,(OR(Hospital!BD26=Hospital!$B$39,(Hospital!BD26=Hospital!$B$40)))),Hospital!BE26,"") | E66: =Hospital!CH26 -> 0 | F66: =IF(AND('Bungalow 1'!AV26>0*(OR('Bungalow 1'!R26='Bungalow 1'!$B$39,('Bungalow 1'!R26='Bungalow 1'!$B$40)))),'Bungalow 1'!S26,"") | G66: ='Bungalow 1'!AV26 -> 0 | H66: =IF(AND('Bungalow 1'!CH26>0,(OR('Bungalow 1'!BD26='Bungalow 1'!$B$39,('Bungalow 1'!BD26='Bungalow 1'!$B$40)))),'Bungalow 1'!BE26,"") | I66: ='Bungalow 1'!CH26 -> 0 | J66: =IF(AND('Office Set'!AV25>0,(OR('Office Set'!R25='Office Set'!$B$38,('Office Set'!R25='Office Set'!$B$39)))),'Office Set'!S25,"") -> Shooting | K66: ='Office Set'!AV25 -> 300 | L66: =IF(AND('Police Station'!AV26>0,(OR('Police Station'!R26='Police Station'!$B$39,('Police Station'!R26='Police Station'!$B$40)))),'Police Station'!S26,"") | M66: ='Police Station'!AV26 -> 0 | N66: =IF(AND('8000 sqft'!AV26>0,(OR('8000 sqft'!R26='8000 sqft'!$B$39,('8000 sqft'!R26='8000 sqft'!$B$40)))),'8000 sqft'!S26,"") -> Makeup Room | O66: ='8000 sqft'!AV26 -> 8 | P66: =IF(AND('Restaurant '!AV26>0,(OR('Restaurant '!R26='Restaurant '!$B$39,('Restaurant '!R26='Restaurant '!$B$40)))),'Restaurant '!S26,"") -> Makeup Room | Q66: ='Restaurant '!AV26 -> 37 | R66: =IF(AND('Parsi Bungalow'!BC26>0,(OR('Parsi Bungalow'!Y26='Parsi Bungalow'!$B$39,('Parsi Bungalow'!Y26='Parsi Bungalow'!$B$40)))),'Parsi Bungalow'!Z26,"") | S66: ='Parsi Bungalow'!BC26 -> 0 | T66: =IF(AND('Parsi Bungalow'!CO26>0,(OR('Parsi Bungalow'!BK26='Parsi Bungalow'!$B$39,('Parsi Bungalow'!BK26='Parsi Bungalow'!$B$40)))),'Parsi Bungalow'!BL26,"") -> Ellora HK Team | U66: ='Parsi Bungalow'!CO26 -> 4 | V66: =IF(AND('Bungalow 2'!AV26>0,(OR('Bungalow 2'!R26='Bungalow 2'!$B$39,('Bungalow 2'!R26='Bungalow 2'!$B$40)))),'Bungalow 2'!S26,"") | W66: ='Bungalow 2'!AV26 -> 0 | X66: =IF(AND('Bungalow 2'!CH26>0,(OR('Bungalow 2'!BD26='Bungalow 2'!$B$39,('Bungalow 2'!BD26='Bungalow 2'!$B$40)))),'Bungalow 2'!BE26,"") -> Makeup Room | Y66: ='Bungalow 2'!CH26 -> 121 | Z66: =IF(AND('Villa Set '!BC26>0,(OR('Villa Set '!Y26='Villa Set '!$B$39,('Villa Set '!Y26='Villa Set '!$B$40)))),'Villa Set '!Z26,"") -> Ellora HK Team | AA66: ='Villa Set '!BC26 -> 9 | AB66: =IF(AND('Villa Set '!CO26>0,(OR('Villa Set '!BK26='Villa Set '!$B$39,('Villa Set '!BK26='Villa Set '!$B$40)))),'Villa Set '!BL26,"") | AC66: ='Villa Set '!CO26 -> 0 | AD66: =IF(AND('Villa Set '!EA26>0,(OR('Villa Set '!CW26='Villa Set '!$B$39,('Villa Set '!CW26='Villa Set '!$B$40)))),'Villa Set '!CX26,"") | AE66: ='Villa Set '!EA26 -> 0 | AF66: Ellora Infra/Maintenance Others | AG66: ='Road Light'!J26-'Road Light'!R26 -> 55 | AH66: =IF(AND(Hill!AV26>0,(OR(Hill!R26=Hill!$B$39,(Hill!R26=Hill!$B$40)))),Hill!S26,"") | AI66: =Hill!AV26 -> 0
A67: 24 | B67: =IF(AND(Hospital!AV27>0,(OR(Hospital!R27=Hospital!$B$39,(Hospital!R27=Hospital!$B$40)))),Hospital!S27,"") -> Ellora HK Team | C67: =Hospital!AV27 -> 21 | D67: =IF(AND(Hospital!CH27>0,(OR(Hospital!BD27=Hospital!$B$39,(Hospital!BD27=Hospital!$B$40)))),Hospital!BE27,"") | E67: =Hospital!CH27 -> 0 | F67: =IF(AND('Bungalow 1'!AV27>0*(OR('Bungalow 1'!R27='Bungalow 1'!$B$39,('Bungalow 1'!R27='Bungalow 1'!$B$40)))),'Bungalow 1'!S27,"") | G67: ='Bungalow 1'!AV27 -> 0 | H67: =IF(AND('Bungalow 1'!CH27>0,(OR('Bungalow 1'!BD27='Bungalow 1'!$B$39,('Bungalow 1'!BD27='Bungalow 1'!$B$40)))),'Bungalow 1'!BE27,"") | I67: ='Bungalow 1'!CH27 -> 0 | J67: =IF(AND('Office Set'!AV26>0,(OR('Office Set'!R26='Office Set'!$B$38,('Office Set'!R26='Office Set'!$B$39)))),'Office Set'!S26,"") -> Shooting | K67: ='Office Set'!AV26 -> 300 | L67: =IF(AND('Police Station'!AV27>0,(OR('Police Station'!R27='Police Station'!$B$39,('Police Station'!R27='Police Station'!$B$40)))),'Police Station'!S27,"") | M67: ='Police Station'!AV27 -> 0 | N67: =IF(AND('8000 sqft'!AV27>0,(OR('8000 sqft'!R27='8000 sqft'!$B$39,('8000 sqft'!R27='8000 sqft'!$B$40)))),'8000 sqft'!S27,"") -> Makeup Room | O67: ='8000 sqft'!AV27 -> 5 | P67: =IF(AND('Restaurant '!AV27>0,(OR('Restaurant '!R27='Restaurant '!$B$39,('Restaurant '!R27='Restaurant '!$B$40)))),'Restaurant '!S27,"") -> Makeup Room | Q67: ='Restaurant '!AV27 -> 30 | R67: =IF(AND('Parsi Bungalow'!BC27>0,(OR('Parsi Bungalow'!Y27='Parsi Bungalow'!$B$39,('Parsi Bungalow'!Y27='Parsi Bungalow'!$B$40)))),'Parsi Bungalow'!Z27,"") | S67: ='Parsi Bungalow'!BC27 -> 0 | T67: =IF(AND('Parsi Bungalow'!CO27>0,(OR('Parsi Bungalow'!BK27='Parsi Bungalow'!$B$39,('Parsi Bungalow'!BK27='Parsi Bungalow'!$B$40)))),'Parsi Bungalow'!BL27,"") -> Ellora HK Team | U67: ='Parsi Bungalow'!CO27 -> 2 | V67: =IF(AND('Bungalow 2'!AV27>0,(OR('Bungalow 2'!R27='Bungalow 2'!$B$39,('Bungalow 2'!R27='Bungalow 2'!$B$40)))),'Bungalow 2'!S27,"") | W67: ='Bungalow 2'!AV27 -> 0 | X67: =IF(AND('Bungalow 2'!CH27>0,(OR('Bungalow 2'!BD27='Bungalow 2'!$B$39,('Bungalow 2'!BD27='Bungalow 2'!$B$40)))),'Bungalow 2'!BE27,"") -> Makeup Room | Y67: ='Bungalow 2'!CH27 -> 124 | Z67: =IF(AND('Villa Set '!BC27>0,(OR('Villa Set '!Y27='Villa Set '!$B$39,('Villa Set '!Y27='Villa Set '!$B$40)))),'Villa Set '!Z27,"") | AA67: ='Villa Set '!BC27 -> 0 | AB67: =IF(AND('Villa Set '!CO27>0,(OR('Villa Set '!BK27='Villa Set '!$B$39,('Villa Set '!BK27='Villa Set '!$B$40)))),'Villa Set '!BL27,"") -> Makeup Room | AC67: ='Villa Set '!CO27 -> 27 | AD67: =IF(AND('Villa Set '!EA27>0,(OR('Villa Set '!CW27='Villa Set '!$B$39,('Villa Set '!CW27='Villa Set '!$B$40)))),'Villa Set '!CX27,"") | AE67: ='Villa Set '!EA27 -> 0 | AF67: Ellora Infra/Maintenance Others | AG67: ='Road Light'!J27-'Road Light'!R27 -> 59 | AH67: =IF(AND(Hill!AV27>0,(OR(Hill!R27=Hill!$B$39,(Hill!R27=Hill!$B$40)))),Hill!S27,"") | AI67: =Hill!AV27 -> 0
A68: 25 | B68: =IF(AND(Hospital!AV28>0,(OR(Hospital!R28=Hospital!$B$39,(Hospital!R28=Hospital!$B$40)))),Hospital!S28,"") -> Ellora HK Team | C68: =Hospital!AV28 -> 28 | D68: =IF(AND(Hospital!CH28>0,(OR(Hospital!BD28=Hospital!$B$39,(Hospital!BD28=Hospital!$B$40)))),Hospital!BE28,"") | E68: =Hospital!CH28 -> 0 | F68: =IF(AND('Bungalow 1'!AV28>0*(OR('Bungalow 1'!R28='Bungalow 1'!$B$39,('Bungalow 1'!R28='Bungalow 1'!$B$40)))),'Bungalow 1'!S28,"") | G68: ='Bungalow 1'!AV28 -> 0 | H68: =IF(AND('Bungalow 1'!CH28>0,(OR('Bungalow 1'!BD28='Bungalow 1'!$B$39,('Bungalow 1'!BD28='Bungalow 1'!$B$40)))),'Bungalow 1'!BE28,"") | I68: ='Bungalow 1'!CH28 -> 0 | J68: =IF(AND('Office Set'!AV27>0,(OR('Office Set'!R27='Office Set'!$B$38,('Office Set'!R27='Office Set'!$B$39)))),'Office Set'!S27,"") -> Shooting | K68: ='Office Set'!AV27 -> 300 | L68: =IF(AND('Police Station'!AV28>0,(OR('Police Station'!R28='Police Station'!$B$39,('Police Station'!R28='Police Station'!$B$40)))),'Police Station'!S28,"") | M68: ='Police Station'!AV28 -> 0 | N68: =IF(AND('8000 sqft'!AV28>0,(OR('8000 sqft'!R28='8000 sqft'!$B$39,('8000 sqft'!R28='8000 sqft'!$B$40)))),'8000 sqft'!S28,"") -> Makeup Room | O68: ='8000 sqft'!AV28 -> 9 | P68: =IF(AND('Restaurant '!AV28>0,(OR('Restaurant '!R28='Restaurant '!$B$39,('Restaurant '!R28='Restaurant '!$B$40)))),'Restaurant '!S28,"") -> Makeup Room | Q68: ='Restaurant '!AV28 -> 30 | R68: =IF(AND('Parsi Bungalow'!BC28>0,(OR('Parsi Bungalow'!Y28='Parsi Bungalow'!$B$39,('Parsi Bungalow'!Y28='Parsi Bungalow'!$B$40)))),'Parsi Bungalow'!Z28,"") -> Ellora AC Team | S68: ='Parsi Bungalow'!BC28 -> 25 | T68: =IF(AND('Parsi Bungalow'!CO28>0,(OR('Parsi Bungalow'!BK28='Parsi Bungalow'!$B$39,('Parsi Bungalow'!BK28='Parsi Bungalow'!$B$40)))),'Parsi Bungalow'!BL28,"") -> Ellora HK Team | U68: ='Parsi Bungalow'!CO28 -> 2 | V68: =IF(AND('Bungalow 2'!AV28>0,(OR('Bungalow 2'!R28='Bungalow 2'!$B$39,('Bungalow 2'!R28='Bungalow 2'!$B$40)))),'Bungalow 2'!S28,"") | W68: ='Bungalow 2'!AV28 -> 0 | X68: =IF(AND('Bungalow 2'!CH28>0,(OR('Bungalow 2'!BD28='Bungalow 2'!$B$39,('Bungalow 2'!BD28='Bungalow 2'!$B$40)))),'Bungalow 2'!BE28,"") -> Makeup Room | Y68: ='Bungalow 2'!CH28 -> 100 | Z68: =IF(AND('Villa Set '!BC28>0,(OR('Villa Set '!Y28='Villa Set '!$B$39,('Villa Set '!Y28='Villa Set '!$B$40)))),'Villa Set '!Z28,"") | AA68: ='Villa Set '!BC28 -> 0 | AB68: =IF(AND('Villa Set '!CO28>0,(OR('Villa Set '!BK28='Villa Set '!$B$39,('Villa Set '!BK28='Villa Set '!$B$40)))),'Villa Set '!BL28,"") -> Makeup Room | AC68: ='Villa Set '!CO28 -> 13 | AD68: =IF(AND('Villa Set '!EA28>0,(OR('Villa Set '!CW28='Villa Set '!$B$39,('Villa Set '!CW28='Villa Set '!$B$40)))),'Villa Set '!CX28,"") | AE68: ='Villa Set '!EA28 -> 0 | AF68: Ellora Infra/Maintenance Others | AG68: ='Road Light'!J28-'Road Light'!R28 -> 44 | AH68: =IF(AND(Hill!AV28>0,(OR(Hill!R28=Hill!$B$39,(Hill!R28=Hill!$B$40)))),Hill!S28,"") | AI68: =Hill!AV28 -> 0
A69: 26 | B69: =IF(AND(Hospital!AV29>0,(OR(Hospital!R29=Hospital!$B$39,(Hospital!R29=Hospital!$B$40)))),Hospital!S29,"") -> Ellora HK Team | C69: =Hospital!AV29 -> 25 | D69: =IF(AND(Hospital!CH29>0,(OR(Hospital!BD29=Hospital!$B$39,(Hospital!BD29=Hospital!$B$40)))),Hospital!BE29,"") | E69: =Hospital!CH29 -> 0 | F69: =IF(AND('Bungalow 1'!AV29>0*(OR('Bungalow 1'!R29='Bungalow 1'!$B$39,('Bungalow 1'!R29='Bungalow 1'!$B$40)))),'Bungalow 1'!S29,"") | G69: ='Bungalow 1'!AV29 -> 0 | H69: =IF(AND('Bungalow 1'!CH29>0,(OR('Bungalow 1'!BD29='Bungalow 1'!$B$39,('Bungalow 1'!BD29='Bungalow 1'!$B$40)))),'Bungalow 1'!BE29,"") | I69: ='Bungalow 1'!CH29 -> 0 | J69: =IF(AND('Office Set'!AV28>0,(OR('Office Set'!R28='Office Set'!$B$38,('Office Set'!R28='Office Set'!$B$39)))),'Office Set'!S28,"") | K69: ='Office Set'!AV28 -> 0 | L69: =IF(AND('Police Station'!AV29>0,(OR('Police Station'!R29='Police Station'!$B$39,('Police Station'!R29='Police Station'!$B$40)))),'Police Station'!S29,"") | M69: ='Police Station'!AV29 -> 0 | N69: =IF(AND('8000 sqft'!AV29>0,(OR('8000 sqft'!R29='8000 sqft'!$B$39,('8000 sqft'!R29='8000 sqft'!$B$40)))),'8000 sqft'!S29,"") -> Makeup Room | O69: ='8000 sqft'!AV29 -> 6 | P69: =IF(AND('Restaurant '!AV29>0,(OR('Restaurant '!R29='Restaurant '!$B$39,('Restaurant '!R29='Restaurant '!$B$40)))),'Restaurant '!S29,"") -> Makeup Room | Q69: ='Restaurant '!AV29 -> 3 | R69: =IF(AND('Parsi Bungalow'!BC29>0,(OR('Parsi Bungalow'!Y29='Parsi Bungalow'!$B$39,('Parsi Bungalow'!Y29='Parsi Bungalow'!$B$40)))),'Parsi Bungalow'!Z29,"") | S69: ='Parsi Bungalow'!BC29 -> 0 | T69: =IF(AND('Parsi Bungalow'!CO29>0,(OR('Parsi Bungalow'!BK29='Parsi Bungalow'!$B$39,('Parsi Bungalow'!BK29='Parsi Bungalow'!$B$40)))),'Parsi Bungalow'!BL29,"") -> Ellora HK Team | U69: ='Parsi Bungalow'!CO29 -> 4 | V69: =IF(AND('Bungalow 2'!AV29>0,(OR('Bungalow 2'!R29='Bungalow 2'!$B$39,('Bungalow 2'!R29='Bungalow 2'!$B$40)))),'Bungalow 2'!S29,"") | W69: ='Bungalow 2'!AV29 -> 0 | X69: =IF(AND('Bungalow 2'!CH29>0,(OR('Bungalow 2'!BD29='Bungalow 2'!$B$39,('Bungalow 2'!BD29='Bungalow 2'!$B$40)))),'Bungalow 2'!BE29,"") -> Makeup Room | Y69: ='Bungalow 2'!CH29 -> 43 | Z69: =IF(AND('Villa Set '!BC29>0,(OR('Villa Set '!Y29='Villa Set '!$B$39,('Villa Set '!Y29='Villa Set '!$B$40)))),'Villa Set '!Z29,"") | AA69: ='Villa Set '!BC29 -> 0 | AB69: =IF(AND('Villa Set '!CO29>0,(OR('Villa Set '!BK29='Villa Set '!$B$39,('Villa Set '!BK29='Villa Set '!$B$40)))),'Villa Set '!BL29,"") -> Makeup Room | AC69: ='Villa Set '!CO29 -> 44 | AD69: =IF(AND('Villa Set '!EA29>0,(OR('Villa Set '!CW29='Villa Set '!$B$39,('Villa Set '!CW29='Villa Set '!$B$40)))),'Villa Set '!CX29,"") | AE69: ='Villa Set '!EA29 -> 0 | AF69: Ellora Infra/Maintenance Others | AG69: ='Road Light'!J29-'Road Light'!R29 -> 58 | AH69: =IF(AND(Hill!AV29>0,(OR(Hill!R29=Hill!$B$39,(Hill!R29=Hill!$B$40)))),Hill!S29,"") | AI69: =Hill!AV29 -> 0
A70: 27 | B70: =IF(AND(Hospital!AV30>0,(OR(Hospital!R30=Hospital!$B$39,(Hospital!R30=Hospital!$B$40)))),Hospital!S30,"") | C70: =Hospital!AV30 -> 0 | D70: =IF(AND(Hospital!CH30>0,(OR(Hospital!BD30=Hospital!$B$39,(Hospital!BD30=Hospital!$B$40)))),Hospital!BE30,"") | E70: =Hospital!CH30 -> 0 | F70: =IF(AND('Bungalow 1'!AV30>0*(OR('Bungalow 1'!R30='Bungalow 1'!$B$39,('Bungalow 1'!R30='Bungalow 1'!$B$40)))),'Bungalow 1'!S30,"") -> Shooting | G70: ='Bungalow 1'!AV30 -> 300 | H70: =IF(AND('Bungalow 1'!CH30>0,(OR('Bungalow 1'!BD30='Bungalow 1'!$B$39,('Bungalow 1'!BD30='Bungalow 1'!$B$40)))),'Bungalow 1'!BE30,"") | I70: ='Bungalow 1'!CH30 -> 0 | J70: =IF(AND('Office Set'!AV29>0,(OR('Office Set'!R29='Office Set'!$B$38,('Office Set'!R29='Office Set'!$B$39)))),'Office Set'!S29,"") -> Shooting | K70: ='Office Set'!AV29 -> 300 | L70: =IF(AND('Police Station'!AV30>0,(OR('Police Station'!R30='Police Station'!$B$39,('Police Station'!R30='Police Station'!$B$40)))),'Police Station'!S30,"") | M70: ='Police Station'!AV30 -> 0 | N70: =IF(AND('8000 sqft'!AV30>0,(OR('8000 sqft'!R30='8000 sqft'!$B$39,('8000 sqft'!R30='8000 sqft'!$B$40)))),'8000 sqft'!S30,"") -> Makeup Room | O70: ='8000 sqft'!AV30 -> 7 | P70: =IF(AND('Restaurant '!AV30>0,(OR('Restaurant '!R30='Restaurant '!$B$39,('Restaurant '!R30='Restaurant '!$B$40)))),'Restaurant '!S30,"") -> Shooting | Q70: ='Restaurant '!AV30 -> 150 | R70: =IF(AND('Parsi Bungalow'!BC30>0,(OR('Parsi Bungalow'!Y30='Parsi Bungalow'!$B$39,('Parsi Bungalow'!Y30='Parsi Bungalow'!$B$40)))),'Parsi Bungalow'!Z30,"") | S70: ='Parsi Bungalow'!BC30 -> 0 | T70: =IF(AND('Parsi Bungalow'!CO30>0,(OR('Parsi Bungalow'!BK30='Parsi Bungalow'!$B$39,('Parsi Bungalow'!BK30='Parsi Bungalow'!$B$40)))),'Parsi Bungalow'!BL30,"") -> Ellora HK Team | U70: ='Parsi Bungalow'!CO30 -> 1 | V70: =IF(AND('Bungalow 2'!AV30>0,(OR('Bungalow 2'!R30='Bungalow 2'!$B$39,('Bungalow 2'!R30='Bungalow 2'!$B$40)))),'Bungalow 2'!S30,"") -> Ellora HK Team | W70: ='Bungalow 2'!AV30 -> 3 | X70: =IF(AND('Bungalow 2'!CH30>0,(OR('Bungalow 2'!BD30='Bungalow 2'!$B$39,('Bungalow 2'!BD30='Bungalow 2'!$B$40)))),'Bungalow 2'!BE30,"") -> Makeup Room | Y70: ='Bungalow 2'!CH30 -> 59 | Z70: =IF(AND('Villa Set '!BC30>0,(OR('Villa Set '!Y30='Villa Set '!$B$39,('Villa Set '!Y30='Villa Set '!$B$40)))),'Villa Set '!Z30,"") | AA70: ='Villa Set '!BC30 -> 0 | AB70: =IF(AND('Villa Set '!CO30>0,(OR('Villa Set '!BK30='Villa Set '!$B$39,('Villa Set '!BK30='Villa Set '!$B$40)))),'Villa Set '!BL30,"") -> Makeup Room | AC70: ='Villa Set '!CO30 -> 28 | AD70: =IF(AND('Villa Set '!EA30>0,(OR('Villa Set '!CW30='Villa Set '!$B$39,('Villa Set '!CW30='Villa Set '!$B$40)))),'Villa Set '!CX30,"") | AE70: ='Villa Set '!EA30 -> 0 | AF70: Ellora Infra/Maintenance Others | AG70: ='Road Light'!J30-'Road Light'!R30 -> 83 | AH70: =IF(AND(Hill!AV30>0,(OR(Hill!R30=Hill!$B$39,(Hill!R30=Hill!$B$40)))),Hill!S30,"") | AI70: =Hill!AV30 -> 0
A71: 28 | B71: =IF(AND(Hospital!AV31>0,(OR(Hospital!R31=Hospital!$B$39,(Hospital!R31=Hospital!$B$40)))),Hospital!S31,"") -> Ellora HK Team | C71: =Hospital!AV31 -> 2 | D71: =IF(AND(Hospital!CH31>0,(OR(Hospital!BD31=Hospital!$B$39,(Hospital!BD31=Hospital!$B$40)))),Hospital!BE31,"") -> Shooting | E71: =Hospital!CH31 -> 9 | F71: =IF(AND('Bungalow 1'!AV31>0*(OR('Bungalow 1'!R31='Bungalow 1'!$B$39,('Bungalow 1'!R31='Bungalow 1'!$B$40)))),'Bungalow 1'!S31,"") | G71: ='Bungalow 1'!AV31 -> 0 | H71: =IF(AND('Bungalow 1'!CH31>0,(OR('Bungalow 1'!BD31='Bungalow 1'!$B$39,('Bungalow 1'!BD31='Bungalow 1'!$B$40)))),'Bungalow 1'!BE31,"") | I71: ='Bungalow 1'!CH31 -> 0 | J71: =IF(AND('Office Set'!AV30>0,(OR('Office Set'!R30='Office Set'!$B$38,('Office Set'!R30='Office Set'!$B$39)))),'Office Set'!S30,"") -> Shooting | K71: ='Office Set'!AV30 -> 300 | L71: =IF(AND('Police Station'!AV31>0,(OR('Police Station'!R31='Police Station'!$B$39,('Police Station'!R31='Police Station'!$B$40)))),'Police Station'!S31,"") | M71: ='Police Station'!AV31 -> 0 | N71: =IF(AND('8000 sqft'!AV31>0,(OR('8000 sqft'!R31='8000 sqft'!$B$39,('8000 sqft'!R31='8000 sqft'!$B$40)))),'8000 sqft'!S31,"") | O71: ='8000 sqft'!AV31 -> 0 | P71: =IF(AND('Restaurant '!AV31>0,(OR('Restaurant '!R31='Restaurant '!$B$39,('Restaurant '!R31='Restaurant '!$B$40)))),'Restaurant '!S31,"") | Q71: ='Restaurant '!AV31 -> 0 | R71: =IF(AND('Parsi Bungalow'!BC31>0,(OR('Parsi Bungalow'!Y31='Parsi Bungalow'!$B$39,('Parsi Bungalow'!Y31='Parsi Bungalow'!$B$40)))),'Parsi Bungalow'!Z31,"") | S71: ='Parsi Bungalow'!BC31 -> 0 | T71: =IF(AND('Parsi Bungalow'!CO31>0,(OR('Parsi Bungalow'!BK31='Parsi Bungalow'!$B$39,('Parsi Bungalow'!BK31='Parsi Bungalow'!$B$40)))),'Parsi Bungalow'!BL31,"") -> Ellora HK Team | U71: ='Parsi Bungalow'!CO31 -> 6 | V71: =IF(AND('Bungalow 2'!AV31>0,(OR('Bungalow 2'!R31='Bungalow 2'!$B$39,('Bungalow 2'!R31='Bungalow 2'!$B$40)))),'Bungalow 2'!S31,"") | W71: ='Bungalow 2'!AV31 -> 0 | X71: =IF(AND('Bungalow 2'!CH31>0,(OR('Bungalow 2'!BD31='Bungalow 2'!$B$39,('Bungalow 2'!BD31='Bungalow 2'!$B$40)))),'Bungalow 2'!BE31,"") -> Makeup Room | Y71: ='Bungalow 2'!CH31 -> 82 | Z71: =IF(AND('Villa Set '!BC31>0,(OR('Villa Set '!Y31='Villa Set '!$B$39,('Villa Set '!Y31='Villa Set '!$B$40)))),'Villa Set '!Z31,"") -> Ellora HK Team | AA71: ='Villa Set '!BC31 -> 2 | AB71: =IF(AND('Villa Set '!CO31>0,(OR('Villa Set '!BK31='Villa Set '!$B$39,('Villa Set '!BK31='Villa Set '!$B$40)))),'Villa Set '!BL31,"") -> Makeup Room | AC71: ='Villa Set '!CO31 -> 33 | AD71: =IF(AND('Villa Set '!EA31>0,(OR('Villa Set '!CW31='Villa Set '!$B$39,('Villa Set '!CW31='Villa Set '!$B$40)))),'Villa Set '!CX31,"") | AE71: ='Villa Set '!EA31 -> 0 | AF71: Ellora Infra/Maintenance Others | AG71: ='Road Light'!J31-'Road Light'!R31 -> 44 | AH71: =IF(AND(Hill!AV31>0,(OR(Hill!R31=Hill!$B$39,(Hill!R31=Hill!$B$40)))),Hill!S31,"") | AI71: =Hill!AV31 -> 0
A72: 29 | B72: =IF(AND(Hospital!AV32>0,(OR(Hospital!R32=Hospital!$B$39,(Hospital!R32=Hospital!$B$40)))),Hospital!S32,"") -> Ellora HK Team | C72: =Hospital!AV32 -> 2 | D72: =IF(AND(Hospital!CH32>0,(OR(Hospital!BD32=Hospital!$B$39,(Hospital!BD32=Hospital!$B$40)))),Hospital!BE32,"") -> Ellora HK Team | E72: =Hospital!CH32 -> 3 | F72: =IF(AND('Bungalow 1'!AV32>0*(OR('Bungalow 1'!R32='Bungalow 1'!$B$39,('Bungalow 1'!R32='Bungalow 1'!$B$40)))),'Bungalow 1'!S32,"") -> Shooting | G72: ='Bungalow 1'!AV32 -> 266 | H72: =IF(AND('Bungalow 1'!CH32>0,(OR('Bungalow 1'!BD32='Bungalow 1'!$B$39,('Bungalow 1'!BD32='Bungalow 1'!$B$40)))),'Bungalow 1'!BE32,"") | I72: ='Bungalow 1'!CH32 -> 0 | J72: =IF(AND('Office Set'!AV31>0,(OR('Office Set'!R31='Office Set'!$B$38,('Office Set'!R31='Office Set'!$B$39)))),'Office Set'!S31,"") -> Ellora AC Team | K72: ='Office Set'!AV31 -> 79 | L72: =IF(AND('Police Station'!AV32>0,(OR('Police Station'!R32='Police Station'!$B$39,('Police Station'!R32='Police Station'!$B$40)))),'Police Station'!S32,"") | M72: ='Police Station'!AV32 -> 0 | N72: =IF(AND('8000 sqft'!AV32>0,(OR('8000 sqft'!R32='8000 sqft'!$B$39,('8000 sqft'!R32='8000 sqft'!$B$40)))),'8000 sqft'!S32,"") -> Makeup Room | O72: ='8000 sqft'!AV32 -> 10 | P72: =IF(AND('Restaurant '!AV32>0,(OR('Restaurant '!R32='Restaurant '!$B$39,('Restaurant '!R32='Restaurant '!$B$40)))),'Restaurant '!S32,"") -> Makeup Room | Q72: ='Restaurant '!AV32 -> 64 | R72: =IF(AND('Parsi Bungalow'!BC32>0,(OR('Parsi Bungalow'!Y32='Parsi Bungalow'!$B$39,('Parsi Bungalow'!Y32='Parsi Bungalow'!$B$40)))),'Parsi Bungalow'!Z32,"") | S72: ='Parsi Bungalow'!BC32 -> 0 | T72: =IF(AND('Parsi Bungalow'!CO32>0,(OR('Parsi Bungalow'!BK32='Parsi Bungalow'!$B$39,('Parsi Bungalow'!BK32='Parsi Bungalow'!$B$40)))),'Parsi Bungalow'!BL32,"") -> Ellora HK Team | U72: ='Parsi Bungalow'!CO32 -> 2 | V72: =IF(AND('Bungalow 2'!AV32>0,(OR('Bungalow 2'!R32='Bungalow 2'!$B$39,('Bungalow 2'!R32='Bungalow 2'!$B$40)))),'Bungalow 2'!S32,"") -> Ellora HK Team | W72: ='Bungalow 2'!AV32 -> 1 | X72: =IF(AND('Bungalow 2'!CH32>0,(OR('Bungalow 2'!BD32='Bungalow 2'!$B$39,('Bungalow 2'!BD32='Bungalow 2'!$B$40)))),'Bungalow 2'!BE32,"") -> Makeup Room | Y72: ='Bungalow 2'!CH32 -> 56 | Z72: =IF(AND('Villa Set '!BC32>0,(OR('Villa Set '!Y32='Villa Set '!$B$39,('Villa Set '!Y32='Villa Set '!$B$40)))),'Villa Set '!Z32,"") | AA72: ='Villa Set '!BC32 -> 0 | AB72: =IF(AND('Villa Set '!CO32>0,(OR('Villa Set '!BK32='Villa Set '!$B$39,('Villa Set '!BK32='Villa Set '!$B$40)))),'Villa Set '!BL32,"") -> Makeup Room | AC72: ='Villa Set '!CO32 -> 25 | AD72: =IF(AND('Villa Set '!EA32>0,(OR('Villa Set '!CW32='Villa Set '!$B$39,('Villa Set '!CW32='Villa Set '!$B$40)))),'Villa Set '!CX32,"") | AE72: ='Villa Set '!EA32 -> 0 | AF72: Ellora Infra/Maintenance Others | AG72: ='Road Light'!J32-'Road Light'!R32 -> 58 | AH72: =IF(AND(Hill!AV32>0,(OR(Hill!R32=Hill!$B$39,(Hill!R32=Hill!$B$40)))),Hill!S32,"") | AI72: =Hill!AV32 -> 0
A73: 30 | B73: =IF(AND(Hospital!AV33>0,(OR(Hospital!R33=Hospital!$B$39,(Hospital!R33=Hospital!$B$40)))),Hospital!S33,"") -> Ellora HK Team | C73: =Hospital!AV33 -> 5 | D73: =IF(AND(Hospital!CH33>0,(OR(Hospital!BD33=Hospital!$B$39,(Hospital!BD33=Hospital!$B$40)))),Hospital!BE33,"") | E73: =Hospital!CH33 -> 0 | F73: =IF(AND('Bungalow 1'!AV33>0*(OR('Bungalow 1'!R33='Bungalow 1'!$B$39,('Bungalow 1'!R33='Bungalow 1'!$B$40)))),'Bungalow 1'!S33,"") -> Ellora HK Team | G73: ='Bungalow 1'!AV33 -> 2 | H73: =IF(AND('Bungalow 1'!CH33>0,(OR('Bungalow 1'!BD33='Bungalow 1'!$B$39,('Bungalow 1'!BD33='Bungalow 1'!$B$40)))),'Bungalow 1'!BE33,"") | I73: ='Bungalow 1'!CH33 -> 0 | J73: =IF(AND('Office Set'!AV32>0,(OR('Office Set'!R32='Office Set'!$B$38,('Office Set'!R32='Office Set'!$B$39)))),'Office Set'!S32,"") -> Ellora HK Team | K73: ='Office Set'!AV32 -> 5 | L73: =IF(AND('Police Station'!AV33>0,(OR('Police Station'!R33='Police Station'!$B$39,('Police Station'!R33='Police Station'!$B$40)))),'Police Station'!S33,"") | M73: ='Police Station'!AV33 -> 0 | N73: =IF(AND('8000 sqft'!AV33>0,(OR('8000 sqft'!R33='8000 sqft'!$B$39,('8000 sqft'!R33='8000 sqft'!$B$40)))),'8000 sqft'!S33,"") -> Makeup Room | O73: ='8000 sqft'!AV33 -> 8 | P73: =IF(AND('Restaurant '!AV33>0,(OR('Restaurant '!R33='Restaurant '!$B$39,('Restaurant '!R33='Restaurant '!$B$40)))),'Restaurant '!S33,"") -> Makeup Room | Q73: ='Restaurant '!AV33 -> 7 | R73: =IF(AND('Parsi Bungalow'!BC33>0,(OR('Parsi Bungalow'!Y33='Parsi Bungalow'!$B$39,('Parsi Bungalow'!Y33='Parsi Bungalow'!$B$40)))),'Parsi Bungalow'!Z33,"") -> Ellora AC Team | S73: ='Parsi Bungalow'!BC33 -> 26 | T73: =IF(AND('Parsi Bungalow'!CO33>0,(OR('Parsi Bungalow'!BK33='Parsi Bungalow'!$B$39,('Parsi Bungalow'!BK33='Parsi Bungalow'!$B$40)))),'Parsi Bungalow'!BL33,"") -> Ellora HK Team | U73: ='Parsi Bungalow'!CO33 -> 7 | V73: =IF(AND('Bungalow 2'!AV33>0,(OR('Bungalow 2'!R33='Bungalow 2'!$B$39,('Bungalow 2'!R33='Bungalow 2'!$B$40)))),'Bungalow 2'!S33,"") | W73: ='Bungalow 2'!AV33 -> 0 | X73: =IF(AND('Bungalow 2'!CH33>0,(OR('Bungalow 2'!BD33='Bungalow 2'!$B$39,('Bungalow 2'!BD33='Bungalow 2'!$B$40)))),'Bungalow 2'!BE33,"") -> Makeup Room | Y73: ='Bungalow 2'!CH33 -> 74 | Z73: =IF(AND('Villa Set '!BC33>0,(OR('Villa Set '!Y33='Villa Set '!$B$39,('Villa Set '!Y33='Villa Set '!$B$40)))),'Villa Set '!Z33,"") | AA73: ='Villa Set '!BC33 -> 0 | AB73: =IF(AND('Villa Set '!CO33>0,(OR('Villa Set '!BK33='Villa Set '!$B$39,('Villa Set '!BK33='Villa Set '!$B$40)))),'Villa Set '!BL33,"") -> Makeup Room | AC73: ='Villa Set '!CO33 -> 32 | AD73: =IF(AND('Villa Set '!EA33>0,(OR('Villa Set '!CW33='Villa Set '!$B$39,('Villa Set '!CW33='Villa Set '!$B$40)))),'Villa Set '!CX33,"") | AE73: ='Villa Set '!EA33 -> 0 | AF73: Ellora Infra/Maintenance Others | AG73: ='Road Light'!J33-'Road Light'!R33 -> 37 | AH73: =IF(AND(Hill!AV33>0,(OR(Hill!R33=Hill!$B$39,(Hill!R33=Hill!$B$40)))),Hill!S33,"") | AI73: =Hill!AV33 -> 0
A74: 31 | B74: =IF(AND(Hospital!AV34>0,(OR(Hospital!R34=Hospital!$B$39,(Hospital!R34=Hospital!$B$40)))),Hospital!S34,"") | C74: =Hospital!AV34 -> 0 | D74: =IF(AND(Hospital!CH34>0,(OR(Hospital!BD34=Hospital!$B$39,(Hospital!BD34=Hospital!$B$40)))),Hospital!BE34,"") | E74: =Hospital!CH34 -> 0 | F74: =IF(AND('Bungalow 1'!AV34>0*(OR('Bungalow 1'!R34='Bungalow 1'!$B$39,('Bungalow 1'!R34='Bungalow 1'!$B$40)))),'Bungalow 1'!S34,"") | G74: ='Bungalow 1'!AV34 -> 0 | H74: =IF(AND('Bungalow 1'!CH34>0,(OR('Bungalow 1'!BD34='Bungalow 1'!$B$39,('Bungalow 1'!BD34='Bungalow 1'!$B$40)))),'Bungalow 1'!BE34,"") | I74: ='Bungalow 1'!CH34 -> 0 | J74: =IF(AND('Office Set'!AV33>0,(OR('Office Set'!R33='Office Set'!$B$38,('Office Set'!R33='Office Set'!$B$39)))),'Office Set'!S33,"") | K74: ='Office Set'!AV33 -> 0 | L74: =IF(AND('Police Station'!AV34>0,(OR('Police Station'!R34='Police Station'!$B$39,('Police Station'!R34='Police Station'!$B$40)))),'Police Station'!S34,"") | M74: ='Police Station'!AV34 -> 0 | N74: =IF(AND('8000 sqft'!AV34>0,(OR('8000 sqft'!R34='8000 sqft'!$B$39,('8000 sqft'!R34='8000 sqft'!$B$40)))),'8000 sqft'!S34,"") | O74: ='8000 sqft'!AV34 -> 0 | P74: =IF(AND('Restaurant '!AV34>0,(OR('Restaurant '!R34='Restaurant '!$B$39,('Restaurant '!R34='Restaurant '!$B$40)))),'Restaurant '!S34,"") | Q74: ='Restaurant '!AV34 -> 0 | R74: =IF(AND('Parsi Bungalow'!BC34>0,(OR('Parsi Bungalow'!Y34='Parsi Bungalow'!$B$39,('Parsi Bungalow'!Y34='Parsi Bungalow'!$B$40)))),'Parsi Bungalow'!Z34,"") | S74: ='Parsi Bungalow'!BC34 -> 0 | T74: =IF(AND('Parsi Bungalow'!CO34>0,(OR('Parsi Bungalow'!BK34='Parsi Bungalow'!$B$39,('Parsi Bungalow'!BK34='Parsi Bungalow'!$B$40)))),'Parsi Bungalow'!BL34,"") | U74: ='Parsi Bungalow'!CO34 -> -1568 | V74: =IF(AND('Bungalow 2'!AV34>0,(OR('Bungalow 2'!R34='Bungalow 2'!$B$39,('Bungalow 2'!R34='Bungalow 2'!$B$40)))),'Bungalow 2'!S34,"") | W74: ='Bungalow 2'!AV34 -> 0 | X74: =IF(AND('Bungalow 2'!CH34>0,(OR('Bungalow 2'!BD34='Bungalow 2'!$B$39,('Bungalow 2'!BD34='Bungalow 2'!$B$40)))),'Bungalow 2'!BE34,"") | Y74: ='Bungalow 2'!CH34 -> -3053 | Z74: =IF(AND('Villa Set '!BC34>0,(OR('Villa Set '!Y34='Villa Set '!$B$39,('Villa Set '!Y34='Villa Set '!$B$40)))),'Villa Set '!Z34,"") | AA74: ='Villa Set '!BC34 -> 0 | AB74: =IF(AND('Villa Set '!CO34>0,(OR('Villa Set '!BK34='Villa Set '!$B$39,('Villa Set '!BK34='Villa Set '!$B$40)))),'Villa Set '!BL34,"") | AC74: ='Villa Set '!CO34 -> 0 | AD74: =IF(AND('Villa Set '!EA34>0,(OR('Villa Set '!CW34='Villa Set '!$B$39,('Villa Set '!CW34='Villa Set '!$B$40)))),'Villa Set '!CX34,"") | AE74: ='Villa Set '!EA34 -> 0 | AF74: Ellora Infra/Maintenance Others | AG74: 0 | AH74: =IF(AND(Hill!AV34>0,(OR(Hill!R34=Hill!$B$39,(Hill!R34=Hill!$B$40)))),Hill!S34,"") | AI74: =Hill!AV34 -> 0
A75: 1. Total Unit Consumption of Above Meter As Per Details | C75: =SUM(C44:C74) -> 861 | E75: =SUM(E44:E74) -> 14 | G75: =SUM(G44:G74) -> 881 | I75: =SUM(I44:I74) -> 12 | K75: =SUM(K44:K74) -> 2815 | M75: =SUM(M44:M74) -> 0 | O75: =SUM(O44:O74) -> 251 | Q75: =SUM(Q44:Q74) -> 562 | S75: =SUM(S44:S74) -> 140 | U75: =SUM(U44:U74) -> -1408 | W75: =SUM(W44:W74) -> 620 | Y75: =SUM(Y44:Y74) -> -1111 | AA75: =SUM(AA44:AA74) -> 32 | AC75: =SUM(AC44:AC74) -> 375 | AE75: =SUM(AE44:AE74) -> 0 | AG75: =SUM(AG44:AG74) -> 1735 | AI75: =SUM(AI44:AI74) -> 0
A76: 2. Total Unit Consumption of Above Meter As per Sheet Details. | C76: =Hospital!AV35 -> 861 | E76: =Hospital!CH35 -> 14 | G76: ='Bungalow 1'!AV35 -> 881 | I76: ='Bungalow 1'!CH35 -> 12 | K76: ='Office Set'!AV34 -> 2815 | M76: ='Police Station'!AV35 -> 0 | O76: ='8000 sqft'!AV35 -> 251 | Q76: ='Restaurant '!AV35 -> 562 | S76: ='Parsi Bungalow'!BC35 -> 140 | U76: ='Parsi Bungalow'!CO35 -> 160 | W76: ='Bungalow 2'!AV35 -> 620 | Y76: ='Bungalow 2'!CH35 -> 1942 | AA76: ='Villa Set '!BC35 -> 32 | AC76: ='Villa Set '!CO35 -> 375 | AE76: ='Villa Set '!EA35 -> 0 | AG76: ='Road Light'!C5 -> 1735 | AI76: =Hill!AJ74 -> 0
A77: Variation between 1 and 2 (Ideally it should be Zero) | C77: =C75-C76 -> 0 | E77: =E75-E76 -> 0 | G77: =G75-G76 -> 0 | I77: =I75-I76 -> 0 | K77: =K75-K76 -> 0 | M77: =M75-M76 -> 0 | O77: =O75-O76 -> 0 | Q77: =Q75-Q76 -> 0 | S77: =S75-S76 -> 0 | U77: =U75-U76 -> -1568 | W77: =W75-W76 -> 0 | Y77: =Y75-Y76 -> -3053 | AA77: =AA75-AA76 -> 0 | AC77: =AC75-AC76 -> 0 | AE77: =AE75-AE76 -> 0 | AG77: =AG75-AG76 -> 0 | AI77: =Hill!AV35 -> 0
C78: 3024
C79: =C78-C36 -> 861

Sheet Sheet1
A1: Meter | B1: Total Reading
A2: A | B2: Daily Breakup | C2: From | D2: To | E2: Units
A3: B | B3: Usage Type | C3: From | D3: To | E3: Units | F3: Shooting - Party | G3: Shooting - Free
B4: Makeup Room | C4: From | D4: To | E4: Units

Sheet Mains Power Unit Detials
A2: Month - Nov 2020 | E2: Meter Name - Main LT Incomer Panel Energy Meter at Main LT Panel | L2: Meter Name - Main LT PanelRelaince/Adani LT Energy Meter at Main LT Panel | S2: Meter Name - Capacitor Bank Energy Meter at Capacitor Panel
A3: Sr.no. | B3: Details | C3: Unit | E3: Day | F3: Opening Reading | G3: Closing Reading | H3: Consumption | I3: MF value | J3: Unit | L3: Day | M3: Opening Reading | N3: Closing Reading | O3: Consumption | P3: MF value | Q3: Unit | S3: Day | T3: Opening Reading | U3: Closing Reading | V3: Consumption | W3: MF value | X3: Unit
A4: 1 | B4: Monthly Unit Billing as per Power Supply Agency Bill | C4: 45360 | E4: 1 | F4: 739271 | G4: 739487 | H4: =G4-F4 -> 216 | I4: 10 | J4: =I4*H4 -> 2160 | L4: 1 | M4: 18488.3 | N4: 18493.7 | O4: =N4-M4 -> 5.4 | P4: 400 | Q4: =P4*O4 -> 2160 | S4: 1 | T4: 2016 | U4: 2016.7 | V4: =U4-T4 -> 0.7 | W4: 60 | X4: =W4*V4 -> 42
A5: 2 | B5: Monthly Unit Consumption as per Ellora Main LT Panel Incomer Energy Meter | C5: =J35 -> 42010 | E5: 2 | F5: =G4 -> 739487 | G5: 739629 | H5: =G5-F5 -> 142 | I5: 10 | J5: =I5*H5 -> 1420 | L5: 2 | M5: =N4 -> 18493.7 | N5: 18497.2 | O5: =N5-M5 -> 3.5 | P5: 400 | Q5: =P5*O5 -> 1400 | S5: 2 | T5: =U4 -> 2016.7 | U5: 2017.2 | V5: =U5-T5 -> 0.5 | W5: 60 | X5: =W5*V5 -> 30
A6: 3 | B6: Monthly Unit Consumption as per Ellora Main LT Panel Reliance Energy Meter | C6: =Q35 -> 41880 | E6: 3 | F6: =G5 -> 739629 | G6: 739646 | H6: =G6-F6 -> 17 | I6: 10 | J6: =I6*H6 -> 170 | L6: 3 | M6: =N5 -> 18497.2 | N6: 18500.1 | O6: =N6-M6 -> 2.9 | P6: 400 | Q6: =P6*O6 -> 1160 | S6: 3 | T6: =U5 -> 2017.2 | U6: 2017.3 | V6: =U6-T6 -> 0.1 | W6: 60 | X6: =W6*V6 -> 6
A7: 4 | B7: Monthly Unit Consumption by Capacitor Bank Panel | C7: =X35 -> 1278 | E7: 4 | F7: =G6 -> 739646 | G7: 739783 | H7: =G7-F7 -> 137 | I7: 10 | J7: =I7*H7 -> 1370 | L7: 4 | M7: =N6 -> 18500.1 | N7: 18501.1 | O7: =N7-M7 -> 1 | P7: 400 | Q7: =P7*O7 -> 400 | S7: 4 | T7: =U6 -> 2017.3 | U7: 2017.3 | V7: =U7-T7 -> 0 | W7: 60 | X7: =W7*V7 -> 0
A8: 5 | B8: Difference between Adani and Ellora Main Incomer | C8: =C4-C5 -> 3350 | E8: 5 | F8: =G7 -> 739783 | G8: 739963 | H8: =G8-F8 -> 180 | I8: 10 | J8: =I8*H8 -> 1800 | L8: 5 | M8: =N7 -> 18501.1 | N8: 18505.5 | O8: =N8-M8 -> 4.4 | P8: 400 | Q8: =P8*O8 -> 1760 | S8: 5 | T8: =U7 -> 2017.3 | U8: 2017.7 | V8: =U8-T8 -> 0.4 | W8: 60 | X8: =W8*V8 -> 24
A9: 6 | B9: Difference between Relaince LT Meter and Ellora Main LT Energy Meter | C9: =C6-C5 -> -130 | E9: 6 | F9: =G8 -> 739963 | G9: 740199 | H9: =G9-F9 -> 236 | I9: 10 | J9: =I9*H9 -> 2360 | L9: 6 | M9: =N8 -> 18505.5 | N9: 18511.4 | O9: =N9-M9 -> 5.9 | P9: 400 | Q9: =P9*O9 -> 2360 | S9: 6 | T9: =U8 -> 2017.7 | U9: 2018.1 | V9: =U9-T9 -> 0.4 | W9: 60 | X9: =W9*V9 -> 24
E10: 7 | F10: =G9 -> 740199 | G10: 740263 | H10: =G10-F10 -> 64 | I10: 10 | J10: =I10*H10 -> 640 | L10: 7 | M10: =N9 -> 18511.4 | N10: 18513 | O10: =N10-M10 -> 1.6 | P10: 400 | Q10: =P10*O10 -> 640 | S10: 7 | T10: =U9 -> 2018.1 | U10: 2018.1 | V10: =U10-T10 -> 0 | W10: 60 | X10: =W10*V10 -> 0
E11: 8 | F11: =G10 -> 740263 | G11: 740452 | H11: =G11-F11 -> 189 | I11: 10 | J11: =I11*H11 -> 1890 | L11: 8 | M11: =N10 -> 18513 | N11: 18517.7 | O11: =N11-M11 -> 4.7 | P11: 400 | Q11: =P11*O11 -> 1880 | S11: 8 | T11: =U10 -> 2018.1 | U11: 2018.4 | V11: =U11-T11 -> 0.3 | W11: 60 | X11: =W11*V11 -> 18
E12: 9 | F12: =G11 -> 740452 | G12: 740486 | H12: =G12-F12 -> 34 | I12: 10 | J12: =I12*H12 -> 340 | L12: 9 | M12: =N11 -> 18517.7 | N12: 18518.8 | O12: =N12-M12 -> 1.1 | P12: 400 | Q12: =P12*O12 -> 440 | S12: 9 | T12: =U11 -> 2018.4 | U12: 2018.4 | V12: =U12-T12 -> 0 | W12: 60 | X12: =W12*V12 -> 0
E13: 10 | F13: =G12 -> 740486 | G13: 740569 | H13: =G13-F13 -> 83 | I13: 10 | J13: =I13*H13 -> 830 | L13: 10 | M13: =N12 -> 18518.8 | N13: 18520.6 | O13: =N13-M13 -> 1.8 | P13: 400 | Q13: =P13*O13 -> 720 | S13: 10 | T13: =U12 -> 2018.4 | U13: 2018.5 | V13: =U13-T13 -> 0.1 | W13: 60 | X13: =W13*V13 -> 6
E14: 11 | F14: =G13 -> 740569 | G14: 740689 | H14: =G14-F14 -> 120 | I14: 10 | J14: =I14*H14 -> 1200 | L14: 11 | M14: =N13 -> 18520.6 | N14: 18523.6 | O14: =N14-M14 -> 3 | P14: 400 | Q14: =P14*O14 -> 1200 | S14: 11 | T14: =U13 -> 2018.5 | U14: 2019.5 | V14: =U14-T14 -> 1 | W14: 60 | X14: =W14*V14 -> 60
E15: 12 | F15: =G14 -> 740689 | G15: 740822 | H15: =G15-F15 -> 133 | I15: 10 | J15: =I15*H15 -> 1330 | L15: 12 | M15: =N14 -> 18523.6 | N15: 18526.9 | O15: =N15-M15 -> 3.3 | P15: 400 | Q15: =P15*O15 -> 1320 | S15: 12 | T15: =U14 -> 2019.5 | U15: 2020.7 | V15: =U15-T15 -> 1.2 | W15: 60 | X15: =W15*V15 -> 72
E16: 13 | F16: =G15 -> 740822 | G16: 740857 | H16: =G16-F16 -> 35 | I16: 10 | J16: =I16*H16 -> 350 | L16: 13 | M16: =N15 -> 18526.9 | N16: 18527.8 | O16: =N16-M16 -> 0.9 | P16: 400 | Q16: =P16*O16 -> 360 | S16: 13 | T16: =U15 -> 2020.7 | U16: 2020.7 | V16: =U16-T16 -> 0 | W16: 60 | X16: =W16*V16 -> 0
E17: 14 | F17: =G16 -> 740857 | G17: 740874 | H17: =G17-F17 -> 17 | I17: 10 | J17: =I17*H17 -> 170 | L17: 14 | M17: =N16 -> 18527.8 | N17: 18528.3 | O17: =N17-M17 -> 0.5 | P17: 400 | Q17: =P17*O17 -> 200 | S17: 14 | T17: =U16 -> 2020.7 | U17: 2020.7 | V17: =U17-T17 -> 0 | W17: 60 | X17: =W17*V17 -> 0
E18: 15 | F18: =G17 -> 740874 | G18: 741062 | H18: =G18-F18 -> 188 | I18: 10 | J18: =I18*H18 -> 1880 | L18: 15 | M18: =N17 -> 18528.3 | N18: 18533 | O18: =N18-M18 -> 4.7 | P18: 400 | Q18: =P18*O18 -> 1880 | S18: 15 | T18: =U17 -> 2020.7 | U18: 2020.7 | V18: =U18-T18 -> 0 | W18: 60 | X18: =W18*V18 -> 0
E19: 16 | F19: =G18 -> 741062 | G19: 741264 | H19: =G19-F19 -> 202 | I19: 10 | J19: =I19*H19 -> 2020 | L19: 16 | M19: =N18 -> 18533 | N19: 18538 | O19: =N19-M19 -> 5 | P19: 400 | Q19: =P19*O19 -> 2000 | S19: 16 | T19: =U18 -> 2020.7 | U19: 2024.2 | V19: =U19-T19 -> 3.5 | W19: 60 | X19: =W19*V19 -> 210
E20: 17 | F20: =G19 -> 741264 | G20: 741444 | H20: =G20-F20 -> 180 | I20: 10 | J20: =I20*H20 -> 1800 | L20: 17 | M20: =N19 -> 18538 | N20: 18542.5 | O20: =N20-M20 -> 4.5 | P20: 400 | Q20: =P20*O20 -> 1800 | S20: 17 | T20: =U19 -> 2024.2 | U20: 2025.7 | V20: =U20-T20 -> 1.5 | W20: 60 | X20: =W20*V20 -> 90
E21: 18 | F21: =G20 -> 741444 | G21: 741608 | H21: =G21-F21 -> 164 | I21: 10 | J21: =I21*H21 -> 1640 | L21: 18 | M21: =N20 -> 18542.5 | N21: 18546.6 | O21: =N21-M21 -> 4.1 | P21: 400 | Q21: =P21*O21 -> 1640 | S21: 18 | T21: =U20 -> 2025.7 | U21: 2026.9 | V21: =U21-T21 -> 1.2 | W21: 60 | X21: =W21*V21 -> 72
... E33: 30 | F33: =G32 -> 743428 | G33: 743472 | H33: =G33-F33 -> 44 | I33: 10 | J33: =I33*H33 -> 440 | L33: 30 | M33: =N32 -> 18591.9 | N33: 18593 | O33: =N33-M33 -> 1.1 | P33: 400 | Q33: =P33*O33 -> 440 | S33: 30 | T33: =U32 -> 2037.3 | U33: 2037.3 | V33: =U33-T33 -> 0 | W33: 60 | X33: =W33*V33 -> 0
E34: 31 | F34: =G33 -> 743472 | H34: =G34-F34 -> -743472 | I34: 10 | J34: =I34*H34 -> -7434720 | L34: 31 | M34: =N33 -> 18593 | O34: =N34-M34 -> -18593 | P34: 400 | Q34: =P34*O34 -> -7437200 | S34: 31 | T34: =U33 -> 2037.3 | V34: =U34-T34 -> -2037.3 | W34: 60 | X34: =W34*V34 -> -122238
E35: Monthly Total Unit Consumption | J35: =SUM(J4:J33) -> 42010 | L35: Monthly Total Unit Consumption | Q35: =SUM(Q4:Q33) -> 41880 | S35: Monthly Total Unit Consumption | X35: =SUM(X4:X33) -> 1278

Sheet Summary
A1: Month - Nov 2020
A2: Sr.no. | B2: Details | G2: Unit | H2: Remarks
A3: 1 | B3: Actual Billing Unit Readings by Power supply Agency(Adani). | G3: ='Mains Power Unit Detials'!C4 -> 45360 | H3: Manual Entry | I3: Bill Master > Monthly Reading
A4: 2 | B4: Monthly Unit Consumption as per Ellora Main LT Panel Incomer Energy Meter. | G4: ='Mains Power Unit Detials'!C5 -> 42010 | H4: LT Panel Entry
A5: 3 | B5: Monthly Total unit consumption at Main LT panel all O/P Energy Meter. | G5: =Hospital!C4+'Bungalow 1'!C4+'Office Set'!C3+'Police Station'!C4+'Restaurant '!C4+'Villa Set '!C4+'Villa Set '!C5+'Parsi Bungalow'!C4+'Parsi Bungalow'!C5+'Bungalow 2'!C4+'Road Light'!C4+'8000 sqft'!C4 -> 43559
A6: 3 | B6: Monthly Total Unit consumption of all Location Energy meter. | G6: =Hospital!C13+'Bungalow 1'!C7+'Office Set'!C4+'Police Station'!C5+'8000 sqft'!C5+'Restaurant '!C5+'Parsi Bungalow'!C6+'Parsi Bungalow'!C7+'Bungalow 2'!C7+'Villa Set '!C6+'Villa Set '!C7+'Villa Set '!C8+'Road Light'!C4+Hill!C4 -> 41355 | H6: Entry
A7: 4 | B7: Variation Between 1 and 2 (Adani Reading and LT Panel Reading) | G7: =G3-G4 -> 3350 | H7: CALCULATION
A8: 5 | B8: Variation Between 2 and 3 (LT Panel Reading and Location Meter Reading) | G8: =G4-G6 -> 655 | H8: CALCULATION
A9: 6 | B9: Variation Between 2 and 4. [Difference between Main LT I/P meters with all Location (Panel) Meters] | G9: =G4-G6 -> 655 | H9: CALCULATION
A10: 6 | B10: Monthly total Billing unit to Customer. | G10: =V84 -> 28395 | H10: From Location Meter - ENTRY
A11: 7 | B11: Monthly total Billing unit to Ellora For Shooting. | G11: =Z110 -> 4882 | H11: From Location Meter - FREE Entry
A12: 8 | B12: Monthly total Billing unit to Ellora For Makeup Room. | G12: =E102 -> 3072 | H12: From Location Meter - Entry
A13: 9 | B13: Monthly total Billing unit to Ellora For Infra. | G13: =SUM(L117:S117) -> 3925 | H13: From Location Meter - Entry
B15: Sr.no. | C15: Users Details | F15: Billing Unit | V15: Total
F16: Hospital LT | G16: Hospital Out Door | H16: Bungalow 1 LT Panel | I16: Bungalow 1 Out Door Area | J16: Office Set LT Panel | K16: Police Station | L16: 8000 Sqft | M16: Restaurant | N16: Parsi AC | O16: Parsi Light | P16: Bungalow 2 LT | Q16: Villa AC | R16: Villa Light | S16: Villa ODU | T16: Raod Light | U16: Hill
B17: 1 | C17: Balaji Telefilms Ltd | F17: =SUMIF('Meterwise Billing Details'!$B$4:$B$35,Summary!C17,('Meterwise Billing Details'!$C$4:$C$35)) -> 0 | G17: =SUMIF('Meterwise Billing Details'!$D$5:$D$35,Summary!$C17,('Meterwise Billing Details'!$E$5:$E$35)) -> 0 | H17: =SUMIF('Meterwise Billing Details'!$F$5:$F$35,Summary!$C17,('Meterwise Billing Details'!$G$5:$G$35)) -> 0 | I17: =SUMIF('Meterwise Billing Details'!$H$5:$H$35,Summary!$C17,('Meterwise Billing Details'!$I$5:$I$35)) -> 0 | J17: =SUMIF('Meterwise Billing Details'!$J$5:$J$35,Summary!$C17,('Meterwise Billing Details'!$K$5:$K$35)) -> 0 | K17: =SUMIF('Meterwise Billing Details'!$L$5:$L$35,Summary!$C17,('Meterwise Billing Details'!$M$5:$M$35)) -> 73 | L17: =SUMIF('Meterwise Billing Details'!$N$5:$N$35,Summary!$C17,('Meterwise Billing Details'!$O$5:$O$35)) -> 0 | M17: =SUMIF('Meterwise Billing Details'!$P$5:$P$35,Summary!$C17,('Meterwise Billing Details'!$Q$5:$Q$35)) -> 0 | N17: =SUMIF('Meterwise Billing Details'!$R$5:$R$35,Summary!$C17,('Meterwise Billing Details'!$S$5:$S$35)) -> 0 | O17: =SUMIF('Meterwise Billing Details'!$T$5:$T$35,Summary!$C17,('Meterwise Billing Details'!$U$5:$U$35)) -> 0 | P17: =SUMIF('Meterwise Billing Details'!$V$5:$V$35,Summary!$C17,('Meterwise Billing Details'!$W$5:$W$35)) -> 0 | Q17: =SUMIF('Meterwise Billing Details'!$Z$5:$Z$35,Summary!$C17,('Meterwise Billing Details'!$AA$5:$AA$35)) -> 0 | R17: =SUMIF('Meterwise Billing Details'!$AB$5:$AB$35,Summary!$C17,('Meterwise Billing Details'!$AC$5:$AC$35)) -> 0 | S17: =SUMIF('Meterwise Billing Details'!$AD$5:$AD$35,Summary!$C17,('Meterwise Billing Details'!$AE$5:$AE$35)) -> 0 | T17: =SUMIF('Meterwise Billing Details'!$AF$5:$AF$35,Summary!$C17,('Meterwise Billing Details'!$AG$5:$AG$35)) -> 0 | U17: =SUMIF('Meterwise Billing Details'!$AH$5:$AH$35,Summary!$C17,('Meterwise Billing Details'!$AI$5:$AI$35)) -> 0 | V17: =SUM(F17:U17) -> 73
B18: 2 | C18: Bambai Dreams Entertainment (Opc) Private Limited | F18: =SUMIF('Meterwise Billing Details'!$B$5:$B$35,Summary!C18,('Meterwise Billing Details'!$C$5:$C$35)) -> 368 | G18: =SUMIF('Meterwise Billing Details'!$D$5:$D$35,Summary!$C18,('Meterwise Billing Details'!$E$5:$E$35)) -> 0 | H18: =SUMIF('Meterwise Billing Details'!$F$5:$F$35,Summary!$C18,('Meterwise Billing Details'!$G$5:$G$35)) -> 0 | I18: =SUMIF('Meterwise Billing Details'!$H$5:$H$35,Summary!$C18,('Meterwise Billing Details'!$I$5:$I$35)) -> 0 | J18: =SUMIF('Meterwise Billing Details'!$J$5:$J$35,Summary!$C18,('Meterwise Billing Details'!$K$5:$K$35)) -> 0 | K18: =SUMIF('Meterwise Billing Details'!$L$5:$L$35,Summary!$C18,('Meterwise Billing Details'!$M$5:$M$35)) -> 0 | L18: =SUMIF('Meterwise Billing Details'!$N$5:$N$35,Summary!$C18,('Meterwise Billing Details'!$O$5:$O$35)) -> 0 | M18: =SUMIF('Meterwise Billing Details'!$P$5:$P$35,Summary!$C18,('Meterwise Billing Details'!$Q$5:$Q$35)) -> 0 | N18: =SUMIF('Meterwise Billing Details'!$R$5:$R$35,Summary!$C18,('Meterwise Billing Details'!$S$5:$S$35)) -> 0 | O18: =SUMIF('Meterwise Billing Details'!$T$5:$T$35,Summary!$C18,('Meterwise Billing Details'!$U$5:$U$35)) -> 0 | P18: =SUMIF('Meterwise Billing Details'!$V$5:$V$35,Summary!$C18,('Meterwise Billing Details'!$W$5:$W$35)) -> 0 | Q18: =SUMIF('Meterwise Billing Details'!$Z$5:$Z$35,Summary!$C18,('Meterwise Billing Details'!$AA$5:$AA$35)) -> 0 | R18: =SUMIF('Meterwise Billing Details'!$AB$5:$AB$35,Summary!$C18,('Meterwise Billing Details'!$AC$5:$AC$35)) -> 0 | S18: =SUMIF('Meterwise Billing Details'!$AD$5:$AD$35,Summary!$C18,('Meterwise Billing Details'!$AE$5:$AE$35)) -> 0 | T18: =SUMIF('Meterwise Billing Details'!$AF$5:$AF$35,Summary!$C18,('Meterwise Billing Details'!$AG$5:$AG$35)) -> 0 | U18: =SUMIF('Meterwise Billing Details'!$AH$5:$AH$35,Summary!$C18,('Meterwise Billing Details'!$AI$5:$AI$35)) -> 0 | V18: =SUM(F18:U18) -> 368
B19: 3 | C19: Boathouse Media Private Limited | D19: Collective Art Private Limited | E19: Collective Art Private Limited | F19: =SUMIF('Meterwise Billing Details'!$B$5:$B$35,Summary!C19,('Meterwise Billing Details'!$C$5:$C$35)) -> 0 | G19: =SUMIF('Meterwise Billing Details'!$D$5:$D$35,Summary!$C19,('Meterwise Billing Details'!$E$5:$E$35)) -> 0 | H19: =SUMIF('Meterwise Billing Details'!$F$5:$F$35,Summary!$C19,('Meterwise Billing Details'!$G$5:$G$35)) -> 620 | I19: =SUMIF('Meterwise Billing Details'!$H$5:$H$35,Summary!$C19,('Meterwise Billing Details'!$I$5:$I$35)) -> 0 | J19: =SUMIF('Meterwise Billing Details'!$J$5:$J$35,Summary!$C19,('Meterwise Billing Details'!$K$5:$K$35)) -> 0 | K19: =SUMIF('Meterwise Billing Details'!$L$5:$L$35,Summary!$C19,('Meterwise Billing Details'!$M$5:$M$35)) -> 0 | L19: =SUMIF('Meterwise Billing Details'!$N$5:$N$35,Summary!$C19,('Meterwise Billing Details'!$O$5:$O$35)) -> 0 | M19: =SUMIF('Meterwise Billing Details'!$P$5:$P$35,Summary!$C19,('Meterwise Billing Details'!$Q$5:$Q$35)) -> 0 | N19: =SUMIF('Meterwise Billing Details'!$R$5:$R$35,Summary!$C19,('Meterwise Billing Details'!$S$5:$S$35)) -> 0 | O19: =SUMIF('Meterwise Billing Details'!$T$5:$T$35,Summary!$C19,('Meterwise Billing Details'!$U$5:$U$35)) -> 0 | P19: =SUMIF('Meterwise Billing Details'!$V$5:$V$35,Summary!$C19,('Meterwise Billing Details'!$W$5:$W$35)) -> 0 | Q19: =SUMIF('Meterwise Billing Details'!$Z$5:$Z$35,Summary!$C19,('Meterwise Billing Details'!$AA$5:$AA$35)) -> 0 | R19: =SUMIF('Meterwise Billing Details'!$AB$5:$AB$35,Summary!$C19,('Meterwise Billing Details'!$AC$5:$AC$35)) -> 0 | S19: =SUMIF('Meterwise Billing Details'!$AD$5:$AD$35,Summary!$C19,('Meterwise Billing Details'!$AE$5:$AE$35)) -> 0 | T19: =SUMIF('Meterwise Billing Details'!$AF$5:$AF$35,Summary!$C19,('Meterwise Billing Details'!$AG$5:$AG$35)) -> 0 | U19: =SUMIF('Meterwise Billing Details'!$AH$5:$AH$35,Summary!$C19,('Meterwise Billing Details'!$AI$5:$AI$35)) -> 0 | V19: =SUM(F19:U19) -> 620
B20: 4 | C20: Classic Films | F20: =SUMIF('Meterwise Billing Details'!$B$5:$B$35,Summary!C20,('Meterwise Billing Details'!$C$5:$C$35)) -> 0 | G20: =SUMIF('Meterwise Billing Details'!$D$5:$D$35,Summary!$C20,('Meterwise Billing Details'!$E$5:$E$35)) -> 0 | H20: =SUMIF('Meterwise Billing Details'!$F$5:$F$35,Summary!$C20,('Meterwise Billing Details'!$G$5:$G$35)) -> 692 | I20: =SUMIF('Meterwise Billing Details'!$H$5:$H$35,Summary!$C20,('Meterwise Billing Details'!$I$5:$I$35)) -> 0 | J20: =SUMIF('Meterwise Billing Details'!$J$5:$J$35,Summary!$C20,('Meterwise Billing Details'!$K$5:$K$35)) -> 0 | K20: =SUMIF('Meterwise Billing Details'!$L$5:$L$35,Summary!$C20,('Meterwise Billing Details'!$M$5:$M$35)) -> 0 | L20: =SUMIF('Meterwise Billing Details'!$N$5:$N$35,Summary!$C20,('Meterwise Billing Details'!$O$5:$O$35)) -> 0 | M20: =SUMIF('Meterwise Billing Details'!$P$5:$P$35,Summary!$C20,('Meterwise Billing Details'!$Q$5:$Q$35)) -> 0 | N20: =SUMIF('Meterwise Billing Details'!$R$5:$R$35,Summary!$C20,('Meterwise Billing Details'!$S$5:$S$35)) -> 0 | O20: =SUMIF('Meterwise Billing Details'!$T$5:$T$35,Summary!$C20,('Meterwise Billing Details'!$U$5:$U$35)) -> 0 | P20: =SUMIF('Meterwise Billing Details'!$V$5:$V$35,Summary!$C20,('Meterwise Billing Details'!$W$5:$W$35)) -> 1954 | Q20: =SUMIF('Meterwise Billing Details'!$Z$5:$Z$35,Summary!$C20,('Meterwise Billing Details'!$AA$5:$AA$35)) -> 0 | R20: =SUMIF('Meterwise Billing Details'!$AB$5:$AB$35,Summary!$C20,('Meterwise Billing Details'!$AC$5:$AC$35)) -> 0 | S20: =SUMIF('Meterwise Billing Details'!$AD$5:$AD$35,Summary!$C20,('Meterwise Billing Details'!$AE$5:$AE$35)) -> 0 | T20: =SUMIF('Meterwise Billing Details'!$AF$5:$AF$35,Summary!$C20,('Meterwise Billing Details'!$AG$5:$AG$35)) -> 0 | U20: =SUMIF('Meterwise Billing Details'!$AH$5:$AH$35,Summary!$C20,('Meterwise Billing Details'!$AI$5:$AI$35)) -> 0 | V20: =SUM(F20:U20) -> 2646
B21: 5 | C21: Contiloe Pictures Pvt Ltd | F21: =SUMIF('Meterwise Billing Details'!$B$5:$B$35,Summary!C21,('Meterwise Billing Details'!$C$5:$C$35)) -> 0 | G21: =SUMIF('Meterwise Billing Details'!$D$5:$D$35,Summary!$C21,('Meterwise Billing Details'!$E$5:$E$35)) -> 0 | H21: =SUMIF('Meterwise Billing Details'!$F$5:$F$35,Summary!$C21,('Meterwise Billing Details'!$G$5:$G$35)) -> 0 | I21: =SUMIF('Meterwise Billing Details'!$H$5:$H$35,Summary!$C21,('Meterwise Billing Details'!$I$5:$I$35)) -> 0 | J21: =SUMIF('Meterwise Billing Details'!$J$5:$J$35,Summary!$C21,('Meterwise Billing Details'!$K$5:$K$35)) -> 0 | K21: =SUMIF('Meterwise Billing Details'!$L$5:$L$35,Summary!$C21,('Meterwise Billing Details'!$M$5:$M$35)) -> 0 | L21: =SUMIF('Meterwise Billing Details'!$N$5:$N$35,Summary!$C21,('Meterwise Billing Details'!$O$5:$O$35)) -> 0 | M21: =SUMIF('Meterwise Billing Details'!$P$5:$P$35,Summary!$C21,('Meterwise Billing Details'!$Q$5:$Q$35)) -> 0 | N21: =SUMIF('Meterwise Billing Details'!$R$5:$R$35,Summary!$C21,('Meterwise Billing Details'!$S$5:$S$35)) -> 0 | O21: =SUMIF('Meterwise Billing Details'!$T$5:$T$35,Summary!$C21,('Meterwise Billing Details'!$U$5:$U$35)) -> 0 | P21: =SUMIF('Meterwise Billing Details'!$V$5:$V$35,Summary!$C21,('Meterwise Billing Details'!$W$5:$W$35)) -> 0 | Q21: =SUMIF('Meterwise Billing Details'!$Z$5:$Z$35,Summary!$C21,('Meterwise Billing Details'!$AA$5:$AA$35)) -> 0 | R21: =SUMIF('Meterwise Billing Details'!$AB$5:$AB$35,Summary!$C21,('Meterwise Billing Details'!$AC$5:$AC$35)) -> 0 | S21: =SUMIF('Meterwise Billing Details'!$AD$5:$AD$35,Summary!$C21,('Meterwise Billing Details'!$AE$5:$AE$35)) -> 0 | T21: =SUMIF('Meterwise Billing Details'!$AF$5:$AF$35,Summary!$C21,('Meterwise Billing Details'!$AG$5:$AG$35)) -> 0 | U21: =SUMIF('Meterwise Billing Details'!$AH$5:$AH$35,Summary!$C21,('Meterwise Billing Details'!$AI$5:$AI$35)) -> 0 | V21: =SUM(F21:U21) -> 0
